Workbook
Name ___xlnm.Print_Titles: Audit!$1:$1
Name __xlnm.Print_Titles: Audit!$A$1:$AB$1
Name Tableau1: Audit!$A$1:$D$440
Name Tableau2: Audit!$A$1:$L$440
Name Tableau3: Config!$A$10:$B$15
Name Tableau4: Config!$D$10:$D$11
Name Tableau5: 'Fiche Audit AOCR 26022018'!$A$1:$T$1401

Sheet Audit
A1: id | B1: Domaine | C1: Sous-domaine | D1: Obligation | E1: Libellé détaillé | F1: Référence | G1: Obligatoire | H1: Avis | I1: Possible réalisateur | J1: Personne obligée | K1: Localisation | L1: Commentaire | M1: Habitation | N1: Travail | O1: ERP/IGH | P1: Modification | Q1: ID Domaine | R1: ID Domaine2 | S1: Colonne1 | T1: Urgence | U1: Validité | V1: Affectation | W1: Hors Contrat | Y1: Dom | Z1: Sdom | AA1: Insert | AB1: Update | AC1: Update Réglementation
A2: 3701 | B2: Accessoire de levage | C2: Carnet de maintenance | D2: Carnet de maintenance de l''accessoire de levage tenu à disposition de l''inspecteur du travail et des organismes des représentants du personnel. | F2: Arrêté du 01/03/2004 Arrêté du 02/03/2004 CDT Art R4323-19 à 4323-21 | H2: Satisfaisant | I2: Personne qualifiée | M2: 1 | N2: 1 | O2: 1 | P2: 0 | Q2: =#REF! -> #REF! | R2: =#REF! -> #REF! | T2: 4 | V2: Propriétaire | Y2: =VLOOKUP(A6,Feuil1!A:B,2,FALSE) -> 421 | Z2: =VLOOKUP(A6,Feuil1!A:C,3,FALSE) -> 524 | AA2: =CONCATENATE("insert into AOCR_ref_arbo (libelle,reglementation,typologie,pere,commentaires,personne_habilitee,type_cont,pere_superieur,criticite) values ('",Tableau6[[#This Row],[Obligation]],"','",Tableau6[[#This Row],[Référence]],"',1,",Tableau6[[#This Row],[ID Domaine2]],",'",Tableau6[[#This Row],[Libellé détaillé]],"','",Tableau6[[#This Row],[Possible réalisateur]],"',3,",Tableau6[[#This Row],[ID Domaine]],",",Tableau6[[#This Row],[Urgence]],")") -> #REF! | AB2: =CONCATENATE("update aocr_ref_arbo set libelle = '",Tableau6[[#This Row],[Obligation]],"', reglementation = '",Tableau6[[#This Row],[Référence]],"', commentaires = '",Tableau6[[#This Row],[Libellé détaillé]],"', personne_habilitee = '",Tableau6[[#This Row],[Possible réalisateur]],"', criticite = ",Tableau6[[#This Row],[Urgence]]," where id = ",Tableau6[[#This Row],[id]]) -> update aocr_ref_arbo set libelle = 'Carnet de maintenance de l''accessoire de levage tenu à disposition de l''inspecteur du travail et des organismes des représentants du personnel.', reglementation = 'Arrêté du 01/03/2004 Arrêté du 02/03/2004 CDT Art R4323-19 à 4323-21', commentaires = '', personne_habilitee = 'Personne qualifiée', criticite = 4 where id = 3701 | AC2: =IF(Tableau6[[#This Row],[Référence]]<>"",CONCATENATE("update aocr_ref_arbo set reglementation = '",Tableau6[[#This Row],[Référence]],"' where id = ",Tableau6[[#This Row],[id]]),"") -> update aocr_ref_arbo set reglementation = 'Arrêté du 01/03/2004 Arrêté du 02/03/2004 CDT Art R4323-19 à 4323-21' where id = 3701
A3: 1906 | B3: Accessoire de levage | C3: Certificat CE | D3: Accessoire de levage CE : Certificat CE pour les équipements postérieurs au 1er Janvier 1993. | F3: Décret n° 93-40 du 11 janvier 1993 relatif aux prescriptions techniques applicables à l''utilisation des équipements de travail soumis à l''article L 233-5-1 du code du travail, aux règles techniques applicables aux matériels d''occasion soumis à l''article L 233-5 du même code et à la mise en conformité des équipements existants et modifiant le code du travail (deuxième partie : Décrets en Conseil d''Etat).; Arrêté du 1er mars 2004 relatif aux vérifications des appareils et accessoires de levage Article 3 | H3: Sans Objet | I3: Fabricant | M3: 1 | N3: 1 | O3: 1 | P3: 0 | Q3: =#REF! -> #REF! | R3: =#REF! -> #REF! | S3: 1 | T3: 5 | V3: Propriétaire | Y3: =VLOOKUP(A7,Feuil1!A:B,2,FALSE) -> 421 | Z3: =VLOOKUP(A7,Feuil1!A:C,3,FALSE) -> 524 | AA3: =CONCATENATE("insert into AOCR_ref_arbo (libelle,reglementation,typologie,pere,commentaires,personne_habilitee,type_cont,pere_superieur,criticite) values ('",Tableau6[[#This Row],[Obligation]],"','",Tableau6[[#This Row],[Référence]],"',1,",Tableau6[[#This Row],[ID Domaine2]],",'",Tableau6[[#This Row],[Libellé détaillé]],"','",Tableau6[[#This Row],[Possible réalisateur]],"',3,",Tableau6[[#This Row],[ID Domaine]],",",Tableau6[[#This Row],[Urgence]],")") -> #REF! | AB3: =CONCATENATE("update aocr_ref_arbo set libelle = '",Tableau6[[#This Row],[Obligation]],"', reglementation = '",Tableau6[[#This Row],[Référence]],"', commentaires = '",Tableau6[[#This Row],[Libellé détaillé]],"', personne_habilitee = '",Tableau6[[#This Row],[Possible réalisateur]],"', criticite = ",Tableau6[[#This Row],[Urgence]]," where id = ",Tableau6[[#This Row],[id]]) -> update aocr_ref_arbo set libelle = 'Accessoire de levage CE : Certificat CE pour les équipements postérieurs au 1er Janvier 1993.', reglementation = 'Décret n° 93-40 du 11 janvier 1993 relatif aux prescriptions techniques applicables à l''utilisation des équipements de travail soumis à l''article L 233-5-1 du code du travail, aux règles techniques applicables aux matériels d''occasion soumis à l''article L 233-5 du même code et à la mise en conformité des équipements existants et modifiant le code du travail (deuxième partie : Décrets en Conseil d''Etat).; Arrêté du 1er mars 2004 relatif aux vérifications des appareils et accessoires de levage Article 3', commentaires = '', personne_habilitee = 'Fabricant', criticite = 5 where id = 1906 | AC3: =IF(Tableau6[[#This Row],[Référence]]<>"",CONCATENATE("update aocr_ref_arbo set reglementation = '",Tableau6[[#This Row],[Référence]],"' where id = ",Tableau6[[#This Row],[id]]),"") -> update aocr_ref_arbo set reglementation = 'Décret n° 93-40 du 11 janvier 1993 relatif aux prescriptions techniques applicables à l''utilisation des équipements de travail soumis à l''article L 233-5-1 du code du travail, aux règles techniques applicables aux matériels d''occasion soumis à l''article L 233-5 du même code et à la mise en conformité des équipements existants et modifiant le code du travail (deuxième partie : Décrets en Conseil d''Etat).; Arrêté du 1er mars 2004 relatif aux vérifications des appareils et accessoires de levage Article 3' where id = 1906
A4: 542 | B4: Accessoire de levage | C4: Notice | D4: Accessoire de levage CE : L''exploitant doit posséder une notice de l''équipement décrivant les instructions d''utilisation, de maintenance, plans, etc. | F4: Article 3 Arrêté du 1er mars 2004 relatif aux vérifications des appareils et accessoires de levage; | H4: Ecart Détecté | I4: Fabricant | M4: 1 | N4: 1 | O4: 1 | P4: 0 | Q4: =#REF! -> #REF! | R4: =#REF! -> #REF! | S4: 1 | T4: 5 | V4: Propriétaire | Y4: =VLOOKUP(A8,Feuil1!A:B,2,FALSE) -> 421 | Z4: =VLOOKUP(A8,Feuil1!A:C,3,FALSE) -> 524 | AA4: =CONCATENATE("insert into AOCR_ref_arbo (libelle,reglementation,typologie,pere,commentaires,personne_habilitee,type_cont,pere_superieur,criticite) values ('",Tableau6[[#This Row],[Obligation]],"','",Tableau6[[#This Row],[Référence]],"',1,",Tableau6[[#This Row],[ID Domaine2]],",'",Tableau6[[#This Row],[Libellé détaillé]],"','",Tableau6[[#This Row],[Possible réalisateur]],"',3,",Tableau6[[#This Row],[ID Domaine]],",",Tableau6[[#This Row],[Urgence]],")") -> #REF! | AB4: =CONCATENATE("update aocr_ref_arbo set libelle = '",Tableau6[[#This Row],[Obligation]],"', reglementation = '",Tableau6[[#This Row],[Référence]],"', commentaires = '",Tableau6[[#This Row],[Libellé détaillé]],"', personne_habilitee = '",Tableau6[[#This Row],[Possible réalisateur]],"', criticite = ",Tableau6[[#This Row],[Urgence]]," where id = ",Tableau6[[#This Row],[id]]) -> update aocr_ref_arbo set libelle = 'Accessoire de levage CE : L''exploitant doit posséder une notice de l''équipement décrivant les instructions d''utilisation, de maintenance, plans, etc. ', reglementation = 'Article 3 Arrêté du 1er mars 2004 relatif aux vérifications des appareils et accessoires de levage;', commentaires = '', personne_habilitee = 'Fabricant', criticite = 5 where id = 542 | AC4: =IF(Tableau6[[#This Row],[Référence]]<>"",CONCATENATE("update aocr_ref_arbo set reglementation = '",Tableau6[[#This Row],[Référence]],"' where id = ",Tableau6[[#This Row],[id]]),"") -> update aocr_ref_arbo set reglementation = 'Article 3 Arrêté du 1er mars 2004 relatif aux vérifications des appareils et accessoires de levage;' where id = 542
A5: 539 | B5: Accessoire de levage | C5: Registre de sécurité | D5: Accessoire de levage : Registre de sécurité Les résultats des vérifications, des contrôles et des maintenances doivent être portés sur le registre sécurité. | F5: Code de la construction et de l''habitation Article R123-51 Code de la construction et de l''habitation Article R122-29 Code du travail Article L4711-5 Code du travail Article R4323-26 Article 3 Arrêté du 1er mars 2004 relatif aux vérifications des appareils et accessoires de levage. | H5: Ecart Détecté | I5: Exploitant | M5: 1 | N5: 1 | O5: 1 | P5: 0 | Q5: =#REF! -> #REF! | R5: =#REF! -> #REF! | S5: 1 | T5: 4 | V5: Locataire / Utilisateur | Y5: =VLOOKUP(A9,Feuil1!A:B,2,FALSE) -> 421 | Z5: =VLOOKUP(A9,Feuil1!A:C,3,FALSE) -> 1608 | AA5: =CONCATENATE("insert into AOCR_ref_arbo (libelle,reglementation,typologie,pere,commentaires,personne_habilitee,type_cont,pere_superieur,criticite) values ('",Tableau6[[#This Row],[Obligation]],"','",Tableau6[[#This Row],[Référence]],"',1,",Tableau6[[#This Row],[ID Domaine2]],",'",Tableau6[[#This Row],[Libellé détaillé]],"','",Tableau6[[#This Row],[Possible réalisateur]],"',3,",Tableau6[[#This Row],[ID Domaine]],",",Tableau6[[#This Row],[Urgence]],")") -> #REF! | AB5: =CONCATENATE("update aocr_ref_arbo set libelle = '",Tableau6[[#This Row],[Obligation]],"', reglementation = '",Tableau6[[#This Row],[Référence]],"', commentaires = '",Tableau6[[#This Row],[Libellé détaillé]],"', personne_habilitee = '",Tableau6[[#This Row],[Possible réalisateur]],"', criticite = ",Tableau6[[#This Row],[Urgence]]," where id = ",Tableau6[[#This Row],[id]]) -> update aocr_ref_arbo set libelle = 'Accessoire de levage : Registre de sécurité Les résultats des vérifications, des contrôles et des maintenances doivent être portés sur le registre sécurité.', reglementation = 'Code de la construction et de l''habitation Article R123-51 Code de la construction et de l''habitation Article R122-29 Code du travail Article L4711-5 Code du travail Article R4323-26 Article 3 Arrêté du 1er mars 2004 relatif aux vérifications des appareils et accessoires de levage.', commentaires = '', personne_habilitee = 'Exploitant', criticite = 4 where id = 539 | AC5: =IF(Tableau6[[#This Row],[Référence]]<>"",CONCATENATE("update aocr_ref_arbo set reglementation = '",Tableau6[[#This Row],[Référence]],"' where id = ",Tableau6[[#This Row],[id]]),"") -> update aocr_ref_arbo set reglementation = 'Code de la construction et de l''habitation Article R123-51 Code de la construction et de l''habitation Article R122-29 Code du travail Article L4711-5 Code du travail Article R4323-26 Article 3 Arrêté du 1er mars 2004 relatif aux vérifications des appareils et accessoires de levage.' where id = 539
A6: 533 | B6: Accessoire de levage | C6: Vérification à la mise en service | D6: Accessoires de levage neufs dont le responsable de la mise sur le marché s''est assuré de l''aptitude à l''emploi Aimant permanent, anneau, araignée, cé, crochet, élingue, manille, palonnier, pince, préhenseur, sangle. Examen d''adéquation | F6: Arrêté du 1 mars 2004 relatif aux vérifications des appareils et accessoires de levage Article 16 | H6: Ecart Détecté | I6: Personne qualifiée | M6: 1 | N6: 1 | O6: 1 | P6: 0 | Q6: =Y2 -> 421 | R6: =Z2 -> 524 | S6: 1 | T6: 5 | V6: Propriétaire | Y6: =VLOOKUP(A10,Feuil1!A:B,2,FALSE) -> 1285 | Z6: =VLOOKUP(A10,Feuil1!A:C,3,FALSE) -> 3771 | AA6: =CONCATENATE("insert into AOCR_ref_arbo (libelle,reglementation,typologie,pere,commentaires,personne_habilitee,type_cont,pere_superieur,criticite) values ('",Tableau6[[#This Row],[Obligation]],"','",Tableau6[[#This Row],[Référence]],"',1,",Tableau6[[#This Row],[ID Domaine2]],",'",Tableau6[[#This Row],[Libellé détaillé]],"','",Tableau6[[#This Row],[Possible réalisateur]],"',3,",Tableau6[[#This Row],[ID Domaine]],",",Tableau6[[#This Row],[Urgence]],")") -> insert into AOCR_ref_arbo (libelle,reglementation,typologie,pere,commentaires,personne_habilitee,type_cont,pere_superieur,criticite) values ('Accessoires de levage neufs dont le responsable de la mise sur le marché s''est assuré de l''aptitude à l''emploi Aimant permanent, anneau, araignée, cé, crochet, élingue, manille, palonnier, pince, préhenseur, sangle. Examen d''adéquation','Arrêté du 1 mars 2004 relatif aux vérifications des appareils et accessoires de levage Article 16',1,524,'','Personne qualifiée',3,421,5) | AB6: =CONCATENATE("update aocr_ref_arbo set libelle = '",Tableau6[[#This Row],[Obligation]],"', reglementation = '",Tableau6[[#This Row],[Référence]],"', commentaires = '",Tableau6[[#This Row],[Libellé détaillé]],"', personne_habilitee = '",Tableau6[[#This Row],[Possible réalisateur]],"', criticite = ",Tableau6[[#This Row],[Urgence]]," where id = ",Tableau6[[#This Row],[id]]) -> update aocr_ref_arbo set libelle = 'Accessoires de levage neufs dont le responsable de la mise sur le marché s''est assuré de l''aptitude à l''emploi Aimant permanent, anneau, araignée, cé, crochet, élingue, manille, palonnier, pince, préhenseur, sangle. Examen d''adéquation', reglementation = 'Arrêté du 1 mars 2004 relatif aux vérifications des appareils et accessoires de levage Article 16', commentaires = '', personne_habilitee = 'Personne qualifiée', criticite = 5 where id = 533 | AC6: =IF(Tableau6[[#This Row],[Référence]]<>"",CONCATENATE("update aocr_ref_arbo set reglementation = '",Tableau6[[#This Row],[Référence]],"' where id = ",Tableau6[[#This Row],[id]]),"") -> update aocr_ref_arbo set reglementation = 'Arrêté du 1 mars 2004 relatif aux vérifications des appareils et accessoires de levage Article 16' where id = 533
A7: 534 | B7: Accessoire de levage | C7: Vérification à la mise en service | D7: Accessoires de levage neufs dont le responsable de la mise sur le marché ne s''est pas assuré de l''aptitude à l''emploi ou accesoires d''occasion Aimant permanent, anneau, araignée, cé, crochet, élingue, manille, palonnier, pince, préhenseur, sangle. Examen d''adéquation / Épreuve statique | F7: Arrêté du 1 mars 2004 relatif aux vérifications des appareils et accessoires de levage Article 17 | H7: Ecart Détecté | I7: Personne qualifiée | M7: 1 | N7: 1 | O7: 1 | P7: 0 | Q7: =Y3 -> 421 | R7: =Z3 -> 524 | S7: 1 | T7: 5 | V7: Propriétaire | Y7: =VLOOKUP(A11,Feuil1!A:B,2,FALSE) -> 1285 | Z7: =VLOOKUP(A11,Feuil1!A:C,3,FALSE) -> 1287 | AA7: =CONCATENATE("insert into AOCR_ref_arbo (libelle,reglementation,typologie,pere,commentaires,personne_habilitee,type_cont,pere_superieur,criticite) values ('",Tableau6[[#This Row],[Obligation]],"','",Tableau6[[#This Row],[Référence]],"',1,",Tableau6[[#This Row],[ID Domaine2]],",'",Tableau6[[#This Row],[Libellé détaillé]],"','",Tableau6[[#This Row],[Possible réalisateur]],"',3,",Tableau6[[#This Row],[ID Domaine]],",",Tableau6[[#This Row],[Urgence]],")") -> insert into AOCR_ref_arbo (libelle,reglementation,typologie,pere,commentaires,personne_habilitee,type_cont,pere_superieur,criticite) values ('Accessoires de levage neufs dont le responsable de la mise sur le marché ne s''est pas assuré de l''aptitude à l''emploi ou accesoires d''occasion Aimant permanent, anneau, araignée, cé, crochet, élingue, manille, palonnier, pince, préhenseur, sangle. Examen d''adéquation / Épreuve statique','Arrêté du 1 mars 2004 relatif aux vérifications des appareils et accessoires de levage Article 17',1,524,'','Personne qualifiée',3,421,5) | AB7: =CONCATENATE("update aocr_ref_arbo set libelle = '",Tableau6[[#This Row],[Obligation]],"', reglementation = '",Tableau6[[#This Row],[Référence]],"', commentaires = '",Tableau6[[#This Row],[Libellé détaillé]],"', personne_habilitee = '",Tableau6[[#This Row],[Possible réalisateur]],"', criticite = ",Tableau6[[#This Row],[Urgence]]," where id = ",Tableau6[[#This Row],[id]]) -> update aocr_ref_arbo set libelle = 'Accessoires de levage neufs dont le responsable de la mise sur le marché ne s''est pas assuré de l''aptitude à l''emploi ou accesoires d''occasion Aimant permanent, anneau, araignée, cé, crochet, élingue, manille, palonnier, pince, préhenseur, sangle. Examen d''adéquation / Épreuve statique', reglementation = 'Arrêté du 1 mars 2004 relatif aux vérifications des appareils et accessoires de levage Article 17', commentaires = '', personne_habilitee = 'Personne qualifiée', criticite = 5 where id = 534 | AC7: =IF(Tableau6[[#This Row],[Référence]]<>"",CONCATENATE("update aocr_ref_arbo set reglementation = '",Tableau6[[#This Row],[Référence]],"' where id = ",Tableau6[[#This Row],[id]]),"") -> update aocr_ref_arbo set reglementation = 'Arrêté du 1 mars 2004 relatif aux vérifications des appareils et accessoires de levage Article 17' where id = 534
A8: 1288 | B8: Accessoire de levage | C8: Vérification à la mise en service | D8: Accessoire de levage CE : Vérification à la mise en service - Aptitude à l''emploi L''aptitude à l''emploi doit être réalisée. Elle mentionne l''épreuve statique de l''équipement. | F8: Arrêté du 1 mars 2004 relatif aux vérifications des appareils et accessoires de levage Article 16; | H8: Ecart Détecté | I8: Personne qualifiée | M8: 1 | N8: 1 | O8: 1 | P8: 0 | Q8: =Y4 -> 421 | R8: =Z4 -> 524 | S8: 1 | T8: 5 | V8: Propriétaire | Y8: =VLOOKUP(A12,Feuil1!A:B,2,FALSE) -> 1285 | Z8: =VLOOKUP(A12,Feuil1!A:C,3,FALSE) -> 1287 | AA8: =CONCATENATE("insert into AOCR_ref_arbo (libelle,reglementation,typologie,pere,commentaires,personne_habilitee,type_cont,pere_superieur,criticite) values ('",Tableau6[[#This Row],[Obligation]],"','",Tableau6[[#This Row],[Référence]],"',1,",Tableau6[[#This Row],[ID Domaine2]],",'",Tableau6[[#This Row],[Libellé détaillé]],"','",Tableau6[[#This Row],[Possible réalisateur]],"',3,",Tableau6[[#This Row],[ID Domaine]],",",Tableau6[[#This Row],[Urgence]],")") -> insert into AOCR_ref_arbo (libelle,reglementation,typologie,pere,commentaires,personne_habilitee,type_cont,pere_superieur,criticite) values ('Accessoire de levage CE : Vérification à la mise en service - Aptitude à l''emploi L''aptitude à l''emploi doit être réalisée. Elle mentionne l''épreuve statique de l''équipement.','Arrêté du 1 mars 2004 relatif aux vérifications des appareils et accessoires de levage Article 16;',1,524,'','Personne qualifiée',3,421,5) | AB8: =CONCATENATE("update aocr_ref_arbo set libelle = '",Tableau6[[#This Row],[Obligation]],"', reglementation = '",Tableau6[[#This Row],[Référence]],"', commentaires = '",Tableau6[[#This Row],[Libellé détaillé]],"', personne_habilitee = '",Tableau6[[#This Row],[Possible réalisateur]],"', criticite = ",Tableau6[[#This Row],[Urgence]]," where id = ",Tableau6[[#This Row],[id]]) -> update aocr_ref_arbo set libelle = 'Accessoire de levage CE : Vérification à la mise en service - Aptitude à l''emploi L''aptitude à l''emploi doit être réalisée. Elle mentionne l''épreuve statique de l''équipement.', reglementation = 'Arrêté du 1 mars 2004 relatif aux vérifications des appareils et accessoires de levage Article 16;', commentaires = '', personne_habilitee = 'Personne qualifiée', criticite = 5 where id = 1288 | AC8: =IF(Tableau6[[#This Row],[Référence]]<>"",CONCATENATE("update aocr_ref_arbo set reglementation = '",Tableau6[[#This Row],[Référence]],"' where id = ",Tableau6[[#This Row],[id]]),"") -> update aocr_ref_arbo set reglementation = 'Arrêté du 1 mars 2004 relatif aux vérifications des appareils et accessoires de levage Article 16;' where id = 1288
A9: 530 | B9: Accessoire de levage | C9: Vérification Périodique 1 an | D9: Accessoire de levage : Vérification Périodique annuelle | E9: Le périmètre de vos équipements contrôlés doit correspondre à votre parc d''appareils soumis à contrôle. Les observations issues des vérifications doivent être traitées / Article R4323-26 : Lorsque les vérifications périodiques sont réalisées par des personnes n''appartenant pas à l''établissement, les rapports établis à la suite de ces vérifications sont annexés au registre de sécurité. Les indications précises relatives à la date des vérifications, à la date de remise des rapports correspondants et à leur archivage dans l''établissement sont portées sur le registre de sécurité. | F9: Arrêté du 1 mars 2004 relatif aux vérifications des appareils et accessoires de levage Article 24 | H9: Ecart Détecté | I9: Personne qualifiée | M9: 1 | N9: 1 | O9: 1 | P9: 0 | Q9: =Y5 -> 421 | R9: =Z5 -> 1608 | S9: 1 | T9: 4 | V9: Locataire / Utilisateur | Y9: =VLOOKUP(A13,Feuil1!A:B,2,FALSE) -> 1285 | Z9: =VLOOKUP(A13,Feuil1!A:C,3,FALSE) -> 1287 | AA9: =CONCATENATE("insert into AOCR_ref_arbo (libelle,reglementation,typologie,pere,commentaires,personne_habilitee,type_cont,pere_superieur,criticite) values ('",Tableau6[[#This Row],[Obligation]],"','",Tableau6[[#This Row],[Référence]],"',1,",Tableau6[[#This Row],[ID Domaine2]],",'",Tableau6[[#This Row],[Libellé détaillé]],"','",Tableau6[[#This Row],[Possible réalisateur]],"',3,",Tableau6[[#This Row],[ID Domaine]],",",Tableau6[[#This Row],[Urgence]],")") -> insert into AOCR_ref_arbo (libelle,reglementation,typologie,pere,commentaires,personne_habilitee,type_cont,pere_superieur,criticite) values ('Accessoire de levage : Vérification Périodique annuelle','Arrêté du 1 mars 2004 relatif aux vérifications des appareils et accessoires de levage Article 24',1,1608,' Le périmètre de vos équipements contrôlés doit correspondre à votre parc d''appareils soumis à contrôle. Les observations issues des vérifications doivent être traitées / Article R4323-26 : Lorsque les vérifications périodiques sont réalisées par des personnes n''appartenant pas à l''établissement, les rapports établis à la suite de ces vérifications sont annexés au registre de sécurité. Les indications précises relatives à la date des vérifications, à la date de remise des rapports correspondants et à leur archivage dans l''établissement sont portées sur le registre de sécurité.','Personne qualifiée',3,421,4) | AB9: =CONCATENATE("update aocr_ref_arbo set libelle = '",Tableau6[[#This Row],[Obligation]],"', reglementation = '",Tableau6[[#This Row],[Référence]],"', commentaires = '",Tableau6[[#This Row],[Libellé détaillé]],"', personne_habilitee = '",Tableau6[[#This Row],[Possible réalisateur]],"', criticite = ",Tableau6[[#This Row],[Urgence]]," where id = ",Tableau6[[#This Row],[id]]) -> update aocr_ref_arbo set libelle = 'Accessoire de levage : Vérification Périodique annuelle', reglementation = 'Arrêté du 1 mars 2004 relatif aux vérifications des appareils et accessoires de levage Article 24', commentaires = ' Le périmètre de vos équipements contrôlés doit correspondre à votre parc d''appareils soumis à contrôle. Les observations issues des vérifications doivent être traitées / Article R4323-26 : Lorsque les vérifications périodiques sont réalisées par des personnes n''appartenant pas à l''établissement, les rapports établis à la suite de ces vérifications sont annexés au registre de sécurité. Les indications précises relatives à la date des vérifications, à la date de remise des rapports correspondants et à leur archivage dans l''établissement sont portées sur le registre de sécurité.', personne_habilitee = 'Personne qualifiée', criticite = 4 where id = 530 | AC9: =IF(Tableau6[[#This Row],[Référence]]<>"",CONCATENATE("update aocr_ref_arbo set reglementation = '",Tableau6[[#This Row],[Référence]],"' where id = ",Tableau6[[#This Row],[id]]),"") -> update aocr_ref_arbo set reglementation = 'Arrêté du 1 mars 2004 relatif aux vérifications des appareils et accessoires de levage Article 24' where id = 530
A10: 3780 | B10: Aération et ventilation | C10: Contrat de maintenance | D10: VMC-Gaz : Contrat de maintenance | E10: Le propriétaire ou le syndic d'un immeuble équipé d'installations collectives de ventilation mécanique contrôlée auxquelles sont raccordés des appareils à gaz (ventilation mécanique contrôlée - gaz) est tenu de faire entretenir et vérifier périodiquement l'ensemble de ces installations et d'en assurer la maintenance aux termes de contrats écrits faisant référence au présent arrêté passés avec un ou plusieurs professionnels qualifiés. | F10: A. du 25-04-1985(1), art. 1 | H10: Ecart Détecté | P10: 0 | Q10: =Y6 -> 1285 | R10: =Z6 -> 3771 | T10: 4 | V10: Propriétaire | Y10: =VLOOKUP(A14,Feuil1!A:B,2,FALSE) -> 1285 | Z10: =VLOOKUP(A14,Feuil1!A:C,3,FALSE) -> 1286 | AA10: =CONCATENATE("insert into AOCR_ref_arbo (libelle,reglementation,typologie,pere,commentaires,personne_habilitee,type_cont,pere_superieur,criticite) values ('",Tableau6[[#This Row],[Obligation]],"','",Tableau6[[#This Row],[Référence]],"',1,",Tableau6[[#This Row],[ID Domaine2]],",'",Tableau6[[#This Row],[Libellé détaillé]],"','",Tableau6[[#This Row],[Possible réalisateur]],"',3,",Tableau6[[#This Row],[ID Domaine]],",",Tableau6[[#This Row],[Urgence]],")") -> insert into AOCR_ref_arbo (libelle,reglementation,typologie,pere,commentaires,personne_habilitee,type_cont,pere_superieur,criticite) values ('VMC-Gaz : Contrat de maintenance','A. du 25-04-1985(1), art. 1 ',1,3771,'Le propriétaire ou le syndic d'un immeuble équipé d'installations collectives de ventilation mécanique contrôlée auxquelles sont raccordés des appareils à gaz (ventilation mécanique contrôlée - gaz) est tenu de faire entretenir et vérifier périodiquement l'ensemble de ces installations et d'en assurer la maintenance aux termes de contrats écrits faisant référence au présent arrêté passés avec un ou plusieurs professionnels qualifiés.','',3,1285,4) | AB10: =CONCATENATE("update aocr_ref_arbo set libelle = '",Tableau6[[#This Row],[Obligation]],"', reglementation = '",Tableau6[[#This Row],[Référence]],"', commentaires = '",Tableau6[[#This Row],[Libellé détaillé]],"', personne_habilitee = '",Tableau6[[#This Row],[Possible réalisateur]],"', criticite = ",Tableau6[[#This Row],[Urgence]]," where id = ",Tableau6[[#This Row],[id]]) -> update aocr_ref_arbo set libelle = 'VMC-Gaz : Contrat de maintenance', reglementation = 'A. du 25-04-1985(1), art. 1 ', commentaires = 'Le propriétaire ou le syndic d'un immeuble équipé d'installations collectives de ventilation mécanique contrôlée auxquelles sont raccordés des appareils à gaz (ventilation mécanique contrôlée - gaz) est tenu de faire entretenir et vérifier périodiquement l'ensemble de ces installations et d'en assurer la maintenance aux termes de contrats écrits faisant référence au présent arrêté passés avec un ou plusieurs professionnels qualifiés.', personne_habilitee = '', criticite = 4 where id = 3780 | AC10: =IF(Tableau6[[#This Row],[Référence]]<>"",CONCATENATE("update aocr_ref_arbo set reglementation = '",Tableau6[[#This Row],[Référence]],"' where id = ",Tableau6[[#This Row],[id]]),"") -> update aocr_ref_arbo set reglementation = 'A. du 25-04-1985(1), art. 1 ' where id = 3780
A11: 1292 | B11: Aération et ventilation | C11: Établissement Recevant du Public (ERP) | D11: Aération et ventilation : Locaux à pollution spécifique et non spécifique ERP : Vérification périodique - Rapport de Vérification | E11: Personne compétente | F11: Arrêté du 25 juin 1980 portant approbation des dispositions générales du règlement de sécurité contre les risques d''incendie et de panique dans les établissements recevant du public (ERP). Article CH 58; | H11: Ecart Détecté | M11: 0 | N11: 0 | O11: 1 | P11: 0 | Q11: =Y7 -> 1285 | R11: =Z7 -> 1287 | S11: 1 | T11: 5 | V11: Propriétaire | Y11: =VLOOKUP(A15,Feuil1!A:B,2,FALSE) -> 1285 | Z11: =VLOOKUP(A15,Feuil1!A:C,3,FALSE) -> 2199 | AA11: =CONCATENATE("insert into AOCR_ref_arbo (libelle,reglementation,typologie,pere,commentaires,personne_habilitee,type_cont,pere_superieur,criticite) values ('",Tableau6[[#This Row],[Obligation]],"','",Tableau6[[#This Row],[Référence]],"',1,",Tableau6[[#This Row],[ID Domaine2]],",'",Tableau6[[#This Row],[Libellé détaillé]],"','",Tableau6[[#This Row],[Possible réalisateur]],"',3,",Tableau6[[#This Row],[ID Domaine]],",",Tableau6[[#This Row],[Urgence]],")") -> insert into AOCR_ref_arbo (libelle,reglementation,typologie,pere,commentaires,personne_habilitee,type_cont,pere_superieur,criticite) values ('Aération et ventilation : Locaux à pollution spécifique et non spécifique ERP : Vérification périodique - Rapport de Vérification','Arrêté du 25 juin 1980 portant approbation des dispositions générales du règlement de sécurité contre les risques d''incendie et de panique dans les établissements recevant du public (ERP). Article CH 58;',1,1287,'Personne compétente','',3,1285,5) | AB11: =CONCATENATE("update aocr_ref_arbo set libelle = '",Tableau6[[#This Row],[Obligation]],"', reglementation = '",Tableau6[[#This Row],[Référence]],"', commentaires = '",Tableau6[[#This Row],[Libellé détaillé]],"', personne_habilitee = '",Tableau6[[#This Row],[Possible réalisateur]],"', criticite = ",Tableau6[[#This Row],[Urgence]]," where id = ",Tableau6[[#This Row],[id]]) -> update aocr_ref_arbo set libelle = 'Aération et ventilation : Locaux à pollution spécifique et non spécifique ERP : Vérification périodique - Rapport de Vérification', reglementation = 'Arrêté du 25 juin 1980 portant approbation des dispositions générales du règlement de sécurité contre les risques d''incendie et de panique dans les établissements recevant du public (ERP). Article CH 58;', commentaires = 'Personne compétente', personne_habilitee = '', criticite = 5 where id = 1292 | AC11: =IF(Tableau6[[#This Row],[Référence]]<>"",CONCATENATE("update aocr_ref_arbo set reglementation = '",Tableau6[[#This Row],[Référence]],"' where id = ",Tableau6[[#This Row],[id]]),"") -> update aocr_ref_arbo set reglementation = 'Arrêté du 25 juin 1980 portant approbation des dispositions générales du règlement de sécurité contre les risques d''incendie et de panique dans les établissements recevant du public (ERP). Article CH 58;' where id = 1292
A12: 1293 | B12: Aération et ventilation | C12: Établissement Recevant du Public (ERP) | D12: Aération et ventilation : Dispositifs de surveillance de la qualité de l''air Parcs de stationnement couverts ERP inférieur ou égale à 250 véhicules : Contrôle biennale | F12: Arrêté du 25 juin 1980 Article PS 32 | H12: Ecart Détecté | M12: 0 | N12: 0 | O12: 1 | P12: 0 | Q12: =Y8 -> 1285 | R12: =Z8 -> 1287 | S12: 1 | T12: 5 | V12: Propriétaire | Y12: =VLOOKUP(A16,Feuil1!A:B,2,FALSE) -> 1285 | Z12: =VLOOKUP(A16,Feuil1!A:C,3,FALSE) -> 1739 | AA12: =CONCATENATE("insert into AOCR_ref_arbo (libelle,reglementation,typologie,pere,commentaires,personne_habilitee,type_cont,pere_superieur,criticite) values ('",Tableau6[[#This Row],[Obligation]],"','",Tableau6[[#This Row],[Référence]],"',1,",Tableau6[[#This Row],[ID Domaine2]],",'",Tableau6[[#This Row],[Libellé détaillé]],"','",Tableau6[[#This Row],[Possible réalisateur]],"',3,",Tableau6[[#This Row],[ID Domaine]],",",Tableau6[[#This Row],[Urgence]],")") -> insert into AOCR_ref_arbo (libelle,reglementation,typologie,pere,commentaires,personne_habilitee,type_cont,pere_superieur,criticite) values ('Aération et ventilation : Dispositifs de surveillance de la qualité de l''air Parcs de stationnement couverts ERP inférieur ou égale à 250 véhicules : Contrôle biennale','Arrêté du 25 juin 1980 Article PS 32',1,1287,'','',3,1285,5) | AB12: =CONCATENATE("update aocr_ref_arbo set libelle = '",Tableau6[[#This Row],[Obligation]],"', reglementation = '",Tableau6[[#This Row],[Référence]],"', commentaires = '",Tableau6[[#This Row],[Libellé détaillé]],"', personne_habilitee = '",Tableau6[[#This Row],[Possible réalisateur]],"', criticite = ",Tableau6[[#This Row],[Urgence]]," where id = ",Tableau6[[#This Row],[id]]) -> update aocr_ref_arbo set libelle = 'Aération et ventilation : Dispositifs de surveillance de la qualité de l''air Parcs de stationnement couverts ERP inférieur ou égale à 250 véhicules : Contrôle biennale', reglementation = 'Arrêté du 25 juin 1980 Article PS 32', commentaires = '', personne_habilitee = '', criticite = 5 where id = 1293 | AC12: =IF(Tableau6[[#This Row],[Référence]]<>"",CONCATENATE("update aocr_ref_arbo set reglementation = '",Tableau6[[#This Row],[Référence]],"' where id = ",Tableau6[[#This Row],[id]]),"") -> update aocr_ref_arbo set reglementation = 'Arrêté du 25 juin 1980 Article PS 32' where id = 1293
A13: 1294 | B13: Aération et ventilation | C13: Établissement Recevant du Public (ERP) | D13: Aération et ventilation : Dispositifs de surveillance de la qualité de l''air Parcs de stationnement couverts ERP supérieur à 250 véhicules : Contrôle annuel | F13: Arrêté du 25 juin 1980 Article PS 32 | H13: Ecart Détecté | M13: 0 | N13: 0 | O13: 1 | P13: 0 | Q13: =Y9 -> 1285 | R13: =Z9 -> 1287 | S13: 1 | T13: 4 | V13: Locataire / Utilisateur | Y13: =VLOOKUP(A17,Feuil1!A:B,2,FALSE) -> 1285 | Z13: =VLOOKUP(A17,Feuil1!A:C,3,FALSE) -> 1739 | AA13: =CONCATENATE("insert into AOCR_ref_arbo (libelle,reglementation,typologie,pere,commentaires,personne_habilitee,type_cont,pere_superieur,criticite) values ('",Tableau6[[#This Row],[Obligation]],"','",Tableau6[[#This Row],[Référence]],"',1,",Tableau6[[#This Row],[ID Domaine2]],",'",Tableau6[[#This Row],[Libellé détaillé]],"','",Tableau6[[#This Row],[Possible réalisateur]],"',3,",Tableau6[[#This Row],[ID Domaine]],",",Tableau6[[#This Row],[Urgence]],")") -> insert into AOCR_ref_arbo (libelle,reglementation,typologie,pere,commentaires,personne_habilitee,type_cont,pere_superieur,criticite) values ('Aération et ventilation : Dispositifs de surveillance de la qualité de l''air Parcs de stationnement couverts ERP supérieur à 250 véhicules : Contrôle annuel','Arrêté du 25 juin 1980 Article PS 32',1,1287,'','',3,1285,4) | AB13: =CONCATENATE("update aocr_ref_arbo set libelle = '",Tableau6[[#This Row],[Obligation]],"', reglementation = '",Tableau6[[#This Row],[Référence]],"', commentaires = '",Tableau6[[#This Row],[Libellé détaillé]],"', personne_habilitee = '",Tableau6[[#This Row],[Possible réalisateur]],"', criticite = ",Tableau6[[#This Row],[Urgence]]," where id = ",Tableau6[[#This Row],[id]]) -> update aocr_ref_arbo set libelle = 'Aération et ventilation : Dispositifs de surveillance de la qualité de l''air Parcs de stationnement couverts ERP supérieur à 250 véhicules : Contrôle annuel', reglementation = 'Arrêté du 25 juin 1980 Article PS 32', commentaires = '', personne_habilitee = '', criticite = 4 where id = 1294 | AC13: =IF(Tableau6[[#This Row],[Référence]]<>"",CONCATENATE("update aocr_ref_arbo set reglementation = '",Tableau6[[#This Row],[Référence]],"' where id = ",Tableau6[[#This Row],[id]]),"") -> update aocr_ref_arbo set reglementation = 'Arrêté du 25 juin 1980 Article PS 32' where id = 1294
A14: 1289 | B14: Aération et ventilation | C14: Immeuble de Grande Hauteur (IGH) | D14: Aération et ventilation : Locaux à pollution spécifique et non spécifique IGH : Contrôle à la Mise en Service Rapport de Vérification Réglementaire Après Travaux (RVRAT) | F14: Arrêté du 30 décembre 2011 portant règlement de sécurité pour la construction des immeubles de grande hauteur et leur protection contre les risques d''incendie et de panique Article GH 5 § 2.; Arrêté du 25 juin 1980 portant approbation des dispositions générales du règlement de sécurité contre les risques d''incendie et de panique dans les établissements recevant du public (ERP). Article CH 58; | H14: Ecart Détecté | M14: 0 | N14: 0 | O14: 1 | P14: 0 | Q14: =Y10 -> 1285 | R14: =Z10 -> 1286 | S14: 1 | T14: 5 | V14: Propriétaire | Y14: =VLOOKUP(A18,Feuil1!A:B,2,FALSE) -> 1285 | Z14: =VLOOKUP(A18,Feuil1!A:C,3,FALSE) -> 1740 | AA14: =CONCATENATE("insert into AOCR_ref_arbo (libelle,reglementation,typologie,pere,commentaires,personne_habilitee,type_cont,pere_superieur,criticite) values ('",Tableau6[[#This Row],[Obligation]],"','",Tableau6[[#This Row],[Référence]],"',1,",Tableau6[[#This Row],[ID Domaine2]],",'",Tableau6[[#This Row],[Libellé détaillé]],"','",Tableau6[[#This Row],[Possible réalisateur]],"',3,",Tableau6[[#This Row],[ID Domaine]],",",Tableau6[[#This Row],[Urgence]],")") -> insert into AOCR_ref_arbo (libelle,reglementation,typologie,pere,commentaires,personne_habilitee,type_cont,pere_superieur,criticite) values ('Aération et ventilation : Locaux à pollution spécifique et non spécifique IGH : Contrôle à la Mise en Service Rapport de Vérification Réglementaire Après Travaux (RVRAT)','Arrêté du 30 décembre 2011 portant règlement de sécurité pour la construction des immeubles de grande hauteur et leur protection contre les risques d''incendie et de panique Article GH 5 § 2.; Arrêté du 25 juin 1980 portant approbation des dispositions générales du règlement de sécurité contre les risques d''incendie et de panique dans les établissements recevant du public (ERP). Article CH 58;',1,1286,'','',3,1285,5) | AB14: =CONCATENATE("update aocr_ref_arbo set libelle = '",Tableau6[[#This Row],[Obligation]],"', reglementation = '",Tableau6[[#This Row],[Référence]],"', commentaires = '",Tableau6[[#This Row],[Libellé détaillé]],"', personne_habilitee = '",Tableau6[[#This Row],[Possible réalisateur]],"', criticite = ",Tableau6[[#This Row],[Urgence]]," where id = ",Tableau6[[#This Row],[id]]) -> update aocr_ref_arbo set libelle = 'Aération et ventilation : Locaux à pollution spécifique et non spécifique IGH : Contrôle à la Mise en Service Rapport de Vérification Réglementaire Après Travaux (RVRAT)', reglementation = 'Arrêté du 30 décembre 2011 portant règlement de sécurité pour la construction des immeubles de grande hauteur et leur protection contre les risques d''incendie et de panique Article GH 5 § 2.; Arrêté du 25 juin 1980 portant approbation des dispositions générales du règlement de sécurité contre les risques d''incendie et de panique dans les établissements recevant du public (ERP). Article CH 58;', commentaires = '', personne_habilitee = '', criticite = 5 where id = 1289 | AC14: =IF(Tableau6[[#This Row],[Référence]]<>"",CONCATENATE("update aocr_ref_arbo set reglementation = '",Tableau6[[#This Row],[Référence]],"' where id = ",Tableau6[[#This Row],[id]]),"") -> update aocr_ref_arbo set reglementation = 'Arrêté du 30 décembre 2011 portant règlement de sécurité pour la construction des immeubles de grande hauteur et leur protection contre les risques d''incendie et de panique Article GH 5 § 2.; Arrêté du 25 juin 1980 portant approbation des dispositions générales du règlement de sécurité contre les risques d''incendie et de panique dans les établissements recevant du public (ERP). Article CH 58;' where id = 1289
A15: 2203 | B15: Aération et ventilation | C15: Registre de sécurité | D15: Aération et ventilation : Registre de sécurité Les résultats des vérifications, des contrôles et des maintenances doivent être portés sur le registre sécurité. | F15: Code de la construction et de l''habitation Article R123-51 Code de la construction et de l''habitation Article R122-29 Code du travail Article L4711-5 Code du travail Article R4323-26 Article 3 Arrêté du 1er mars 2004 Arrêté du 08-10-1987, art. 2 | H15: Ecart Détecté | M15: 1 | N15: 1 | O15: 1 | P15: 0 | Q15: =Y11 -> 1285 | R15: =Z11 -> 2199 | S15: 1 | T15: 4 | V15: Locataire / Utilisateur | Y15: =VLOOKUP(A19,Feuil1!A:B,2,FALSE) -> 1285 | Z15: =VLOOKUP(A19,Feuil1!A:C,3,FALSE) -> 1740 | AA15: =CONCATENATE("insert into AOCR_ref_arbo (libelle,reglementation,typologie,pere,commentaires,personne_habilitee,type_cont,pere_superieur,criticite) values ('",Tableau6[[#This Row],[Obligation]],"','",Tableau6[[#This Row],[Référence]],"',1,",Tableau6[[#This Row],[ID Domaine2]],",'",Tableau6[[#This Row],[Libellé détaillé]],"','",Tableau6[[#This Row],[Possible réalisateur]],"',3,",Tableau6[[#This Row],[ID Domaine]],",",Tableau6[[#This Row],[Urgence]],")") -> insert into AOCR_ref_arbo (libelle,reglementation,typologie,pere,commentaires,personne_habilitee,type_cont,pere_superieur,criticite) values ('Aération et ventilation : Registre de sécurité Les résultats des vérifications, des contrôles et des maintenances doivent être portés sur le registre sécurité.','Code de la construction et de l''habitation Article R123-51 Code de la construction et de l''habitation Article R122-29 Code du travail Article L4711-5 Code du travail Article R4323-26 Article 3 Arrêté du 1er mars 2004 Arrêté du 08-10-1987, art. 2',1,2199,'','',3,1285,4) | AB15: =CONCATENATE("update aocr_ref_arbo set libelle = '",Tableau6[[#This Row],[Obligation]],"', reglementation = '",Tableau6[[#This Row],[Référence]],"', commentaires = '",Tableau6[[#This Row],[Libellé détaillé]],"', personne_habilitee = '",Tableau6[[#This Row],[Possible réalisateur]],"', criticite = ",Tableau6[[#This Row],[Urgence]]," where id = ",Tableau6[[#This Row],[id]]) -> update aocr_ref_arbo set libelle = 'Aération et ventilation : Registre de sécurité Les résultats des vérifications, des contrôles et des maintenances doivent être portés sur le registre sécurité.', reglementation = 'Code de la construction et de l''habitation Article R123-51 Code de la construction et de l''habitation Article R122-29 Code du travail Article L4711-5 Code du travail Article R4323-26 Article 3 Arrêté du 1er mars 2004 Arrêté du 08-10-1987, art. 2', commentaires = '', personne_habilitee = '', criticite = 4 where id = 2203 | AC15: =IF(Tableau6[[#This Row],[Référence]]<>"",CONCATENATE("update aocr_ref_arbo set reglementation = '",Tableau6[[#This Row],[Référence]],"' where id = ",Tableau6[[#This Row],[id]]),"") -> update aocr_ref_arbo set reglementation = 'Code de la construction et de l''habitation Article R123-51 Code de la construction et de l''habitation Article R122-29 Code du travail Article L4711-5 Code du travail Article R4323-26 Article 3 Arrêté du 1er mars 2004 Arrêté du 08-10-1987, art. 2' where id = 2203
A16: 1053 | B16: Aération et ventilation | C16: Vérification à la mise en service | D16: Aération et ventilation: Installation à pollution spécifique et non spécifique Vérification à la mise en service / Etablissement d''une notice d''instruction | E16: Des mesures, contrôles et examen doivent être effectué au plus tard un mois après la mise en service. | F16: CT. art. R. 4212-7 CT. art. R. 4212-3 CT. art. R. 4222-21 Arrêté du 08-10-1987, art. 2, 3 et 4. | H16: Ecart Détecté | M16: 1 | N16: 1 | O16: 1 | P16: 0 | Q16: =Y12 -> 1285 | R16: =Z12 -> 1739 | S16: 1 | T16: 5 | V16: Propriétaire | Y16: =VLOOKUP(A20,Feuil1!A:B,2,FALSE) -> 1285 | Z16: =VLOOKUP(A20,Feuil1!A:C,3,FALSE) -> 3770 | AA16: =CONCATENATE("insert into AOCR_ref_arbo (libelle,reglementation,typologie,pere,commentaires,personne_habilitee,type_cont,pere_superieur,criticite) values ('",Tableau6[[#This Row],[Obligation]],"','",Tableau6[[#This Row],[Référence]],"',1,",Tableau6[[#This Row],[ID Domaine2]],",'",Tableau6[[#This Row],[Libellé détaillé]],"','",Tableau6[[#This Row],[Possible réalisateur]],"',3,",Tableau6[[#This Row],[ID Domaine]],",",Tableau6[[#This Row],[Urgence]],")") -> insert into AOCR_ref_arbo (libelle,reglementation,typologie,pere,commentaires,personne_habilitee,type_cont,pere_superieur,criticite) values ('Aération et ventilation: Installation à pollution spécifique et non spécifique Vérification à la mise en service / Etablissement d''une notice d''instruction','CT. art. R. 4212-7 CT. art. R. 4212-3 CT. art. R. 4222-21 Arrêté du 08-10-1987, art. 2, 3 et 4. ',1,1739,'Des mesures, contrôles et examen doivent être effectué au plus tard un mois après la mise en service.','',3,1285,5) | AB16: =CONCATENATE("update aocr_ref_arbo set libelle = '",Tableau6[[#This Row],[Obligation]],"', reglementation = '",Tableau6[[#This Row],[Référence]],"', commentaires = '",Tableau6[[#This Row],[Libellé détaillé]],"', personne_habilitee = '",Tableau6[[#This Row],[Possible réalisateur]],"', criticite = ",Tableau6[[#This Row],[Urgence]]," where id = ",Tableau6[[#This Row],[id]]) -> update aocr_ref_arbo set libelle = 'Aération et ventilation: Installation à pollution spécifique et non spécifique Vérification à la mise en service / Etablissement d''une notice d''instruction', reglementation = 'CT. art. R. 4212-7 CT. art. R. 4212-3 CT. art. R. 4222-21 Arrêté du 08-10-1987, art. 2, 3 et 4. ', commentaires = 'Des mesures, contrôles et examen doivent être effectué au plus tard un mois après la mise en service.', personne_habilitee = '', criticite = 5 where id = 1053 | AC16: =IF(Tableau6[[#This Row],[Référence]]<>"",CONCATENATE("update aocr_ref_arbo set reglementation = '",Tableau6[[#This Row],[Référence]],"' where id = ",Tableau6[[#This Row],[id]]),"") -> update aocr_ref_arbo set reglementation = 'CT. art. R. 4212-7 CT. art. R. 4212-3 CT. art. R. 4222-21 Arrêté du 08-10-1987, art. 2, 3 et 4. ' where id = 1053
A17: 3702 | B17: Aération et ventilation | C17: Vérification à la mise en service | D17: Aération et ventilation: Installation à pollution spécifique avec système de recyclage Vérification à la mise en service établissement d''une notice d''instruction | E17: Des mesures, contrôles et examen doivent être effectué au plus tard un mois après la mise en service. | F17: CT. art. R. 4212-7 CT. art. R. 4212-3 CT. art. R. 4222-21 Arrêté du 08-10-1987, art 2 et 4. | H17: Ecart Détecté | M17: 1 | N17: 1 | O17: 1 | P17: 0 | Q17: =Y13 -> 1285 | R17: =Z13 -> 1739 | S17: 1 | T17: 5 | V17: Propriétaire | Y17: =VLOOKUP(A21,Feuil1!A:B,2,FALSE) -> 1285 | Z17: =VLOOKUP(A21,Feuil1!A:C,3,FALSE) -> 1741 | AA17: =CONCATENATE("insert into AOCR_ref_arbo (libelle,reglementation,typologie,pere,commentaires,personne_habilitee,type_cont,pere_superieur,criticite) values ('",Tableau6[[#This Row],[Obligation]],"','",Tableau6[[#This Row],[Référence]],"',1,",Tableau6[[#This Row],[ID Domaine2]],",'",Tableau6[[#This Row],[Libellé détaillé]],"','",Tableau6[[#This Row],[Possible réalisateur]],"',3,",Tableau6[[#This Row],[ID Domaine]],",",Tableau6[[#This Row],[Urgence]],")") -> insert into AOCR_ref_arbo (libelle,reglementation,typologie,pere,commentaires,personne_habilitee,type_cont,pere_superieur,criticite) values ('Aération et ventilation: Installation à pollution spécifique avec système de recyclage Vérification à la mise en service établissement d''une notice d''instruction','CT. art. R. 4212-7 CT. art. R. 4212-3 CT. art. R. 4222-21 Arrêté du 08-10-1987, art 2 et 4. ',1,1739,'Des mesures, contrôles et examen doivent être effectué au plus tard un mois après la mise en service.','',3,1285,5) | AB17: =CONCATENATE("update aocr_ref_arbo set libelle = '",Tableau6[[#This Row],[Obligation]],"', reglementation = '",Tableau6[[#This Row],[Référence]],"', commentaires = '",Tableau6[[#This Row],[Libellé détaillé]],"', personne_habilitee = '",Tableau6[[#This Row],[Possible réalisateur]],"', criticite = ",Tableau6[[#This Row],[Urgence]]," where id = ",Tableau6[[#This Row],[id]]) -> update aocr_ref_arbo set libelle = 'Aération et ventilation: Installation à pollution spécifique avec système de recyclage Vérification à la mise en service établissement d''une notice d''instruction', reglementation = 'CT. art. R. 4212-7 CT. art. R. 4212-3 CT. art. R. 4222-21 Arrêté du 08-10-1987, art 2 et 4. ', commentaires = 'Des mesures, contrôles et examen doivent être effectué au plus tard un mois après la mise en service.', personne_habilitee = '', criticite = 5 where id = 3702 | AC17: =IF(Tableau6[[#This Row],[Référence]]<>"",CONCATENATE("update aocr_ref_arbo set reglementation = '",Tableau6[[#This Row],[Référence]],"' where id = ",Tableau6[[#This Row],[id]]),"") -> update aocr_ref_arbo set reglementation = 'CT. art. R. 4212-7 CT. art. R. 4212-3 CT. art. R. 4222-21 Arrêté du 08-10-1987, art 2 et 4. ' where id = 3702
A18: 2232 | B18: Aération et ventilation | C18: Vérification Périodique 1 an | D18: Installation à pollution spécifique et non spécifique Vérification Périodique Annuelle : rapport de vérification et de maintenance | E18: Une maintenance périodique des installations à pollution non spécifique doit être effectué tous les ans. Au minimum une fois par an, les opérations suivantes doivent être effectuées : - contrôle du débit global minimal d''air neuf de l''installation ; - examen de l''état des éléments de l''installation (système d''introduction et d''extraction, gaines, ventilateurs) et plus particulièrement de la présence et de la conformité des filtres de rechange par rapport à la fourniture initiale (caractéristique, classe d''efficacité), de leurs dimensions, de leur perte de charge ; - examen de l''état des systèmes de traitement de l''air (humidificateur, batterie d''échangeurs) ; - lorsque le dossier de valeurs de référence est constitué, contrôle des pressions statiques ou des vitesses d''air aux points caractéristiques de l''installation. | F18: Article 3 Arrêté du 8 octobre 1987 CDT Art R4222-21 CDT Art R4222-22 | H18: Ecart Détecté | M18: 1 | N18: 1 | O18: 1 | P18: 0 | Q18: =Y14 -> 1285 | R18: =Z14 -> 1740 | S18: 1 | T18: 4 | V18: Locataire / Utilisateur | Y18: =VLOOKUP(A22,Feuil1!A:B,2,FALSE) -> 2 | Z18: =VLOOKUP(A22,Feuil1!A:C,3,FALSE) -> 1098 | AA18: =CONCATENATE("insert into AOCR_ref_arbo (libelle,reglementation,typologie,pere,commentaires,personne_habilitee,type_cont,pere_superieur,criticite) values ('",Tableau6[[#This Row],[Obligation]],"','",Tableau6[[#This Row],[Référence]],"',1,",Tableau6[[#This Row],[ID Domaine2]],",'",Tableau6[[#This Row],[Libellé détaillé]],"','",Tableau6[[#This Row],[Possible réalisateur]],"',3,",Tableau6[[#This Row],[ID Domaine]],",",Tableau6[[#This Row],[Urgence]],")") -> insert into AOCR_ref_arbo (libelle,reglementation,typologie,pere,commentaires,personne_habilitee,type_cont,pere_superieur,criticite) values ('Installation à pollution spécifique et non spécifique Vérification Périodique Annuelle : rapport de vérification et de maintenance','Article 3 Arrêté du 8 octobre 1987 CDT Art R4222-21 CDT Art R4222-22',1,1740,'Une maintenance périodique des installations à pollution non spécifique doit être effectué tous les ans. Au minimum une fois par an, les opérations suivantes doivent être effectuées : - contrôle du débit global minimal d''air neuf de l''installation ; - examen de l''état des éléments de l''installation (système d''introduction et d''extraction, gaines, ventilateurs) et plus particulièrement de la présence et de la conformité des filtres de rechange par rapport à la fourniture initiale (caractéristique, classe d''efficacité), de leurs dimensions, de leur perte de charge ; - examen de l''état des systèmes de traitement de l''air (humidificateur, batterie d''échangeurs) ; - lorsque le dossier de valeurs de référence est constitué, contrôle des pressions statiques ou des vitesses d''air aux points caractéristiques de l''installation.','',3,1285,4) | AB18: =CONCATENATE("update aocr_ref_arbo set libelle = '",Tableau6[[#This Row],[Obligation]],"', reglementation = '",Tableau6[[#This Row],[Référence]],"', commentaires = '",Tableau6[[#This Row],[Libellé détaillé]],"', personne_habilitee = '",Tableau6[[#This Row],[Possible réalisateur]],"', criticite = ",Tableau6[[#This Row],[Urgence]]," where id = ",Tableau6[[#This Row],[id]]) -> update aocr_ref_arbo set libelle = 'Installation à pollution spécifique et non spécifique Vérification Périodique Annuelle : rapport de vérification et de maintenance', reglementation = 'Article 3 Arrêté du 8 octobre 1987 CDT Art R4222-21 CDT Art R4222-22', commentaires = 'Une maintenance périodique des installations à pollution non spécifique doit être effectué tous les ans. Au minimum une fois par an, les opérations suivantes doivent être effectuées : - contrôle du débit global minimal d''air neuf de l''installation ; - examen de l''état des éléments de l''installation (système d''introduction et d''extraction, gaines, ventilateurs) et plus particulièrement de la présence et de la conformité des filtres de rechange par rapport à la fourniture initiale (caractéristique, classe d''efficacité), de leurs dimensions, de leur perte de charge ; - examen de l''état des systèmes de traitement de l''air (humidificateur, batterie d''échangeurs) ; - lorsque le dossier de valeurs de référence est constitué, contrôle des pressions statiques ou des vitesses d''air aux points caractéristiques de l''installation.', personne_habilitee = '', criticite = 4 where id = 2232 | AC18: =IF(Tableau6[[#This Row],[Référence]]<>"",CONCATENATE("update aocr_ref_arbo set reglementation = '",Tableau6[[#This Row],[Référence]],"' where id = ",Tableau6[[#This Row],[id]]),"") -> update aocr_ref_arbo set reglementation = 'Article 3 Arrêté du 8 octobre 1987 CDT Art R4222-21 CDT Art R4222-22' where id = 2232
A19: 3778 | B19: Aération et ventilation | C19: Vérification Périodique 1 an | D19: VMC-Gaz : Vérification Périodique 1 an | E19: Tous les ans au moins Le nettoyage des pales de ventilateur ; Le remplacement des courroies de transmission lorsqu'elles existent ; La vérification des paliers et des connexions électriques, des caractéristiques de fonctionnement du ventilateur (vitesse ou débit-pression, etc.) et du fonctionnement des alarmes éventuelles ; La vérification de la vacuité des conduits aérauliques, conduits collecteurs, conduits de liaison entre bouches d'extraction et conduits collecteurs, et du bon état des manchettes souples, des dispositifs de pied de conduits, des trappes de visite, des purges et siphons éventuels ; La vérification de l'état et du fonctionnement des bouches d'entrée d'air et d'extraction ainsi que leur entretien ou leur échange standard éventuel ; La vérification de la conformité à l'installation d'origine : absence de hottes ou armoires sèche-linge motorisées raccordées à la ventilation mécanique contrôlée - gaz, etc.. Le bon fonctionnement du système de détection de défaut du dispositif de sécurité collective ; " | F19: A. du 25-04-1985(1), art. 1 et 2. | H19: Ecart Détecté | P19: 0 | Q19: =Y15 -> 1285 | R19: =Z15 -> 1740 | T19: 4 | V19: Propriétaire | Y19: =VLOOKUP(A23,Feuil1!A:B,2,FALSE) -> 2 | Z19: =VLOOKUP(A23,Feuil1!A:C,3,FALSE) -> 1901 | AA19: =CONCATENATE("insert into AOCR_ref_arbo (libelle,reglementation,typologie,pere,commentaires,personne_habilitee,type_cont,pere_superieur,criticite) values ('",Tableau6[[#This Row],[Obligation]],"','",Tableau6[[#This Row],[Référence]],"',1,",Tableau6[[#This Row],[ID Domaine2]],",'",Tableau6[[#This Row],[Libellé détaillé]],"','",Tableau6[[#This Row],[Possible réalisateur]],"',3,",Tableau6[[#This Row],[ID Domaine]],",",Tableau6[[#This Row],[Urgence]],")") -> insert into AOCR_ref_arbo (libelle,reglementation,typologie,pere,commentaires,personne_habilitee,type_cont,pere_superieur,criticite) values ('VMC-Gaz : Vérification Périodique 1 an','A. du 25-04-1985(1), art. 1 et 2.',1,1740,'Tous les ans au moins Le nettoyage des pales de ventilateur ; Le remplacement des courroies de transmission lorsqu'elles existent ; La vérification des paliers et des connexions électriques, des caractéristiques de fonctionnement du ventilateur (vitesse ou débit-pression, etc.) et du fonctionnement des alarmes éventuelles ; La vérification de la vacuité des conduits aérauliques, conduits collecteurs, conduits de liaison entre bouches d'extraction et conduits collecteurs, et du bon état des manchettes souples, des dispositifs de pied de conduits, des trappes de visite, des purges et siphons éventuels ; La vérification de l'état et du fonctionnement des bouches d'entrée d'air et d'extraction ainsi que leur entretien ou leur échange standard éventuel ; La vérification de la conformité à l'installation d'origine : absence de hottes ou armoires sèche-linge motorisées raccordées à la ventilation mécanique contrôlée - gaz, etc.. Le bon fonctionnement du système de détection de défaut du dispositif de sécurité collective ; "','',3,1285,4) | AB19: =CONCATENATE("update aocr_ref_arbo set libelle = '",Tableau6[[#This Row],[Obligation]],"', reglementation = '",Tableau6[[#This Row],[Référence]],"', commentaires = '",Tableau6[[#This Row],[Libellé détaillé]],"', personne_habilitee = '",Tableau6[[#This Row],[Possible réalisateur]],"', criticite = ",Tableau6[[#This Row],[Urgence]]," where id = ",Tableau6[[#This Row],[id]]) -> update aocr_ref_arbo set libelle = 'VMC-Gaz : Vérification Périodique 1 an', reglementation = 'A. du 25-04-1985(1), art. 1 et 2.', commentaires = 'Tous les ans au moins Le nettoyage des pales de ventilateur ; Le remplacement des courroies de transmission lorsqu'elles existent ; La vérification des paliers et des connexions électriques, des caractéristiques de fonctionnement du ventilateur (vitesse ou débit-pression, etc.) et du fonctionnement des alarmes éventuelles ; La vérification de la vacuité des conduits aérauliques, conduits collecteurs, conduits de liaison entre bouches d'extraction et conduits collecteurs, et du bon état des manchettes souples, des dispositifs de pied de conduits, des trappes de visite, des purges et siphons éventuels ; La vérification de l'état et du fonctionnement des bouches d'entrée d'air et d'extraction ainsi que leur entretien ou leur échange standard éventuel ; La vérification de la conformité à l'installation d'origine : absence de hottes ou armoires sèche-linge motorisées raccordées à la ventilation mécanique contrôlée - gaz, etc.. Le bon fonctionnement du système de détection de défaut du dispositif de sécurité collective ; "', personne_habilitee = '', criticite = 4 where id = 3778 | AC19: =IF(Tableau6[[#This Row],[Référence]]<>"",CONCATENATE("update aocr_ref_arbo set reglementation = '",Tableau6[[#This Row],[Référence]],"' where id = ",Tableau6[[#This Row],[id]]),"") -> update aocr_ref_arbo set reglementation = 'A. du 25-04-1985(1), art. 1 et 2.' where id = 3778
A20: 3779 | B20: Aération et ventilation | C20: Vérification Périodique 5 ans | D20: VMC-Gaz : Vérification Périodique 5 ans | E20: Tous les cinq ans au moins. Le contrôle et le réglage global de l'ensemble de l'installation et notamment le réglage général du réseau aéraulique (volets de réglage, etc.), le réglage ou le remplacement des bouches d'air et d'extraction, le réglage du ventilateur (vitesse, débit-pression, etc.). La vérification du bon fonctionnement de l'ensemble du dispositif de sécurité collective ; cette vérification devra porter également sur chaque appareil raccordé. Lorsque l'installation n'est pas équipée d'un dispositif de sécurité collective, la vérification par arrêt de l'extracteur que certains appareils raccordés ne restent en fonctionnement que si l'évacuation des fumées est assurée par tirage naturel. " | F20: A. du 25-04-1985(1), art. 1 et 2. | H20: Ecart Détecté | P20: 0 | Q20: =Y16 -> 1285 | R20: =Z16 -> 3770 | T20: 4 | V20: Propriétaire | Y20: =VLOOKUP(A24,Feuil1!A:B,2,FALSE) -> 2 | Z20: =VLOOKUP(A24,Feuil1!A:C,3,FALSE) -> 1495 | AA20: =CONCATENATE("insert into AOCR_ref_arbo (libelle,reglementation,typologie,pere,commentaires,personne_habilitee,type_cont,pere_superieur,criticite) values ('",Tableau6[[#This Row],[Obligation]],"','",Tableau6[[#This Row],[Référence]],"',1,",Tableau6[[#This Row],[ID Domaine2]],",'",Tableau6[[#This Row],[Libellé détaillé]],"','",Tableau6[[#This Row],[Possible réalisateur]],"',3,",Tableau6[[#This Row],[ID Domaine]],",",Tableau6[[#This Row],[Urgence]],")") -> insert into AOCR_ref_arbo (libelle,reglementation,typologie,pere,commentaires,personne_habilitee,type_cont,pere_superieur,criticite) values ('VMC-Gaz : Vérification Périodique 5 ans','A. du 25-04-1985(1), art. 1 et 2.',1,3770,'Tous les cinq ans au moins. Le contrôle et le réglage global de l'ensemble de l'installation et notamment le réglage général du réseau aéraulique (volets de réglage, etc.), le réglage ou le remplacement des bouches d'air et d'extraction, le réglage du ventilateur (vitesse, débit-pression, etc.). La vérification du bon fonctionnement de l'ensemble du dispositif de sécurité collective ; cette vérification devra porter également sur chaque appareil raccordé. Lorsque l'installation n'est pas équipée d'un dispositif de sécurité collective, la vérification par arrêt de l'extracteur que certains appareils raccordés ne restent en fonctionnement que si l'évacuation des fumées est assurée par tirage naturel. "','',3,1285,4) | AB20: =CONCATENATE("update aocr_ref_arbo set libelle = '",Tableau6[[#This Row],[Obligation]],"', reglementation = '",Tableau6[[#This Row],[Référence]],"', commentaires = '",Tableau6[[#This Row],[Libellé détaillé]],"', personne_habilitee = '",Tableau6[[#This Row],[Possible réalisateur]],"', criticite = ",Tableau6[[#This Row],[Urgence]]," where id = ",Tableau6[[#This Row],[id]]) -> update aocr_ref_arbo set libelle = 'VMC-Gaz : Vérification Périodique 5 ans', reglementation = 'A. du 25-04-1985(1), art. 1 et 2.', commentaires = 'Tous les cinq ans au moins. Le contrôle et le réglage global de l'ensemble de l'installation et notamment le réglage général du réseau aéraulique (volets de réglage, etc.), le réglage ou le remplacement des bouches d'air et d'extraction, le réglage du ventilateur (vitesse, débit-pression, etc.). La vérification du bon fonctionnement de l'ensemble du dispositif de sécurité collective ; cette vérification devra porter également sur chaque appareil raccordé. Lorsque l'installation n'est pas équipée d'un dispositif de sécurité collective, la vérification par arrêt de l'extracteur que certains appareils raccordés ne restent en fonctionnement que si l'évacuation des fumées est assurée par tirage naturel. "', personne_habilitee = '', criticite = 4 where id = 3779 | AC20: =IF(Tableau6[[#This Row],[Référence]]<>"",CONCATENATE("update aocr_ref_arbo set reglementation = '",Tableau6[[#This Row],[Référence]],"' where id = ",Tableau6[[#This Row],[id]]),"") -> update aocr_ref_arbo set reglementation = 'A. du 25-04-1985(1), art. 1 et 2.' where id = 3779
A21: 1058 | B21: Aération et ventilation | C21: Vérification Périodique 6 mois | D21: Locaux à pollution spécifique avec système de recyclage Vérification Périodique semestrielle | F21: Arrêté du 08-10-1987, art 2 et 4 CT. art. R. 4222-21 CT. art. R. 4222-22 | H21: Ecart Détecté | M21: 1 | N21: 1 | O21: 1 | P21: 0 | Q21: =Y17 -> 1285 | R21: =Z17 -> 1741 | S21: 1 | T21: 4 | V21: Locataire / Utilisateur | Y21: =VLOOKUP(A25,Feuil1!A:B,2,FALSE) -> 2 | Z21: =VLOOKUP(A25,Feuil1!A:C,3,FALSE) -> 1490 | AA21: =CONCATENATE("insert into AOCR_ref_arbo (libelle,reglementation,typologie,pere,commentaires,personne_habilitee,type_cont,pere_superieur,criticite) values ('",Tableau6[[#This Row],[Obligation]],"','",Tableau6[[#This Row],[Référence]],"',1,",Tableau6[[#This Row],[ID Domaine2]],",'",Tableau6[[#This Row],[Libellé détaillé]],"','",Tableau6[[#This Row],[Possible réalisateur]],"',3,",Tableau6[[#This Row],[ID Domaine]],",",Tableau6[[#This Row],[Urgence]],")") -> insert into AOCR_ref_arbo (libelle,reglementation,typologie,pere,commentaires,personne_habilitee,type_cont,pere_superieur,criticite) values ('Locaux à pollution spécifique avec système de recyclage Vérification Périodique semestrielle','Arrêté du 08-10-1987, art 2 et 4 CT. art. R. 4222-21 CT. art. R. 4222-22',1,1741,'','',3,1285,4) | AB21: =CONCATENATE("update aocr_ref_arbo set libelle = '",Tableau6[[#This Row],[Obligation]],"', reglementation = '",Tableau6[[#This Row],[Référence]],"', commentaires = '",Tableau6[[#This Row],[Libellé détaillé]],"', personne_habilitee = '",Tableau6[[#This Row],[Possible réalisateur]],"', criticite = ",Tableau6[[#This Row],[Urgence]]," where id = ",Tableau6[[#This Row],[id]]) -> update aocr_ref_arbo set libelle = 'Locaux à pollution spécifique avec système de recyclage Vérification Périodique semestrielle', reglementation = 'Arrêté du 08-10-1987, art 2 et 4 CT. art. R. 4222-21 CT. art. R. 4222-22', commentaires = '', personne_habilitee = '', criticite = 4 where id = 1058 | AC21: =IF(Tableau6[[#This Row],[Référence]]<>"",CONCATENATE("update aocr_ref_arbo set reglementation = '",Tableau6[[#This Row],[Référence]],"' where id = ",Tableau6[[#This Row],[id]]),"") -> update aocr_ref_arbo set reglementation = 'Arrêté du 08-10-1987, art 2 et 4 CT. art. R. 4222-21 CT. art. R. 4222-22' where id = 1058
A22: 3703 | B22: Ascenseur | C22: Carnet d'entretien | D22: Ascenseur : Carnet d''entretien | F22: CCH R125-2-1 | H22: Ecart Détecté | M22: 1 | N22: 1 | O22: 1 | P22: 0 | Q22: =Y18 -> 2 | R22: =Z18 -> 1098 | T22: 4 | V22: Propriétaire | Y22: =VLOOKUP(A26,Feuil1!A:B,2,FALSE) -> 2 | Z22: =VLOOKUP(A26,Feuil1!A:C,3,FALSE) -> 1496 | AA22: =CONCATENATE("insert into AOCR_ref_arbo (libelle,reglementation,typologie,pere,commentaires,personne_habilitee,type_cont,pere_superieur,criticite) values ('",Tableau6[[#This Row],[Obligation]],"','",Tableau6[[#This Row],[Référence]],"',1,",Tableau6[[#This Row],[ID Domaine2]],",'",Tableau6[[#This Row],[Libellé détaillé]],"','",Tableau6[[#This Row],[Possible réalisateur]],"',3,",Tableau6[[#This Row],[ID Domaine]],",",Tableau6[[#This Row],[Urgence]],")") -> insert into AOCR_ref_arbo (libelle,reglementation,typologie,pere,commentaires,personne_habilitee,type_cont,pere_superieur,criticite) values ('Ascenseur : Carnet d''entretien','CCH R125-2-1',1,1098,'','',3,2,4) | AB22: =CONCATENATE("update aocr_ref_arbo set libelle = '",Tableau6[[#This Row],[Obligation]],"', reglementation = '",Tableau6[[#This Row],[Référence]],"', commentaires = '",Tableau6[[#This Row],[Libellé détaillé]],"', personne_habilitee = '",Tableau6[[#This Row],[Possible réalisateur]],"', criticite = ",Tableau6[[#This Row],[Urgence]]," where id = ",Tableau6[[#This Row],[id]]) -> update aocr_ref_arbo set libelle = 'Ascenseur : Carnet d''entretien', reglementation = 'CCH R125-2-1', commentaires = '', personne_habilitee = '', criticite = 4 where id = 3703 | AC22: =IF(Tableau6[[#This Row],[Référence]]<>"",CONCATENATE("update aocr_ref_arbo set reglementation = '",Tableau6[[#This Row],[Référence]],"' where id = ",Tableau6[[#This Row],[id]]),"") -> update aocr_ref_arbo set reglementation = 'CCH R125-2-1' where id = 3703
A23: 1909 | B23: Ascenseur | C23: Certificat CE | D23: Ascenseur CE : Certificat CE pour les installations postérieures au 27 août 2000. | F23: Code de la construction et de l''habitation Article R125-1-1 | H23: Ecart Détecté | M23: 1 | N23: 1 | O23: 1 | P23: 0 | Q23: =Y19 -> 2 | R23: =Z19 -> 1901 | S23: 1 | T23: 5 | V23: Propriétaire | Y23: =VLOOKUP(A27,Feuil1!A:B,2,FALSE) -> 2 | Z23: =VLOOKUP(A27,Feuil1!A:C,3,FALSE) -> 1496 | AA23: =CONCATENATE("insert into AOCR_ref_arbo (libelle,reglementation,typologie,pere,commentaires,personne_habilitee,type_cont,pere_superieur,criticite) values ('",Tableau6[[#This Row],[Obligation]],"','",Tableau6[[#This Row],[Référence]],"',1,",Tableau6[[#This Row],[ID Domaine2]],",'",Tableau6[[#This Row],[Libellé détaillé]],"','",Tableau6[[#This Row],[Possible réalisateur]],"',3,",Tableau6[[#This Row],[ID Domaine]],",",Tableau6[[#This Row],[Urgence]],")") -> insert into AOCR_ref_arbo (libelle,reglementation,typologie,pere,commentaires,personne_habilitee,type_cont,pere_superieur,criticite) values ('Ascenseur CE : Certificat CE pour les installations postérieures au 27 août 2000.','Code de la construction et de l''habitation Article R125-1-1',1,1901,'','',3,2,5) | AB23: =CONCATENATE("update aocr_ref_arbo set libelle = '",Tableau6[[#This Row],[Obligation]],"', reglementation = '",Tableau6[[#This Row],[Référence]],"', commentaires = '",Tableau6[[#This Row],[Libellé détaillé]],"', personne_habilitee = '",Tableau6[[#This Row],[Possible réalisateur]],"', criticite = ",Tableau6[[#This Row],[Urgence]]," where id = ",Tableau6[[#This Row],[id]]) -> update aocr_ref_arbo set libelle = 'Ascenseur CE : Certificat CE pour les installations postérieures au 27 août 2000.', reglementation = 'Code de la construction et de l''habitation Article R125-1-1', commentaires = '', personne_habilitee = '', criticite = 5 where id = 1909 | AC23: =IF(Tableau6[[#This Row],[Référence]]<>"",CONCATENATE("update aocr_ref_arbo set reglementation = '",Tableau6[[#This Row],[Référence]],"' where id = ",Tableau6[[#This Row],[id]]),"") -> update aocr_ref_arbo set reglementation = 'Code de la construction et de l''habitation Article R125-1-1' where id = 1909
A24: 1113 | B24: Ascenseur | C24: Contrat de Maintenance | D24: Ascenseur : Contrat de Maintenance | F24: Décret n° 2012-674 du 7 mai 2012 relatif à l''entretien et au contrôle technique des ascenseurs Article 7 CCH R125-2-1 | H24: Ecart Détecté | M24: 1 | N24: 1 | O24: 1 | P24: 0 | Q24: =Y20 -> 2 | R24: =Z20 -> 1495 | S24: 1 | T24: 4 | V24: Propriétaire | Y24: =VLOOKUP(A28,Feuil1!A:B,2,FALSE) -> 2 | Z24: =VLOOKUP(A28,Feuil1!A:C,3,FALSE) -> 1295 | AA24: =CONCATENATE("insert into AOCR_ref_arbo (libelle,reglementation,typologie,pere,commentaires,personne_habilitee,type_cont,pere_superieur,criticite) values ('",Tableau6[[#This Row],[Obligation]],"','",Tableau6[[#This Row],[Référence]],"',1,",Tableau6[[#This Row],[ID Domaine2]],",'",Tableau6[[#This Row],[Libellé détaillé]],"','",Tableau6[[#This Row],[Possible réalisateur]],"',3,",Tableau6[[#This Row],[ID Domaine]],",",Tableau6[[#This Row],[Urgence]],")") -> insert into AOCR_ref_arbo (libelle,reglementation,typologie,pere,commentaires,personne_habilitee,type_cont,pere_superieur,criticite) values ('Ascenseur : Contrat de Maintenance','Décret n° 2012-674 du 7 mai 2012 relatif à l''entretien et au contrôle technique des ascenseurs Article 7 CCH R125-2-1',1,1495,'','',3,2,4) | AB24: =CONCATENATE("update aocr_ref_arbo set libelle = '",Tableau6[[#This Row],[Obligation]],"', reglementation = '",Tableau6[[#This Row],[Référence]],"', commentaires = '",Tableau6[[#This Row],[Libellé détaillé]],"', personne_habilitee = '",Tableau6[[#This Row],[Possible réalisateur]],"', criticite = ",Tableau6[[#This Row],[Urgence]]," where id = ",Tableau6[[#This Row],[id]]) -> update aocr_ref_arbo set libelle = 'Ascenseur : Contrat de Maintenance', reglementation = 'Décret n° 2012-674 du 7 mai 2012 relatif à l''entretien et au contrôle technique des ascenseurs Article 7 CCH R125-2-1', commentaires = '', personne_habilitee = '', criticite = 4 where id = 1113 | AC24: =IF(Tableau6[[#This Row],[Référence]]<>"",CONCATENATE("update aocr_ref_arbo set reglementation = '",Tableau6[[#This Row],[Référence]],"' where id = ",Tableau6[[#This Row],[id]]),"") -> update aocr_ref_arbo set reglementation = 'Décret n° 2012-674 du 7 mai 2012 relatif à l''entretien et au contrôle technique des ascenseurs Article 7 CCH R125-2-1' where id = 1113
A25: 1110 | B25: Ascenseur | C25: Contrôle Périodique 5 ans | D25: Ascenseur : Contrôle Périodique quinquennal - Contrôle Technique Sécurité des Appareils Existants (CTSAE) | E25: Le premier CTSAE : 31 décembre 2010 Les appareils sont CE depuis Juillet 2000. | F25: Code de la construction et de l''habitation Articles R125-2-4, R125-2-5 et R125-2-6 | H25: Ecart Détecté | M25: 1 | N25: 1 | O25: 1 | P25: 0 | Q25: =Y21 -> 2 | R25: =Z21 -> 1490 | S25: 1 | T25: 4 | V25: Propriétaire | Y25: =VLOOKUP(A29,Feuil1!A:B,2,FALSE) -> 2 | Z25: =VLOOKUP(A29,Feuil1!A:C,3,FALSE) -> 1295 | AA25: =CONCATENATE("insert into AOCR_ref_arbo (libelle,reglementation,typologie,pere,commentaires,personne_habilitee,type_cont,pere_superieur,criticite) values ('",Tableau6[[#This Row],[Obligation]],"','",Tableau6[[#This Row],[Référence]],"',1,",Tableau6[[#This Row],[ID Domaine2]],",'",Tableau6[[#This Row],[Libellé détaillé]],"','",Tableau6[[#This Row],[Possible réalisateur]],"',3,",Tableau6[[#This Row],[ID Domaine]],",",Tableau6[[#This Row],[Urgence]],")") -> insert into AOCR_ref_arbo (libelle,reglementation,typologie,pere,commentaires,personne_habilitee,type_cont,pere_superieur,criticite) values ('Ascenseur : Contrôle Périodique quinquennal - Contrôle Technique Sécurité des Appareils Existants (CTSAE)','Code de la construction et de l''habitation Articles R125-2-4, R125-2-5 et R125-2-6 ',1,1490,'Le premier CTSAE : 31 décembre 2010 Les appareils sont CE depuis Juillet 2000.','',3,2,4) | AB25: =CONCATENATE("update aocr_ref_arbo set libelle = '",Tableau6[[#This Row],[Obligation]],"', reglementation = '",Tableau6[[#This Row],[Référence]],"', commentaires = '",Tableau6[[#This Row],[Libellé détaillé]],"', personne_habilitee = '",Tableau6[[#This Row],[Possible réalisateur]],"', criticite = ",Tableau6[[#This Row],[Urgence]]," where id = ",Tableau6[[#This Row],[id]]) -> update aocr_ref_arbo set libelle = 'Ascenseur : Contrôle Périodique quinquennal - Contrôle Technique Sécurité des Appareils Existants (CTSAE)', reglementation = 'Code de la construction et de l''habitation Articles R125-2-4, R125-2-5 et R125-2-6 ', commentaires = 'Le premier CTSAE : 31 décembre 2010 Les appareils sont CE depuis Juillet 2000.', personne_habilitee = '', criticite = 4 where id = 1110 | AC25: =IF(Tableau6[[#This Row],[Référence]]<>"",CONCATENATE("update aocr_ref_arbo set reglementation = '",Tableau6[[#This Row],[Référence]],"' where id = ",Tableau6[[#This Row],[id]]),"") -> update aocr_ref_arbo set reglementation = 'Code de la construction et de l''habitation Articles R125-2-4, R125-2-5 et R125-2-6 ' where id = 1110
A26: 672 | B26: Ascenseur | C26: Établissement Recevant du Public (ERP) | D26: Ascenseur ERP (1er groupe et PO, Parcs de stationnement et Gares) Contrôle Périodique 5 ans Rapport de Vérification Réglementaire en Exploitation (RVRE) | E26: Vérification, fonctionnement compris, par un organisme agréé | F26: Arrêté du 25 juin 1980 Article AS 9 et PO1§3 GE6 à GE9 PS32 GA36 | H26: Ecart Détecté | M26: 0 | N26: 0 | O26: 1 | P26: 0 | Q26: =Y22 -> 2 | R26: =Z22 -> 1496 | S26: 1 | T26: 4 | V26: Locataire / Utilisateur | Y26: =VLOOKUP(A30,Feuil1!A:B,2,FALSE) -> 2 | Z26: =VLOOKUP(A30,Feuil1!A:C,3,FALSE) -> 1295 | AA26: =CONCATENATE("insert into AOCR_ref_arbo (libelle,reglementation,typologie,pere,commentaires,personne_habilitee,type_cont,pere_superieur,criticite) values ('",Tableau6[[#This Row],[Obligation]],"','",Tableau6[[#This Row],[Référence]],"',1,",Tableau6[[#This Row],[ID Domaine2]],",'",Tableau6[[#This Row],[Libellé détaillé]],"','",Tableau6[[#This Row],[Possible réalisateur]],"',3,",Tableau6[[#This Row],[ID Domaine]],",",Tableau6[[#This Row],[Urgence]],")") -> insert into AOCR_ref_arbo (libelle,reglementation,typologie,pere,commentaires,personne_habilitee,type_cont,pere_superieur,criticite) values ('Ascenseur ERP (1er groupe et PO, Parcs de stationnement et Gares) Contrôle Périodique 5 ans Rapport de Vérification Réglementaire en Exploitation (RVRE)','Arrêté du 25 juin 1980 Article AS 9 et PO1§3 GE6 à GE9 PS32 GA36',1,1496,'Vérification, fonctionnement compris, par un organisme agréé','',3,2,4) | AB26: =CONCATENATE("update aocr_ref_arbo set libelle = '",Tableau6[[#This Row],[Obligation]],"', reglementation = '",Tableau6[[#This Row],[Référence]],"', commentaires = '",Tableau6[[#This Row],[Libellé détaillé]],"', personne_habilitee = '",Tableau6[[#This Row],[Possible réalisateur]],"', criticite = ",Tableau6[[#This Row],[Urgence]]," where id = ",Tableau6[[#This Row],[id]]) -> update aocr_ref_arbo set libelle = 'Ascenseur ERP (1er groupe et PO, Parcs de stationnement et Gares) Contrôle Périodique 5 ans Rapport de Vérification Réglementaire en Exploitation (RVRE)', reglementation = 'Arrêté du 25 juin 1980 Article AS 9 et PO1§3 GE6 à GE9 PS32 GA36', commentaires = 'Vérification, fonctionnement compris, par un organisme agréé', personne_habilitee = '', criticite = 4 where id = 672 | AC26: =IF(Tableau6[[#This Row],[Référence]]<>"",CONCATENATE("update aocr_ref_arbo set reglementation = '",Tableau6[[#This Row],[Référence]],"' where id = ",Tableau6[[#This Row],[id]]),"") -> update aocr_ref_arbo set reglementation = 'Arrêté du 25 juin 1980 Article AS 9 et PO1§3 GE6 à GE9 PS32 GA36' where id = 672
A27: 1118 | B27: Ascenseur | C27: Établissement Recevant du Public (ERP) | D27: Ascenseur ERP : Contrôle à la mise en service Rapport de Vérification Réglementaire Après Travaux (RVRAT). | E27: Un Rapport de Vérification Réglementaire Après Travaux (RVRAT) doit être réalisée suite à une modification importante des ascenseurs. | F27: Arrêté du 25 juin 1980 Article AS 9 et GE6 à GE9 | H27: Ecart Détecté | M27: 0 | N27: 0 | O27: 1 | P27: 0 | Q27: =Y23 -> 2 | R27: =Z23 -> 1496 | S27: 1 | T27: 5 | V27: Propriétaire | Y27: =VLOOKUP(A31,Feuil1!A:B,2,FALSE) -> 2 | Z27: =VLOOKUP(A31,Feuil1!A:C,3,FALSE) -> 1295 | AA27: =CONCATENATE("insert into AOCR_ref_arbo (libelle,reglementation,typologie,pere,commentaires,personne_habilitee,type_cont,pere_superieur,criticite) values ('",Tableau6[[#This Row],[Obligation]],"','",Tableau6[[#This Row],[Référence]],"',1,",Tableau6[[#This Row],[ID Domaine2]],",'",Tableau6[[#This Row],[Libellé détaillé]],"','",Tableau6[[#This Row],[Possible réalisateur]],"',3,",Tableau6[[#This Row],[ID Domaine]],",",Tableau6[[#This Row],[Urgence]],")") -> insert into AOCR_ref_arbo (libelle,reglementation,typologie,pere,commentaires,personne_habilitee,type_cont,pere_superieur,criticite) values ('Ascenseur ERP : Contrôle à la mise en service Rapport de Vérification Réglementaire Après Travaux (RVRAT).','Arrêté du 25 juin 1980 Article AS 9 et GE6 à GE9',1,1496,'Un Rapport de Vérification Réglementaire Après Travaux (RVRAT) doit être réalisée suite à une modification importante des ascenseurs.','',3,2,5) | AB27: =CONCATENATE("update aocr_ref_arbo set libelle = '",Tableau6[[#This Row],[Obligation]],"', reglementation = '",Tableau6[[#This Row],[Référence]],"', commentaires = '",Tableau6[[#This Row],[Libellé détaillé]],"', personne_habilitee = '",Tableau6[[#This Row],[Possible réalisateur]],"', criticite = ",Tableau6[[#This Row],[Urgence]]," where id = ",Tableau6[[#This Row],[id]]) -> update aocr_ref_arbo set libelle = 'Ascenseur ERP : Contrôle à la mise en service Rapport de Vérification Réglementaire Après Travaux (RVRAT).', reglementation = 'Arrêté du 25 juin 1980 Article AS 9 et GE6 à GE9', commentaires = 'Un Rapport de Vérification Réglementaire Après Travaux (RVRAT) doit être réalisée suite à une modification importante des ascenseurs.', personne_habilitee = '', criticite = 5 where id = 1118 | AC27: =IF(Tableau6[[#This Row],[Référence]]<>"",CONCATENATE("update aocr_ref_arbo set reglementation = '",Tableau6[[#This Row],[Référence]],"' where id = ",Tableau6[[#This Row],[id]]),"") -> update aocr_ref_arbo set reglementation = 'Arrêté du 25 juin 1980 Article AS 9 et GE6 à GE9' where id = 1118
A28: 1301 | B28: Ascenseur | C28: Immeuble de Grande Hauteur (IGH) | D28: Ascenseur non équipé de dispositif d''appel prioritaire IGH : Contrôle Périodique annuel Rapport de Vérification Réglementaire en Exploitation (RVRE) | F28: Arrêté du 30 décembre 2011 Article GH 5 3.1.2 CCH R122-16 | H28: Ecart Détecté | M28: 0 | N28: 0 | O28: 1 | P28: 0 | Q28: =Y24 -> 2 | R28: =Z24 -> 1295 | S28: 1 | T28: 4 | V28: Locataire / Utilisateur | Y28: =VLOOKUP(A32,Feuil1!A:B,2,FALSE) -> 2 | Z28: =VLOOKUP(A32,Feuil1!A:C,3,FALSE) -> 170 | AA28: =CONCATENATE("insert into AOCR_ref_arbo (libelle,reglementation,typologie,pere,commentaires,personne_habilitee,type_cont,pere_superieur,criticite) values ('",Tableau6[[#This Row],[Obligation]],"','",Tableau6[[#This Row],[Référence]],"',1,",Tableau6[[#This Row],[ID Domaine2]],",'",Tableau6[[#This Row],[Libellé détaillé]],"','",Tableau6[[#This Row],[Possible réalisateur]],"',3,",Tableau6[[#This Row],[ID Domaine]],",",Tableau6[[#This Row],[Urgence]],")") -> insert into AOCR_ref_arbo (libelle,reglementation,typologie,pere,commentaires,personne_habilitee,type_cont,pere_superieur,criticite) values ('Ascenseur non équipé de dispositif d''appel prioritaire IGH : Contrôle Périodique annuel Rapport de Vérification Réglementaire en Exploitation (RVRE)','Arrêté du 30 décembre 2011 Article GH 5 3.1.2 CCH R122-16',1,1295,'','',3,2,4) | AB28: =CONCATENATE("update aocr_ref_arbo set libelle = '",Tableau6[[#This Row],[Obligation]],"', reglementation = '",Tableau6[[#This Row],[Référence]],"', commentaires = '",Tableau6[[#This Row],[Libellé détaillé]],"', personne_habilitee = '",Tableau6[[#This Row],[Possible réalisateur]],"', criticite = ",Tableau6[[#This Row],[Urgence]]," where id = ",Tableau6[[#This Row],[id]]) -> update aocr_ref_arbo set libelle = 'Ascenseur non équipé de dispositif d''appel prioritaire IGH : Contrôle Périodique annuel Rapport de Vérification Réglementaire en Exploitation (RVRE)', reglementation = 'Arrêté du 30 décembre 2011 Article GH 5 3.1.2 CCH R122-16', commentaires = '', personne_habilitee = '', criticite = 4 where id = 1301 | AC28: =IF(Tableau6[[#This Row],[Référence]]<>"",CONCATENATE("update aocr_ref_arbo set reglementation = '",Tableau6[[#This Row],[Référence]],"' where id = ",Tableau6[[#This Row],[id]]),"") -> update aocr_ref_arbo set reglementation = 'Arrêté du 30 décembre 2011 Article GH 5 3.1.2 CCH R122-16' where id = 1301
A29: 1300 | B29: Ascenseur | C29: Immeuble de Grande Hauteur (IGH) | D29: Ascenseur IGH : Contrôle à la mise en service Rapport de Vérification Réglementaire Après Travaux (RVRAT). | E29: Un Rapport de Vérification Réglementaire Après Travaux (RVRAT) doit être réalisée suite à une modification importante des ascenseurs. | F29: Arrêté du 30 décembre 2011 Article GH 5 § 2 Arrêté du 25 juin 1980 Article AS 9 CCH R122-16 | H29: Ecart Détecté | M29: 0 | N29: 0 | O29: 1 | P29: 0 | Q29: =Y25 -> 2 | R29: =Z25 -> 1295 | S29: 1 | T29: 5 | V29: Propriétaire | Y29: =VLOOKUP(A33,Feuil1!A:B,2,FALSE) -> 2 | Z29: =VLOOKUP(A33,Feuil1!A:C,3,FALSE) -> 170 | AA29: =CONCATENATE("insert into AOCR_ref_arbo (libelle,reglementation,typologie,pere,commentaires,personne_habilitee,type_cont,pere_superieur,criticite) values ('",Tableau6[[#This Row],[Obligation]],"','",Tableau6[[#This Row],[Référence]],"',1,",Tableau6[[#This Row],[ID Domaine2]],",'",Tableau6[[#This Row],[Libellé détaillé]],"','",Tableau6[[#This Row],[Possible réalisateur]],"',3,",Tableau6[[#This Row],[ID Domaine]],",",Tableau6[[#This Row],[Urgence]],")") -> insert into AOCR_ref_arbo (libelle,reglementation,typologie,pere,commentaires,personne_habilitee,type_cont,pere_superieur,criticite) values ('Ascenseur IGH : Contrôle à la mise en service Rapport de Vérification Réglementaire Après Travaux (RVRAT).','Arrêté du 30 décembre 2011 Article GH 5 § 2 Arrêté du 25 juin 1980 Article AS 9 CCH R122-16',1,1295,'Un Rapport de Vérification Réglementaire Après Travaux (RVRAT) doit être réalisée suite à une modification importante des ascenseurs.','',3,2,5) | AB29: =CONCATENATE("update aocr_ref_arbo set libelle = '",Tableau6[[#This Row],[Obligation]],"', reglementation = '",Tableau6[[#This Row],[Référence]],"', commentaires = '",Tableau6[[#This Row],[Libellé détaillé]],"', personne_habilitee = '",Tableau6[[#This Row],[Possible réalisateur]],"', criticite = ",Tableau6[[#This Row],[Urgence]]," where id = ",Tableau6[[#This Row],[id]]) -> update aocr_ref_arbo set libelle = 'Ascenseur IGH : Contrôle à la mise en service Rapport de Vérification Réglementaire Après Travaux (RVRAT).', reglementation = 'Arrêté du 30 décembre 2011 Article GH 5 § 2 Arrêté du 25 juin 1980 Article AS 9 CCH R122-16', commentaires = 'Un Rapport de Vérification Réglementaire Après Travaux (RVRAT) doit être réalisée suite à une modification importante des ascenseurs.', personne_habilitee = '', criticite = 5 where id = 1300 | AC29: =IF(Tableau6[[#This Row],[Référence]]<>"",CONCATENATE("update aocr_ref_arbo set reglementation = '",Tableau6[[#This Row],[Référence]],"' where id = ",Tableau6[[#This Row],[id]]),"") -> update aocr_ref_arbo set reglementation = 'Arrêté du 30 décembre 2011 Article GH 5 § 2 Arrêté du 25 juin 1980 Article AS 9 CCH R122-16' where id = 1300
A30: 1877 | B30: Ascenseur | C30: Immeuble de Grande Hauteur (IGH) | D30: Ascenseur équipé de dispositif d''appel prioritaire IGH : Contrôle Périodique semestriel Rapport de Vérification Réglementaire en Exploitation (RVRE) | F30: Arrêté du 30 décembre 2011 Article GH 5 3.1.1 CCH R122-16 | H30: Ecart Détecté | M30: 0 | N30: 0 | O30: 1 | P30: 0 | Q30: =Y26 -> 2 | R30: =Z26 -> 1295 | S30: 1 | T30: 4 | V30: Locataire / Utilisateur | Y30: =VLOOKUP(A34,Feuil1!A:B,2,FALSE) -> 2 | Z30: =VLOOKUP(A34,Feuil1!A:C,3,FALSE) -> 170 | AA30: =CONCATENATE("insert into AOCR_ref_arbo (libelle,reglementation,typologie,pere,commentaires,personne_habilitee,type_cont,pere_superieur,criticite) values ('",Tableau6[[#This Row],[Obligation]],"','",Tableau6[[#This Row],[Référence]],"',1,",Tableau6[[#This Row],[ID Domaine2]],",'",Tableau6[[#This Row],[Libellé détaillé]],"','",Tableau6[[#This Row],[Possible réalisateur]],"',3,",Tableau6[[#This Row],[ID Domaine]],",",Tableau6[[#This Row],[Urgence]],")") -> insert into AOCR_ref_arbo (libelle,reglementation,typologie,pere,commentaires,personne_habilitee,type_cont,pere_superieur,criticite) values ('Ascenseur équipé de dispositif d''appel prioritaire IGH : Contrôle Périodique semestriel Rapport de Vérification Réglementaire en Exploitation (RVRE)','Arrêté du 30 décembre 2011 Article GH 5 3.1.1 CCH R122-16',1,1295,'','',3,2,4) | AB30: =CONCATENATE("update aocr_ref_arbo set libelle = '",Tableau6[[#This Row],[Obligation]],"', reglementation = '",Tableau6[[#This Row],[Référence]],"', commentaires = '",Tableau6[[#This Row],[Libellé détaillé]],"', personne_habilitee = '",Tableau6[[#This Row],[Possible réalisateur]],"', criticite = ",Tableau6[[#This Row],[Urgence]]," where id = ",Tableau6[[#This Row],[id]]) -> update aocr_ref_arbo set libelle = 'Ascenseur équipé de dispositif d''appel prioritaire IGH : Contrôle Périodique semestriel Rapport de Vérification Réglementaire en Exploitation (RVRE)', reglementation = 'Arrêté du 30 décembre 2011 Article GH 5 3.1.1 CCH R122-16', commentaires = '', personne_habilitee = '', criticite = 4 where id = 1877 | AC30: =IF(Tableau6[[#This Row],[Référence]]<>"",CONCATENATE("update aocr_ref_arbo set reglementation = '",Tableau6[[#This Row],[Référence]],"' where id = ",Tableau6[[#This Row],[id]]),"") -> update aocr_ref_arbo set reglementation = 'Arrêté du 30 décembre 2011 Article GH 5 3.1.1 CCH R122-16' where id = 1877
A31: 3704 | B31: Ascenseur | C31: Immeuble de Grande Hauteur (IGH) de type TC | D31: Ascenseur dans les immeubles à usage de Tour de Contrôle (GH TC) avec effectif > ou égal à 19 personnes : Contrôle Périodique semestriel Rapport de Vérification Réglementaire en Exploitation (RVRE) | F31: Arrêté du 30 décembre 2011 A. du 30-12-2011, point 18.1 du cahier des charges annexé à l''art. GHTC. CCH R122-2 | H31: Ecart Détecté | M31: 0 | N31: 0 | O31: 1 | P31: 0 | Q31: =Y27 -> 2 | R31: =Z27 -> 1295 | S31: 1 | T31: 4 | V31: Locataire / Utilisateur | Y31: =VLOOKUP(A35,Feuil1!A:B,2,FALSE) -> 2 | Z31: =VLOOKUP(A35,Feuil1!A:C,3,FALSE) -> 1499 | AA31: =CONCATENATE("insert into AOCR_ref_arbo (libelle,reglementation,typologie,pere,commentaires,personne_habilitee,type_cont,pere_superieur,criticite) values ('",Tableau6[[#This Row],[Obligation]],"','",Tableau6[[#This Row],[Référence]],"',1,",Tableau6[[#This Row],[ID Domaine2]],",'",Tableau6[[#This Row],[Libellé détaillé]],"','",Tableau6[[#This Row],[Possible réalisateur]],"',3,",Tableau6[[#This Row],[ID Domaine]],",",Tableau6[[#This Row],[Urgence]],")") -> insert into AOCR_ref_arbo (libelle,reglementation,typologie,pere,commentaires,personne_habilitee,type_cont,pere_superieur,criticite) values ('Ascenseur dans les immeubles à usage de Tour de Contrôle (GH TC) avec effectif > ou égal à 19 personnes : Contrôle Périodique semestriel Rapport de Vérification Réglementaire en Exploitation (RVRE)','Arrêté du 30 décembre 2011 A. du 30-12-2011, point 18.1 du cahier des charges annexé à l''art. GHTC. CCH R122-2',1,1295,'','',3,2,4) | AB31: =CONCATENATE("update aocr_ref_arbo set libelle = '",Tableau6[[#This Row],[Obligation]],"', reglementation = '",Tableau6[[#This Row],[Référence]],"', commentaires = '",Tableau6[[#This Row],[Libellé détaillé]],"', personne_habilitee = '",Tableau6[[#This Row],[Possible réalisateur]],"', criticite = ",Tableau6[[#This Row],[Urgence]]," where id = ",Tableau6[[#This Row],[id]]) -> update aocr_ref_arbo set libelle = 'Ascenseur dans les immeubles à usage de Tour de Contrôle (GH TC) avec effectif > ou égal à 19 personnes : Contrôle Périodique semestriel Rapport de Vérification Réglementaire en Exploitation (RVRE)', reglementation = 'Arrêté du 30 décembre 2011 A. du 30-12-2011, point 18.1 du cahier des charges annexé à l''art. GHTC. CCH R122-2', commentaires = '', personne_habilitee = '', criticite = 4 where id = 3704 | AC31: =IF(Tableau6[[#This Row],[Référence]]<>"",CONCATENATE("update aocr_ref_arbo set reglementation = '",Tableau6[[#This Row],[Référence]],"' where id = ",Tableau6[[#This Row],[id]]),"") -> update aocr_ref_arbo set reglementation = 'Arrêté du 30 décembre 2011 A. du 30-12-2011, point 18.1 du cahier des charges annexé à l''art. GHTC. CCH R122-2' where id = 3704
A32: 1115 | B32: Ascenseur | C32: Mise en conformité | D32: Ascenseurs installé avant le 27 août 2000 : Mise en conformité avant le 31 décembre 2010. | E32: Avant le 31 décembre 2010. 1. Des serrures munies de dispositifs de contrôle de la fermeture et du verrouillage des portes palières ; 2. Lorsqu''il est nécessaire de prévenir des actes de nature à porter atteinte au verrouillage de la porte palière, un dispositif empêchant ou limitant de tels actes ; 3. Un dispositif de détection de la présence des personnes destiné à les protéger contre le choc des portes coulissantes lors de leur fermeture ; 4. La clôture de la gaine d''ascenseur empêchant l''accès à cette gaine et aux éléments de déverrouillage des serrures de porte palière ; 5. Pour les ascenseurs électriques, un parachute de cabine et un limiteur de vitesse en descente ; 6. Un dispositif destiné à éviter toute chute en gaine lorsque la cabine est immobilisée en dehors de la zone de déverrouillage ; 7. Une commande de manœuvre d''inspection et d''arrêt de la cabine en vue de protéger les personnels d''intervention opérant sur le toit de la cabine, en gaine ou en cuvette ; 8. Des dispositifs permettant aux personnels d''intervention d''accéder sans danger aux locaux de machines ou de poulies ; 9. Un système de verrouillage des portes et portillons destinés à la visite technique de la gaine et de la cuvette ainsi que des portes de secours, avec une commande automatique de l''arrêt de l''ascenseur lors de l''ouverture de ces portes et portillons par les personnels d''intervention. | F32: Code de la construction et de l''habitation Article R125-1-2 A. du 18-11-2004 (travaux de sécurité) | H32: Ecart Détecté | M32: 1 | N32: 1 | O32: 1 | P32: 0 | Q32: =Y28 -> 2 | R32: =Z28 -> 170 | S32: 1 | T32: 5 | V32: Propriétaire | W32: Oui | Y32: =VLOOKUP(A36,Feuil1!A:B,2,FALSE) -> 2 | Z32: =VLOOKUP(A36,Feuil1!A:C,3,FALSE) -> 1101 | AA32: =CONCATENATE("insert into AOCR_ref_arbo (libelle,reglementation,typologie,pere,commentaires,personne_habilitee,type_cont,pere_superieur,criticite) values ('",Tableau6[[#This Row],[Obligation]],"','",Tableau6[[#This Row],[Référence]],"',1,",Tableau6[[#This Row],[ID Domaine2]],",'",Tableau6[[#This Row],[Libellé détaillé]],"','",Tableau6[[#This Row],[Possible réalisateur]],"',3,",Tableau6[[#This Row],[ID Domaine]],",",Tableau6[[#This Row],[Urgence]],")") -> insert into AOCR_ref_arbo (libelle,reglementation,typologie,pere,commentaires,personne_habilitee,type_cont,pere_superieur,criticite) values ('Ascenseurs installé avant le 27 août 2000 : Mise en conformité avant le 31 décembre 2010.','Code de la construction et de l''habitation Article R125-1-2 A. du 18-11-2004 (travaux de sécurité)',1,170,'Avant le 31 décembre 2010. 1. Des serrures munies de dispositifs de contrôle de la fermeture et du verrouillage des portes palières ; 2. Lorsqu''il est nécessaire de prévenir des actes de nature à porter atteinte au verrouillage de la porte palière, un dispositif empêchant ou limitant de tels actes ; 3. Un dispositif de détection de la présence des personnes destiné à les protéger contre le choc des portes coulissantes lors de leur fermeture ; 4. La clôture de la gaine d''ascenseur empêchant l''accès à cette gaine et aux éléments de déverrouillage des serrures de porte palière ; 5. Pour les ascenseurs électriques, un parachute de cabine et un limiteur de vitesse en descente ; 6. Un dispositif destiné à éviter toute chute en gaine lorsque la cabine est immobilisée en dehors de la zone de déverrouillage ; 7. Une commande de manœuvre d''inspection et d''arrêt de la cabine en vue de protéger les personnels d''intervention opérant sur le toit de la cabine, en gaine ou en cuvette ; 8. Des dispositifs permettant aux personnels d''intervention d''accéder sans danger aux locaux de machines ou de poulies ; 9. Un système de verrouillage des portes et portillons destinés à la visite technique de la gaine et de la cuvette ainsi que des portes de secours, avec une commande automatique de l''arrêt de l''ascenseur lors de l''ouverture de ces portes et portillons par les personnels d''intervention.','',3,2,5) | AB32: =CONCATENATE("update aocr_ref_arbo set libelle = '",Tableau6[[#This Row],[Obligation]],"', reglementation = '",Tableau6[[#This Row],[Référence]],"', commentaires = '",Tableau6[[#This Row],[Libellé détaillé]],"', personne_habilitee = '",Tableau6[[#This Row],[Possible réalisateur]],"', criticite = ",Tableau6[[#This Row],[Urgence]]," where id = ",Tableau6[[#This Row],[id]]) -> update aocr_ref_arbo set libelle = 'Ascenseurs installé avant le 27 août 2000 : Mise en conformité avant le 31 décembre 2010.', reglementation = 'Code de la construction et de l''habitation Article R125-1-2 A. du 18-11-2004 (travaux de sécurité)', commentaires = 'Avant le 31 décembre 2010. 1. Des serrures munies de dispositifs de contrôle de la fermeture et du verrouillage des portes palières ; 2. Lorsqu''il est nécessaire de prévenir des actes de nature à porter atteinte au verrouillage de la porte palière, un dispositif empêchant ou limitant de tels actes ; 3. Un dispositif de détection de la présence des personnes destiné à les protéger contre le choc des portes coulissantes lors de leur fermeture ; 4. La clôture de la gaine d''ascenseur empêchant l''accès à cette gaine et aux éléments de déverrouillage des serrures de porte palière ; 5. Pour les ascenseurs électriques, un parachute de cabine et un limiteur de vitesse en descente ; 6. Un dispositif destiné à éviter toute chute en gaine lorsque la cabine est immobilisée en dehors de la zone de déverrouillage ; 7. Une commande de manœuvre d''inspection et d''arrêt de la cabine en vue de protéger les personnels d''intervention opérant sur le toit de la cabine, en gaine ou en cuvette ; 8. Des dispositifs permettant aux personnels d''intervention d''accéder sans danger aux locaux de machines ou de poulies ; 9. Un système de verrouillage des portes et portillons destinés à la visite technique de la gaine et de la cuvette ainsi que des portes de secours, avec une commande automatique de l''arrêt de l''ascenseur lors de l''ouverture de ces portes et portillons par les personnels d''intervention.', personne_habilitee = '', criticite = 5 where id = 1115 | AC32: =IF(Tableau6[[#This Row],[Référence]]<>"",CONCATENATE("update aocr_ref_arbo set reglementation = '",Tableau6[[#This Row],[Référence]],"' where id = ",Tableau6[[#This Row],[id]]),"") -> update aocr_ref_arbo set reglementation = 'Code de la construction et de l''habitation Article R125-1-2 A. du 18-11-2004 (travaux de sécurité)' where id = 1115
A33: 1302 | B33: Ascenseur | C33: Mise en conformité | D33: Ascenseurs installé avant le 27 août 2000 : Mise en conformité avant le 3 juillet 2014. | E33: Avant le 3 juillet 2014 : 1. Dans les ascenseurs des établissements recevant du public mentionnés à l''article L. 111-7-3 installés avant le 1er janvier 1983, un système de contrôle de l''arrêt et du maintien à niveau de la cabine, à tous les niveaux desservis. 2. Un système de téléalarme entre la cabine et un service d''intervention et un éclairage de secours en cabine ; 3. Une résistance mécanique suffisante des portes palières lorsqu''elles comportent un vitrage ; 4. Pour les ascenseurs hydrauliques, un système de prévention des risques de chute libre, de dérive et d''excès de vitesse de la cabine ; 5. Une protection avec marquage ou signalisation éliminant le risque de contact direct des personnels d''intervention avec des composants ou conducteurs nus sous tension, dans les armoires de commande, les armoires électriques et les tableaux d''arrivée de courant ; 6. Un dispositif de protection des personnels d''intervention contre le risque de happement par les organes mobiles de transmission, notamment les poulies, câbles ou courroies ; 7. Un éclairage fixe du local de machines ou de poulies assurant un éclairement suffisant des zones de travail et de circulation. | F33: Code de la construction et de l''habitation Article R125-1-2 A. du 18-11-2004 (travaux de sécurité) | H33: Ecart Détecté | M33: 1 | N33: 1 | O33: 1 | P33: 0 | Q33: =Y29 -> 2 | R33: =Z29 -> 170 | S33: 1 | T33: 5 | V33: Propriétaire | W33: Oui | Y33: =VLOOKUP(A37,Feuil1!A:B,2,FALSE) -> 2 | Z33: =VLOOKUP(A37,Feuil1!A:C,3,FALSE) -> 1497 | AA33: =CONCATENATE("insert into AOCR_ref_arbo (libelle,reglementation,typologie,pere,commentaires,personne_habilitee,type_cont,pere_superieur,criticite) values ('",Tableau6[[#This Row],[Obligation]],"','",Tableau6[[#This Row],[Référence]],"',1,",Tableau6[[#This Row],[ID Domaine2]],",'",Tableau6[[#This Row],[Libellé détaillé]],"','",Tableau6[[#This Row],[Possible réalisateur]],"',3,",Tableau6[[#This Row],[ID Domaine]],",",Tableau6[[#This Row],[Urgence]],")") -> insert into AOCR_ref_arbo (libelle,reglementation,typologie,pere,commentaires,personne_habilitee,type_cont,pere_superieur,criticite) values ('Ascenseurs installé avant le 27 août 2000 : Mise en conformité avant le 3 juillet 2014.','Code de la construction et de l''habitation Article R125-1-2 A. du 18-11-2004 (travaux de sécurité)',1,170,'Avant le 3 juillet 2014 : 1. Dans les ascenseurs des établissements recevant du public mentionnés à l''article L. 111-7-3 installés avant le 1er janvier 1983, un système de contrôle de l''arrêt et du maintien à niveau de la cabine, à tous les niveaux desservis. 2. Un système de téléalarme entre la cabine et un service d''intervention et un éclairage de secours en cabine ; 3. Une résistance mécanique suffisante des portes palières lorsqu''elles comportent un vitrage ; 4. Pour les ascenseurs hydrauliques, un système de prévention des risques de chute libre, de dérive et d''excès de vitesse de la cabine ; 5. Une protection avec marquage ou signalisation éliminant le risque de contact direct des personnels d''intervention avec des composants ou conducteurs nus sous tension, dans les armoires de commande, les armoires électriques et les tableaux d''arrivée de courant ; 6. Un dispositif de protection des personnels d''intervention contre le risque de happement par les organes mobiles de transmission, notamment les poulies, câbles ou courroies ; 7. Un éclairage fixe du local de machines ou de poulies assurant un éclairement suffisant des zones de travail et de circulation.','',3,2,5) | AB33: =CONCATENATE("update aocr_ref_arbo set libelle = '",Tableau6[[#This Row],[Obligation]],"', reglementation = '",Tableau6[[#This Row],[Référence]],"', commentaires = '",Tableau6[[#This Row],[Libellé détaillé]],"', personne_habilitee = '",Tableau6[[#This Row],[Possible réalisateur]],"', criticite = ",Tableau6[[#This Row],[Urgence]]," where id = ",Tableau6[[#This Row],[id]]) -> update aocr_ref_arbo set libelle = 'Ascenseurs installé avant le 27 août 2000 : Mise en conformité avant le 3 juillet 2014.', reglementation = 'Code de la construction et de l''habitation Article R125-1-2 A. du 18-11-2004 (travaux de sécurité)', commentaires = 'Avant le 3 juillet 2014 : 1. Dans les ascenseurs des établissements recevant du public mentionnés à l''article L. 111-7-3 installés avant le 1er janvier 1983, un système de contrôle de l''arrêt et du maintien à niveau de la cabine, à tous les niveaux desservis. 2. Un système de téléalarme entre la cabine et un service d''intervention et un éclairage de secours en cabine ; 3. Une résistance mécanique suffisante des portes palières lorsqu''elles comportent un vitrage ; 4. Pour les ascenseurs hydrauliques, un système de prévention des risques de chute libre, de dérive et d''excès de vitesse de la cabine ; 5. Une protection avec marquage ou signalisation éliminant le risque de contact direct des personnels d''intervention avec des composants ou conducteurs nus sous tension, dans les armoires de commande, les armoires électriques et les tableaux d''arrivée de courant ; 6. Un dispositif de protection des personnels d''intervention contre le risque de happement par les organes mobiles de transmission, notamment les poulies, câbles ou courroies ; 7. Un éclairage fixe du local de machines ou de poulies assurant un éclairement suffisant des zones de travail et de circulation.', personne_habilitee = '', criticite = 5 where id = 1302 | AC33: =IF(Tableau6[[#This Row],[Référence]]<>"",CONCATENATE("update aocr_ref_arbo set reglementation = '",Tableau6[[#This Row],[Référence]],"' where id = ",Tableau6[[#This Row],[id]]),"") -> update aocr_ref_arbo set reglementation = 'Code de la construction et de l''habitation Article R125-1-2 A. du 18-11-2004 (travaux de sécurité)' where id = 1302
A34: 1303 | B34: Ascenseur | C34: Mise en conformité | D34: Ascenseurs installé avant le 27 août 2000 : Mise en conformité avant le 3 juillet 2018. | E34: Avant le 3 juillet 2018 : 1. Dans les ascenseurs des établissements recevant du public mentionnés à l''article L. 111-7-3 installés après le 31 décembre 1982, un système de contrôle de l''arrêt et du maintien à niveau de la cabine, à tous les niveaux desservis. 2. Dans les ascenseurs électriques à adhérence, un système de protection contre la vitesse excessive de la cabine en montée. | F34: Code de la construction et de l''habitation Article R125-1-2 A. du 18-11-2004 (travaux de sécurité) | H34: Ecart Détecté | M34: 1 | N34: 1 | O34: 1 | P34: 0 | Q34: =Y30 -> 2 | R34: =Z30 -> 170 | S34: 1 | T34: 5 | V34: Propriétaire | W34: Oui | Y34: =VLOOKUP(A38,Feuil1!A:B,2,FALSE) -> 2 | Z34: =VLOOKUP(A38,Feuil1!A:C,3,FALSE) -> 1497 | AA34: =CONCATENATE("insert into AOCR_ref_arbo (libelle,reglementation,typologie,pere,commentaires,personne_habilitee,type_cont,pere_superieur,criticite) values ('",Tableau6[[#This Row],[Obligation]],"','",Tableau6[[#This Row],[Référence]],"',1,",Tableau6[[#This Row],[ID Domaine2]],",'",Tableau6[[#This Row],[Libellé détaillé]],"','",Tableau6[[#This Row],[Possible réalisateur]],"',3,",Tableau6[[#This Row],[ID Domaine]],",",Tableau6[[#This Row],[Urgence]],")") -> insert into AOCR_ref_arbo (libelle,reglementation,typologie,pere,commentaires,personne_habilitee,type_cont,pere_superieur,criticite) values ('Ascenseurs installé avant le 27 août 2000 : Mise en conformité avant le 3 juillet 2018.','Code de la construction et de l''habitation Article R125-1-2 A. du 18-11-2004 (travaux de sécurité)',1,170,'Avant le 3 juillet 2018 : 1. Dans les ascenseurs des établissements recevant du public mentionnés à l''article L. 111-7-3 installés après le 31 décembre 1982, un système de contrôle de l''arrêt et du maintien à niveau de la cabine, à tous les niveaux desservis. 2. Dans les ascenseurs électriques à adhérence, un système de protection contre la vitesse excessive de la cabine en montée.','',3,2,5) | AB34: =CONCATENATE("update aocr_ref_arbo set libelle = '",Tableau6[[#This Row],[Obligation]],"', reglementation = '",Tableau6[[#This Row],[Référence]],"', commentaires = '",Tableau6[[#This Row],[Libellé détaillé]],"', personne_habilitee = '",Tableau6[[#This Row],[Possible réalisateur]],"', criticite = ",Tableau6[[#This Row],[Urgence]]," where id = ",Tableau6[[#This Row],[id]]) -> update aocr_ref_arbo set libelle = 'Ascenseurs installé avant le 27 août 2000 : Mise en conformité avant le 3 juillet 2018.', reglementation = 'Code de la construction et de l''habitation Article R125-1-2 A. du 18-11-2004 (travaux de sécurité)', commentaires = 'Avant le 3 juillet 2018 : 1. Dans les ascenseurs des établissements recevant du public mentionnés à l''article L. 111-7-3 installés après le 31 décembre 1982, un système de contrôle de l''arrêt et du maintien à niveau de la cabine, à tous les niveaux desservis. 2. Dans les ascenseurs électriques à adhérence, un système de protection contre la vitesse excessive de la cabine en montée.', personne_habilitee = '', criticite = 5 where id = 1303 | AC34: =IF(Tableau6[[#This Row],[Référence]]<>"",CONCATENATE("update aocr_ref_arbo set reglementation = '",Tableau6[[#This Row],[Référence]],"' where id = ",Tableau6[[#This Row],[id]]),"") -> update aocr_ref_arbo set reglementation = 'Code de la construction et de l''habitation Article R125-1-2 A. du 18-11-2004 (travaux de sécurité)' where id = 1303
A35: 1114 | B35: Ascenseur | C35: Rapport d'activité 1 an | D35: Ascenseur : Un rapport annuel d''activité des ascenseurs est fourni par la société de maintenance. | E35: Le rapport d’activités doit comporter, notamment, les renseignements suivants : - l’inventaire mis à jour du matériel mis en place ; - le bilan des interventions indiquant : o le nombre de pannes et de dépannages ; o le nombre d’interventions de déblocage des personnes en cabine ; o la date, la durée et la nature des interventions ; o la durée et le temps total d’indisponibilité. - la date et la nature des travaux effectués au cours des visites d’entretien, et dans le cadre de prestations complémentaires ; - des informations générales relatives à la sécurité, aux dégradations éventuelles (actes de vandalisme, et autres déprédations) : notamment les travaux modificatifs avec la justification du maintien du niveau de sécurité et du marquage CE des composants de sécurité ; - l’état des installations et les propositions d’amélioration | F35: Code de la construction et de l''habitation Article R125-2-1 Article 2 chapitre III | H35: Ecart Détecté | M35: 1 | N35: 1 | O35: 1 | P35: 0 | Q35: =Y31 -> 2 | R35: =Z31 -> 1499 | S35: 1 | T35: 4 | V35: Locataire / Utilisateur | Y35: =VLOOKUP(A39,Feuil1!A:B,2,FALSE) -> 2 | Z35: =VLOOKUP(A39,Feuil1!A:C,3,FALSE) -> 1489 | AA35: =CONCATENATE("insert into AOCR_ref_arbo (libelle,reglementation,typologie,pere,commentaires,personne_habilitee,type_cont,pere_superieur,criticite) values ('",Tableau6[[#This Row],[Obligation]],"','",Tableau6[[#This Row],[Référence]],"',1,",Tableau6[[#This Row],[ID Domaine2]],",'",Tableau6[[#This Row],[Libellé détaillé]],"','",Tableau6[[#This Row],[Possible réalisateur]],"',3,",Tableau6[[#This Row],[ID Domaine]],",",Tableau6[[#This Row],[Urgence]],")") -> insert into AOCR_ref_arbo (libelle,reglementation,typologie,pere,commentaires,personne_habilitee,type_cont,pere_superieur,criticite) values ('Ascenseur : Un rapport annuel d''activité des ascenseurs est fourni par la société de maintenance.','Code de la construction et de l''habitation Article R125-2-1 Article 2 chapitre III',1,1499,'Le rapport d’activités doit comporter, notamment, les renseignements suivants : - l’inventaire mis à jour du matériel mis en place ; - le bilan des interventions indiquant : o le nombre de pannes et de dépannages ; o le nombre d’interventions de déblocage des personnes en cabine ; o la date, la durée et la nature des interventions ; o la durée et le temps total d’indisponibilité. - la date et la nature des travaux effectués au cours des visites d’entretien, et dans le cadre de prestations complémentaires ; - des informations générales relatives à la sécurité, aux dégradations éventuelles (actes de vandalisme, et autres déprédations) : notamment les travaux modificatifs avec la justification du maintien du niveau de sécurité et du marquage CE des composants de sécurité ; - l’état des installations et les propositions d’amélioration','',3,2,4) | AB35: =CONCATENATE("update aocr_ref_arbo set libelle = '",Tableau6[[#This Row],[Obligation]],"', reglementation = '",Tableau6[[#This Row],[Référence]],"', commentaires = '",Tableau6[[#This Row],[Libellé détaillé]],"', personne_habilitee = '",Tableau6[[#This Row],[Possible réalisateur]],"', criticite = ",Tableau6[[#This Row],[Urgence]]," where id = ",Tableau6[[#This Row],[id]]) -> update aocr_ref_arbo set libelle = 'Ascenseur : Un rapport annuel d''activité des ascenseurs est fourni par la société de maintenance.', reglementation = 'Code de la construction et de l''habitation Article R125-2-1 Article 2 chapitre III', commentaires = 'Le rapport d’activités doit comporter, notamment, les renseignements suivants : - l’inventaire mis à jour du matériel mis en place ; - le bilan des interventions indiquant : o le nombre de pannes et de dépannages ; o le nombre d’interventions de déblocage des personnes en cabine ; o la date, la durée et la nature des interventions ; o la durée et le temps total d’indisponibilité. - la date et la nature des travaux effectués au cours des visites d’entretien, et dans le cadre de prestations complémentaires ; - des informations générales relatives à la sécurité, aux dégradations éventuelles (actes de vandalisme, et autres déprédations) : notamment les travaux modificatifs avec la justification du maintien du niveau de sécurité et du marquage CE des composants de sécurité ; - l’état des installations et les propositions d’amélioration', personne_habilitee = '', criticite = 4 where id = 1114 | AC35: =IF(Tableau6[[#This Row],[Référence]]<>"",CONCATENATE("update aocr_ref_arbo set reglementation = '",Tableau6[[#This Row],[Référence]],"' where id = ",Tableau6[[#This Row],[id]]),"") -> update aocr_ref_arbo set reglementation = 'Code de la construction et de l''habitation Article R125-2-1 Article 2 chapitre III' where id = 1114
A36: 1116 | B36: Ascenseur | C36: Registre de sécurité | D36: Ascenseurs, montes charges et élévateurs de personnes dont la vitesse n''excède pas 0,15 m/s : Registre de sécurité Les résultats des vérifications, des contrôles et des maintenances doivent être portés sur le registre sécurité. | F36: Code de la construction et de l''habitation Article R123-51; Code de la construction et de l''habitation Article R122-29 CDT Article L4711-5 | H36: Ecart Détecté | M36: 1 | N36: 1 | O36: 1 | P36: 0 | Q36: =Y32 -> 2 | R36: =Z32 -> 1101 | S36: 1 | T36: 4 | V36: Locataire / Utilisateur | Y36: =VLOOKUP(A40,Feuil1!A:B,2,FALSE) -> 2 | Z36: =VLOOKUP(A40,Feuil1!A:C,3,FALSE) -> 1491 | AA36: =CONCATENATE("insert into AOCR_ref_arbo (libelle,reglementation,typologie,pere,commentaires,personne_habilitee,type_cont,pere_superieur,criticite) values ('",Tableau6[[#This Row],[Obligation]],"','",Tableau6[[#This Row],[Référence]],"',1,",Tableau6[[#This Row],[ID Domaine2]],",'",Tableau6[[#This Row],[Libellé détaillé]],"','",Tableau6[[#This Row],[Possible réalisateur]],"',3,",Tableau6[[#This Row],[ID Domaine]],",",Tableau6[[#This Row],[Urgence]],")") -> insert into AOCR_ref_arbo (libelle,reglementation,typologie,pere,commentaires,personne_habilitee,type_cont,pere_superieur,criticite) values ('Ascenseurs, montes charges et élévateurs de personnes dont la vitesse n''excède pas 0,15 m/s : Registre de sécurité Les résultats des vérifications, des contrôles et des maintenances doivent être portés sur le registre sécurité.','Code de la construction et de l''habitation Article R123-51; Code de la construction et de l''habitation Article R122-29 CDT Article L4711-5',1,1101,'','',3,2,4) | AB36: =CONCATENATE("update aocr_ref_arbo set libelle = '",Tableau6[[#This Row],[Obligation]],"', reglementation = '",Tableau6[[#This Row],[Référence]],"', commentaires = '",Tableau6[[#This Row],[Libellé détaillé]],"', personne_habilitee = '",Tableau6[[#This Row],[Possible réalisateur]],"', criticite = ",Tableau6[[#This Row],[Urgence]]," where id = ",Tableau6[[#This Row],[id]]) -> update aocr_ref_arbo set libelle = 'Ascenseurs, montes charges et élévateurs de personnes dont la vitesse n''excède pas 0,15 m/s : Registre de sécurité Les résultats des vérifications, des contrôles et des maintenances doivent être portés sur le registre sécurité.', reglementation = 'Code de la construction et de l''habitation Article R123-51; Code de la construction et de l''habitation Article R122-29 CDT Article L4711-5', commentaires = '', personne_habilitee = '', criticite = 4 where id = 1116 | AC36: =IF(Tableau6[[#This Row],[Référence]]<>"",CONCATENATE("update aocr_ref_arbo set reglementation = '",Tableau6[[#This Row],[Référence]],"' where id = ",Tableau6[[#This Row],[id]]),"") -> update aocr_ref_arbo set reglementation = 'Code de la construction et de l''habitation Article R123-51; Code de la construction et de l''habitation Article R122-29 CDT Article L4711-5' where id = 1116
A37: 1122 | B37: Ascenseur | C37: Vérification Périodique 1 an | D37: Ascenseur, monte charges et élévateur de personnes dont la vitesse n''excède pas 0,15 m/s : Vérification Périodique annuelle | E37: Cette visite comporte un essai de fonctionnement et un examen de l''état de conservation. Les ascenseurs sont dispensés de cette vérification l''année au cours de laquelle s''effectue le contrôle technique quinquennal. L''employeur est dispensé de l''essai de l''efficacité du fonctionnement du dispositif parachute ou de l''équipement assurant une fonction équivalente s''il dispose d''un document assurant que le prestataire du contrat d''entretien a réalisé cette vérification. | F37: Arrêté du 29 décembre 2010 relatif aux vérifications générales périodiques portant sur les ascenseurs et les monte-charges ainsi que sur les élévateurs de personnes n''excédant pas une vitesse de 0,15 m/s, installés à demeure, et modifiant l''arrêté du 1er mars 2004 modifié relatif aux vérifications des appareils et accessoires de levage Article 6 R4323-24 à R4323-27 | H37: Ecart Détecté | M37: 1 | N37: 1 | O37: 1 | P37: 0 | Q37: =Y33 -> 2 | R37: =Z33 -> 1497 | S37: 1 | T37: 4 | V37: Locataire / Utilisateur | Y37: =VLOOKUP(A41,Feuil1!A:B,2,FALSE) -> 432 | Z37: =VLOOKUP(A41,Feuil1!A:C,3,FALSE) -> 1668 | AA37: =CONCATENATE("insert into AOCR_ref_arbo (libelle,reglementation,typologie,pere,commentaires,personne_habilitee,type_cont,pere_superieur,criticite) values ('",Tableau6[[#This Row],[Obligation]],"','",Tableau6[[#This Row],[Référence]],"',1,",Tableau6[[#This Row],[ID Domaine2]],",'",Tableau6[[#This Row],[Libellé détaillé]],"','",Tableau6[[#This Row],[Possible réalisateur]],"',3,",Tableau6[[#This Row],[ID Domaine]],",",Tableau6[[#This Row],[Urgence]],")") -> insert into AOCR_ref_arbo (libelle,reglementation,typologie,pere,commentaires,personne_habilitee,type_cont,pere_superieur,criticite) values ('Ascenseur, monte charges et élévateur de personnes dont la vitesse n''excède pas 0,15 m/s : Vérification Périodique annuelle','Arrêté du 29 décembre 2010 relatif aux vérifications générales périodiques portant sur les ascenseurs et les monte-charges ainsi que sur les élévateurs de personnes n''excédant pas une vitesse de 0,15 m/s, installés à demeure, et modifiant l''arrêté du 1er mars 2004 modifié relatif aux vérifications des appareils et accessoires de levage Article 6 R4323-24 à R4323-27',1,1497,'Cette visite comporte un essai de fonctionnement et un examen de l''état de conservation. Les ascenseurs sont dispensés de cette vérification l''année au cours de laquelle s''effectue le contrôle technique quinquennal. L''employeur est dispensé de l''essai de l''efficacité du fonctionnement du dispositif parachute ou de l''équipement assurant une fonction équivalente s''il dispose d''un document assurant que le prestataire du contrat d''entretien a réalisé cette vérification.','',3,2,4) | AB37: =CONCATENATE("update aocr_ref_arbo set libelle = '",Tableau6[[#This Row],[Obligation]],"', reglementation = '",Tableau6[[#This Row],[Référence]],"', commentaires = '",Tableau6[[#This Row],[Libellé détaillé]],"', personne_habilitee = '",Tableau6[[#This Row],[Possible réalisateur]],"', criticite = ",Tableau6[[#This Row],[Urgence]]," where id = ",Tableau6[[#This Row],[id]]) -> update aocr_ref_arbo set libelle = 'Ascenseur, monte charges et élévateur de personnes dont la vitesse n''excède pas 0,15 m/s : Vérification Périodique annuelle', reglementation = 'Arrêté du 29 décembre 2010 relatif aux vérifications générales périodiques portant sur les ascenseurs et les monte-charges ainsi que sur les élévateurs de personnes n''excédant pas une vitesse de 0,15 m/s, installés à demeure, et modifiant l''arrêté du 1er mars 2004 modifié relatif aux vérifications des appareils et accessoires de levage Article 6 R4323-24 à R4323-27', commentaires = 'Cette visite comporte un essai de fonctionnement et un examen de l''état de conservation. Les ascenseurs sont dispensés de cette vérification l''année au cours de laquelle s''effectue le contrôle technique quinquennal. L''employeur est dispensé de l''essai de l''efficacité du fonctionnement du dispositif parachute ou de l''équipement assurant une fonction équivalente s''il dispose d''un document assurant que le prestataire du contrat d''entretien a réalisé cette vérification.', personne_habilitee = '', criticite = 4 where id = 1122 | AC37: =IF(Tableau6[[#This Row],[Référence]]<>"",CONCATENATE("update aocr_ref_arbo set reglementation = '",Tableau6[[#This Row],[Référence]],"' where id = ",Tableau6[[#This Row],[id]]),"") -> update aocr_ref_arbo set reglementation = 'Arrêté du 29 décembre 2010 relatif aux vérifications générales périodiques portant sur les ascenseurs et les monte-charges ainsi que sur les élévateurs de personnes n''excédant pas une vitesse de 0,15 m/s, installés à demeure, et modifiant l''arrêté du 1er mars 2004 modifié relatif aux vérifications des appareils et accessoires de levage Article 6 R4323-24 à R4323-27' where id = 1122
A38: 1123 | B38: Ascenseur | C38: Vérification Périodique 1 an | D38: Ascenseur : Vérification Périodique annuelle - Procès Verbal d''essais Un essai du système parachute et / ou du moyen de protection contre les mouvements incontrôlés de la cabine en montée ou tout autre dispositif antichute doit être réalisé annuellement. | E38: Cette vérification fait partie des opérations minimales d''entretien listées au contrat de l''ascensoriste. | F38: Arrêté du 29 décembre 2010 Article 3 paragraphe 3 R125-2 | H38: Ecart Détecté | M38: 1 | N38: 1 | O38: 1 | P38: 0 | Q38: =Y34 -> 2 | R38: =Z34 -> 1497 | S38: 1 | T38: 4 | V38: Locataire / Utilisateur | Y38: =VLOOKUP(A42,Feuil1!A:B,2,FALSE) -> 432 | Z38: =VLOOKUP(A42,Feuil1!A:C,3,FALSE) -> 1671 | AA38: =CONCATENATE("insert into AOCR_ref_arbo (libelle,reglementation,typologie,pere,commentaires,personne_habilitee,type_cont,pere_superieur,criticite) values ('",Tableau6[[#This Row],[Obligation]],"','",Tableau6[[#This Row],[Référence]],"',1,",Tableau6[[#This Row],[ID Domaine2]],",'",Tableau6[[#This Row],[Libellé détaillé]],"','",Tableau6[[#This Row],[Possible réalisateur]],"',3,",Tableau6[[#This Row],[ID Domaine]],",",Tableau6[[#This Row],[Urgence]],")") -> insert into AOCR_ref_arbo (libelle,reglementation,typologie,pere,commentaires,personne_habilitee,type_cont,pere_superieur,criticite) values ('Ascenseur : Vérification Périodique annuelle - Procès Verbal d''essais Un essai du système parachute et / ou du moyen de protection contre les mouvements incontrôlés de la cabine en montée ou tout autre dispositif antichute doit être réalisé annuellement.','Arrêté du 29 décembre 2010 Article 3 paragraphe 3 R125-2',1,1497,'Cette vérification fait partie des opérations minimales d''entretien listées au contrat de l''ascensoriste.','',3,2,4) | AB38: =CONCATENATE("update aocr_ref_arbo set libelle = '",Tableau6[[#This Row],[Obligation]],"', reglementation = '",Tableau6[[#This Row],[Référence]],"', commentaires = '",Tableau6[[#This Row],[Libellé détaillé]],"', personne_habilitee = '",Tableau6[[#This Row],[Possible réalisateur]],"', criticite = ",Tableau6[[#This Row],[Urgence]]," where id = ",Tableau6[[#This Row],[id]]) -> update aocr_ref_arbo set libelle = 'Ascenseur : Vérification Périodique annuelle - Procès Verbal d''essais Un essai du système parachute et / ou du moyen de protection contre les mouvements incontrôlés de la cabine en montée ou tout autre dispositif antichute doit être réalisé annuellement.', reglementation = 'Arrêté du 29 décembre 2010 Article 3 paragraphe 3 R125-2', commentaires = 'Cette vérification fait partie des opérations minimales d''entretien listées au contrat de l''ascensoriste.', personne_habilitee = '', criticite = 4 where id = 1123 | AC38: =IF(Tableau6[[#This Row],[Référence]]<>"",CONCATENATE("update aocr_ref_arbo set reglementation = '",Tableau6[[#This Row],[Référence]],"' where id = ",Tableau6[[#This Row],[id]]),"") -> update aocr_ref_arbo set reglementation = 'Arrêté du 29 décembre 2010 Article 3 paragraphe 3 R125-2' where id = 1123
A39: 1304 | B39: Ascenseur | C39: Vérification Périodique 6 mois | D39: Ascenseur : Une vérification des câbles ou chaînes de suspension et leurs extrémités doit être réalisé semestriellement. | E39: Cette vérification fait partie des opérations minimales d''entretien listées au contrat de l''ascensoriste. | F39: R125-2 | H39: Ecart Détecté | M39: 1 | N39: 1 | O39: 1 | P39: 0 | Q39: =Y35 -> 2 | R39: =Z35 -> 1489 | S39: 1 | T39: 4 | V39: Locataire / Utilisateur | Y39: =VLOOKUP(A43,Feuil1!A:B,2,FALSE) -> 432 | Z39: =VLOOKUP(A43,Feuil1!A:C,3,FALSE) -> 3680 | AA39: =CONCATENATE("insert into AOCR_ref_arbo (libelle,reglementation,typologie,pere,commentaires,personne_habilitee,type_cont,pere_superieur,criticite) values ('",Tableau6[[#This Row],[Obligation]],"','",Tableau6[[#This Row],[Référence]],"',1,",Tableau6[[#This Row],[ID Domaine2]],",'",Tableau6[[#This Row],[Libellé détaillé]],"','",Tableau6[[#This Row],[Possible réalisateur]],"',3,",Tableau6[[#This Row],[ID Domaine]],",",Tableau6[[#This Row],[Urgence]],")") -> insert into AOCR_ref_arbo (libelle,reglementation,typologie,pere,commentaires,personne_habilitee,type_cont,pere_superieur,criticite) values ('Ascenseur : Une vérification des câbles ou chaînes de suspension et leurs extrémités doit être réalisé semestriellement.','R125-2',1,1489,'Cette vérification fait partie des opérations minimales d''entretien listées au contrat de l''ascensoriste.','',3,2,4) | AB39: =CONCATENATE("update aocr_ref_arbo set libelle = '",Tableau6[[#This Row],[Obligation]],"', reglementation = '",Tableau6[[#This Row],[Référence]],"', commentaires = '",Tableau6[[#This Row],[Libellé détaillé]],"', personne_habilitee = '",Tableau6[[#This Row],[Possible réalisateur]],"', criticite = ",Tableau6[[#This Row],[Urgence]]," where id = ",Tableau6[[#This Row],[id]]) -> update aocr_ref_arbo set libelle = 'Ascenseur : Une vérification des câbles ou chaînes de suspension et leurs extrémités doit être réalisé semestriellement.', reglementation = 'R125-2', commentaires = 'Cette vérification fait partie des opérations minimales d''entretien listées au contrat de l''ascensoriste.', personne_habilitee = '', criticite = 4 where id = 1304 | AC39: =IF(Tableau6[[#This Row],[Référence]]<>"",CONCATENATE("update aocr_ref_arbo set reglementation = '",Tableau6[[#This Row],[Référence]],"' where id = ",Tableau6[[#This Row],[id]]),"") -> update aocr_ref_arbo set reglementation = 'R125-2' where id = 1304
A40: 1119 | B40: Ascenseur | C40: Vérification Périodique 6 semaines | D40: Ascenseur : Vérification Périodique 6 semaines | E40: Cette vérification fait partie des opérations minimales d''entretien listées au contrat de l''ascensoriste. | F40: Arrêté du 18 novembre 2004 Article 2 R125-2 | H40: Ecart Détecté | M40: 1 | N40: 1 | O40: 1 | P40: 0 | Q40: =Y36 -> 2 | R40: =Z36 -> 1491 | S40: 1 | T40: 4 | V40: Locataire / Utilisateur | Y40: =VLOOKUP(A44,Feuil1!A:B,2,FALSE) -> 938 | Z40: =VLOOKUP(A44,Feuil1!A:C,3,FALSE) -> 1679 | AA40: =CONCATENATE("insert into AOCR_ref_arbo (libelle,reglementation,typologie,pere,commentaires,personne_habilitee,type_cont,pere_superieur,criticite) values ('",Tableau6[[#This Row],[Obligation]],"','",Tableau6[[#This Row],[Référence]],"',1,",Tableau6[[#This Row],[ID Domaine2]],",'",Tableau6[[#This Row],[Libellé détaillé]],"','",Tableau6[[#This Row],[Possible réalisateur]],"',3,",Tableau6[[#This Row],[ID Domaine]],",",Tableau6[[#This Row],[Urgence]],")") -> insert into AOCR_ref_arbo (libelle,reglementation,typologie,pere,commentaires,personne_habilitee,type_cont,pere_superieur,criticite) values ('Ascenseur : Vérification Périodique 6 semaines','Arrêté du 18 novembre 2004 Article 2 R125-2',1,1491,'Cette vérification fait partie des opérations minimales d''entretien listées au contrat de l''ascensoriste.','',3,2,4) | AB40: =CONCATENATE("update aocr_ref_arbo set libelle = '",Tableau6[[#This Row],[Obligation]],"', reglementation = '",Tableau6[[#This Row],[Référence]],"', commentaires = '",Tableau6[[#This Row],[Libellé détaillé]],"', personne_habilitee = '",Tableau6[[#This Row],[Possible réalisateur]],"', criticite = ",Tableau6[[#This Row],[Urgence]]," where id = ",Tableau6[[#This Row],[id]]) -> update aocr_ref_arbo set libelle = 'Ascenseur : Vérification Périodique 6 semaines', reglementation = 'Arrêté du 18 novembre 2004 Article 2 R125-2', commentaires = 'Cette vérification fait partie des opérations minimales d''entretien listées au contrat de l''ascensoriste.', personne_habilitee = '', criticite = 4 where id = 1119 | AC40: =IF(Tableau6[[#This Row],[Référence]]<>"",CONCATENATE("update aocr_ref_arbo set reglementation = '",Tableau6[[#This Row],[Référence]],"' where id = ",Tableau6[[#This Row],[id]]),"") -> update aocr_ref_arbo set reglementation = 'Arrêté du 18 novembre 2004 Article 2 R125-2' where id = 1119
A41: 837 | B41: ATmosphère EXplosible (ATEX) | C41: Document Relatif à la Protection Contre les Explosions (DRPCE) | D41: Document Relatif à la Protection Contre les Explosions (DRPCE) : Le Document Relatif à la Protection Contre les Explosions (DRPCE) doit être réalisé depuis le 1er Juillet 2006. | E41: Il est mis à jour à chaque modifications (substance, local, détection, ventilation…). Le DRPCE comporte les informations suivantes : -La détermination et l''évaluation des risques d''explosion ; -La nature des mesures prises pour assurer le respect des objectifs définis à la présente section ; -La classification en zones des emplacements dans lesquels des atmosphères explosives peuvent se présenter ; -Les emplacements auxquels s''appliquent les prescriptions minimales prévues; -Les modalités et les règles selon lesquelles les lieux et les équipements de travail, y compris les dispositifs d''alarme, sont conçus, utilisés et entretenus pour assurer la sécurité ; -Le cas échéant, la liste des travaux devant être accomplis selon les instructions écrites de l''employeur ou dont l''exécution est subordonnée à la délivrance d''une autorisation par l''employeur ou par une personne habilitée par celui-ci à cet effet ; -La nature des dispositions prises pour que l''utilisation des équipements de travail soit sûre | F41: Code du travail Article R4227-52 à 54 | H41: Ecart Détecté | M41: 0 | N41: 1 | O41: 0 | P41: 0 | Q41: =Y37 -> 432 | R41: =Z37 -> 1668 | S41: 1 | T41: 5 | V41: Propriétaire | Y41: =VLOOKUP(A45,Feuil1!A:B,2,FALSE) -> 938 | Z41: =VLOOKUP(A45,Feuil1!A:C,3,FALSE) -> 1679 | AA41: =CONCATENATE("insert into AOCR_ref_arbo (libelle,reglementation,typologie,pere,commentaires,personne_habilitee,type_cont,pere_superieur,criticite) values ('",Tableau6[[#This Row],[Obligation]],"','",Tableau6[[#This Row],[Référence]],"',1,",Tableau6[[#This Row],[ID Domaine2]],",'",Tableau6[[#This Row],[Libellé détaillé]],"','",Tableau6[[#This Row],[Possible réalisateur]],"',3,",Tableau6[[#This Row],[ID Domaine]],",",Tableau6[[#This Row],[Urgence]],")") -> insert into AOCR_ref_arbo (libelle,reglementation,typologie,pere,commentaires,personne_habilitee,type_cont,pere_superieur,criticite) values ('Document Relatif à la Protection Contre les Explosions (DRPCE) : Le Document Relatif à la Protection Contre les Explosions (DRPCE) doit être réalisé depuis le 1er Juillet 2006.','Code du travail Article R4227-52 à 54',1,1668,'Il est mis à jour à chaque modifications (substance, local, détection, ventilation…). Le DRPCE comporte les informations suivantes : -La détermination et l''évaluation des risques d''explosion ; -La nature des mesures prises pour assurer le respect des objectifs définis à la présente section ; -La classification en zones des emplacements dans lesquels des atmosphères explosives peuvent se présenter ; -Les emplacements auxquels s''appliquent les prescriptions minimales prévues; -Les modalités et les règles selon lesquelles les lieux et les équipements de travail, y compris les dispositifs d''alarme, sont conçus, utilisés et entretenus pour assurer la sécurité ; -Le cas échéant, la liste des travaux devant être accomplis selon les instructions écrites de l''employeur ou dont l''exécution est subordonnée à la délivrance d''une autorisation par l''employeur ou par une personne habilitée par celui-ci à cet effet ; -La nature des dispositions prises pour que l''utilisation des équipements de travail soit sûre','',3,432,5) | AB41: =CONCATENATE("update aocr_ref_arbo set libelle = '",Tableau6[[#This Row],[Obligation]],"', reglementation = '",Tableau6[[#This Row],[Référence]],"', commentaires = '",Tableau6[[#This Row],[Libellé détaillé]],"', personne_habilitee = '",Tableau6[[#This Row],[Possible réalisateur]],"', criticite = ",Tableau6[[#This Row],[Urgence]]," where id = ",Tableau6[[#This Row],[id]]) -> update aocr_ref_arbo set libelle = 'Document Relatif à la Protection Contre les Explosions (DRPCE) : Le Document Relatif à la Protection Contre les Explosions (DRPCE) doit être réalisé depuis le 1er Juillet 2006.', reglementation = 'Code du travail Article R4227-52 à 54', commentaires = 'Il est mis à jour à chaque modifications (substance, local, détection, ventilation…). Le DRPCE comporte les informations suivantes : -La détermination et l''évaluation des risques d''explosion ; -La nature des mesures prises pour assurer le respect des objectifs définis à la présente section ; -La classification en zones des emplacements dans lesquels des atmosphères explosives peuvent se présenter ; -Les emplacements auxquels s''appliquent les prescriptions minimales prévues; -Les modalités et les règles selon lesquelles les lieux et les équipements de travail, y compris les dispositifs d''alarme, sont conçus, utilisés et entretenus pour assurer la sécurité ; -Le cas échéant, la liste des travaux devant être accomplis selon les instructions écrites de l''employeur ou dont l''exécution est subordonnée à la délivrance d''une autorisation par l''employeur ou par une personne habilitée par celui-ci à cet effet ; -La nature des dispositions prises pour que l''utilisation des équipements de travail soit sûre', personne_habilitee = '', criticite = 5 where id = 837 | AC41: =IF(Tableau6[[#This Row],[Référence]]<>"",CONCATENATE("update aocr_ref_arbo set reglementation = '",Tableau6[[#This Row],[Référence]],"' where id = ",Tableau6[[#This Row],[id]]),"") -> update aocr_ref_arbo set reglementation = 'Code du travail Article R4227-52 à 54' where id = 837
A42: 841 | B42: ATmosphère EXplosible (ATEX) | C42: Formation | D42: Risque d''explosion : Formation sur la base du Document Relatif à la Protection Contre les Explosions (DRPCE). | E42: Lorsque des atmosphères explosives peuvent se former en quantités susceptibles de présenter un risque pour la santé et la sécurité des travailleurs ou d''autres personnes, l''employeur forme des travailleurs en matière de protection contre les explosions. | F42: Code du travail Article R4227-49 A. 08/07/2003 Art 5 | H42: Ecart Détecté | M42: 0 | N42: 1 | O42: 0 | P42: 0 | Q42: =Y38 -> 432 | R42: =Z38 -> 1671 | S42: 1 | T42: 4 | V42: Locataire / Utilisateur | Y42: =VLOOKUP(A46,Feuil1!A:B,2,FALSE) -> 938 | Z42: =VLOOKUP(A46,Feuil1!A:C,3,FALSE) -> 1681 | AA42: =CONCATENATE("insert into AOCR_ref_arbo (libelle,reglementation,typologie,pere,commentaires,personne_habilitee,type_cont,pere_superieur,criticite) values ('",Tableau6[[#This Row],[Obligation]],"','",Tableau6[[#This Row],[Référence]],"',1,",Tableau6[[#This Row],[ID Domaine2]],",'",Tableau6[[#This Row],[Libellé détaillé]],"','",Tableau6[[#This Row],[Possible réalisateur]],"',3,",Tableau6[[#This Row],[ID Domaine]],",",Tableau6[[#This Row],[Urgence]],")") -> insert into AOCR_ref_arbo (libelle,reglementation,typologie,pere,commentaires,personne_habilitee,type_cont,pere_superieur,criticite) values ('Risque d''explosion : Formation sur la base du Document Relatif à la Protection Contre les Explosions (DRPCE).','Code du travail Article R4227-49 A. 08/07/2003 Art 5',1,1671,'Lorsque des atmosphères explosives peuvent se former en quantités susceptibles de présenter un risque pour la santé et la sécurité des travailleurs ou d''autres personnes, l''employeur forme des travailleurs en matière de protection contre les explosions.','',3,432,4) | AB42: =CONCATENATE("update aocr_ref_arbo set libelle = '",Tableau6[[#This Row],[Obligation]],"', reglementation = '",Tableau6[[#This Row],[Référence]],"', commentaires = '",Tableau6[[#This Row],[Libellé détaillé]],"', personne_habilitee = '",Tableau6[[#This Row],[Possible réalisateur]],"', criticite = ",Tableau6[[#This Row],[Urgence]]," where id = ",Tableau6[[#This Row],[id]]) -> update aocr_ref_arbo set libelle = 'Risque d''explosion : Formation sur la base du Document Relatif à la Protection Contre les Explosions (DRPCE).', reglementation = 'Code du travail Article R4227-49 A. 08/07/2003 Art 5', commentaires = 'Lorsque des atmosphères explosives peuvent se former en quantités susceptibles de présenter un risque pour la santé et la sécurité des travailleurs ou d''autres personnes, l''employeur forme des travailleurs en matière de protection contre les explosions.', personne_habilitee = '', criticite = 4 where id = 841 | AC42: =IF(Tableau6[[#This Row],[Référence]]<>"",CONCATENATE("update aocr_ref_arbo set reglementation = '",Tableau6[[#This Row],[Référence]],"' where id = ",Tableau6[[#This Row],[id]]),"") -> update aocr_ref_arbo set reglementation = 'Code du travail Article R4227-49 A. 08/07/2003 Art 5' where id = 841
A43: 3705 | B43: ATmosphère EXplosible (ATEX) | C43: Signalisation | D43: Signalisation des accès aux emplacements dans lesquels des atmosphères explosives peuvent se présenter et peuvent constituer un risque pour la santé et la sécurité des travailleurs. | F43: CT art. R. 4227-51 ; - A. du 08-07-2003 ; - A. du 04-11-1993. | H43: Ecart Détecté | M43: 0 | N43: 1 | O43: 0 | P43: 0 | Q43: =Y39 -> 432 | R43: =Z39 -> 3680 | S43: 1 | T43: 5 | V43: Propriétaire | Y43: =VLOOKUP(A47,Feuil1!A:B,2,FALSE) -> 3802 | Z43: =VLOOKUP(A47,Feuil1!A:C,3,FALSE) -> 3803 | AA43: =CONCATENATE("insert into AOCR_ref_arbo (libelle,reglementation,typologie,pere,commentaires,personne_habilitee,type_cont,pere_superieur,criticite) values ('",Tableau6[[#This Row],[Obligation]],"','",Tableau6[[#This Row],[Référence]],"',1,",Tableau6[[#This Row],[ID Domaine2]],",'",Tableau6[[#This Row],[Libellé détaillé]],"','",Tableau6[[#This Row],[Possible réalisateur]],"',3,",Tableau6[[#This Row],[ID Domaine]],",",Tableau6[[#This Row],[Urgence]],")") -> insert into AOCR_ref_arbo (libelle,reglementation,typologie,pere,commentaires,personne_habilitee,type_cont,pere_superieur,criticite) values ('Signalisation des accès aux emplacements dans lesquels des atmosphères explosives peuvent se présenter et peuvent constituer un risque pour la santé et la sécurité des travailleurs.','CT art. R. 4227-51 ; - A. du 08-07-2003 ; - A. du 04-11-1993.',1,3680,'','',3,432,5) | AB43: =CONCATENATE("update aocr_ref_arbo set libelle = '",Tableau6[[#This Row],[Obligation]],"', reglementation = '",Tableau6[[#This Row],[Référence]],"', commentaires = '",Tableau6[[#This Row],[Libellé détaillé]],"', personne_habilitee = '",Tableau6[[#This Row],[Possible réalisateur]],"', criticite = ",Tableau6[[#This Row],[Urgence]]," where id = ",Tableau6[[#This Row],[id]]) -> update aocr_ref_arbo set libelle = 'Signalisation des accès aux emplacements dans lesquels des atmosphères explosives peuvent se présenter et peuvent constituer un risque pour la santé et la sécurité des travailleurs.', reglementation = 'CT art. R. 4227-51 ; - A. du 08-07-2003 ; - A. du 04-11-1993.', commentaires = '', personne_habilitee = '', criticite = 5 where id = 3705 | AC43: =IF(Tableau6[[#This Row],[Référence]]<>"",CONCATENATE("update aocr_ref_arbo set reglementation = '",Tableau6[[#This Row],[Référence]],"' where id = ",Tableau6[[#This Row],[id]]),"") -> update aocr_ref_arbo set reglementation = 'CT art. R. 4227-51 ; - A. du 08-07-2003 ; - A. du 04-11-1993.' where id = 3705
A44: 949 | B44: Bruit, nuisance sonore | C44: Surveillance médicale | D44: Pour les travailleurs exposés à des niveaux supérieurs à 80 dB (A) ou 135 dB (C). | F44: CT art. R. 4431-2 CT art. R. 4435-2. | H44: Ecart Détecté | M44: 1 | N44: 1 | O44: 1 | P44: 0 | Q44: =Y40 -> 938 | R44: =Z40 -> 1679 | S44: 1 | T44: 4 | V44: Locataire / Utilisateur | Y44: =VLOOKUP(A48,Feuil1!A:B,2,FALSE) -> 3802 | Z44: =VLOOKUP(A48,Feuil1!A:C,3,FALSE) -> 3803 | AA44: =CONCATENATE("insert into AOCR_ref_arbo (libelle,reglementation,typologie,pere,commentaires,personne_habilitee,type_cont,pere_superieur,criticite) values ('",Tableau6[[#This Row],[Obligation]],"','",Tableau6[[#This Row],[Référence]],"',1,",Tableau6[[#This Row],[ID Domaine2]],",'",Tableau6[[#This Row],[Libellé détaillé]],"','",Tableau6[[#This Row],[Possible réalisateur]],"',3,",Tableau6[[#This Row],[ID Domaine]],",",Tableau6[[#This Row],[Urgence]],")") -> insert into AOCR_ref_arbo (libelle,reglementation,typologie,pere,commentaires,personne_habilitee,type_cont,pere_superieur,criticite) values ('Pour les travailleurs exposés à des niveaux supérieurs à 80 dB (A) ou 135 dB (C).','CT art. R. 4431-2 CT art. R. 4435-2.',1,1679,'','',3,938,4) | AB44: =CONCATENATE("update aocr_ref_arbo set libelle = '",Tableau6[[#This Row],[Obligation]],"', reglementation = '",Tableau6[[#This Row],[Référence]],"', commentaires = '",Tableau6[[#This Row],[Libellé détaillé]],"', personne_habilitee = '",Tableau6[[#This Row],[Possible réalisateur]],"', criticite = ",Tableau6[[#This Row],[Urgence]]," where id = ",Tableau6[[#This Row],[id]]) -> update aocr_ref_arbo set libelle = 'Pour les travailleurs exposés à des niveaux supérieurs à 80 dB (A) ou 135 dB (C).', reglementation = 'CT art. R. 4431-2 CT art. R. 4435-2.', commentaires = '', personne_habilitee = '', criticite = 4 where id = 949 | AC44: =IF(Tableau6[[#This Row],[Référence]]<>"",CONCATENATE("update aocr_ref_arbo set reglementation = '",Tableau6[[#This Row],[Référence]],"' where id = ",Tableau6[[#This Row],[id]]),"") -> update aocr_ref_arbo set reglementation = 'CT art. R. 4431-2 CT art. R. 4435-2.' where id = 949
A45: 951 | B45: Bruit, nuisance sonore | C45: Surveillance médicale renforcée | D45: Pour un niveau d''exposition supérieur à 85 dB (A) ou un niveau de pression acoustique de crête supérieur à 137 dB (C). | E45: Examen à minima tous les deux ans. | F45: CT art. R. 4431-2 CT art. R. 4624-18 et R. 4624-19. | H45: Ecart Détecté | M45: 1 | N45: 1 | O45: 1 | P45: 0 | Q45: =Y41 -> 938 | R45: =Z41 -> 1679 | S45: 1 | T45: 4 | V45: Locataire / Utilisateur | Y45: =VLOOKUP(A49,Feuil1!A:B,2,FALSE) -> 1309 | Z45: =VLOOKUP(A49,Feuil1!A:C,3,FALSE) -> 1742 | AA45: =CONCATENATE("insert into AOCR_ref_arbo (libelle,reglementation,typologie,pere,commentaires,personne_habilitee,type_cont,pere_superieur,criticite) values ('",Tableau6[[#This Row],[Obligation]],"','",Tableau6[[#This Row],[Référence]],"',1,",Tableau6[[#This Row],[ID Domaine2]],",'",Tableau6[[#This Row],[Libellé détaillé]],"','",Tableau6[[#This Row],[Possible réalisateur]],"',3,",Tableau6[[#This Row],[ID Domaine]],",",Tableau6[[#This Row],[Urgence]],")") -> insert into AOCR_ref_arbo (libelle,reglementation,typologie,pere,commentaires,personne_habilitee,type_cont,pere_superieur,criticite) values ('Pour un niveau d''exposition supérieur à 85 dB (A) ou un niveau de pression acoustique de crête supérieur à 137 dB (C).','CT art. R. 4431-2 CT art. R. 4624-18 et R. 4624-19.',1,1679,'Examen à minima tous les deux ans.','',3,938,4) | AB45: =CONCATENATE("update aocr_ref_arbo set libelle = '",Tableau6[[#This Row],[Obligation]],"', reglementation = '",Tableau6[[#This Row],[Référence]],"', commentaires = '",Tableau6[[#This Row],[Libellé détaillé]],"', personne_habilitee = '",Tableau6[[#This Row],[Possible réalisateur]],"', criticite = ",Tableau6[[#This Row],[Urgence]]," where id = ",Tableau6[[#This Row],[id]]) -> update aocr_ref_arbo set libelle = 'Pour un niveau d''exposition supérieur à 85 dB (A) ou un niveau de pression acoustique de crête supérieur à 137 dB (C).', reglementation = 'CT art. R. 4431-2 CT art. R. 4624-18 et R. 4624-19.', commentaires = 'Examen à minima tous les deux ans.', personne_habilitee = '', criticite = 4 where id = 951 | AC45: =IF(Tableau6[[#This Row],[Référence]]<>"",CONCATENATE("update aocr_ref_arbo set reglementation = '",Tableau6[[#This Row],[Référence]],"' where id = ",Tableau6[[#This Row],[id]]),"") -> update aocr_ref_arbo set reglementation = 'CT art. R. 4431-2 CT art. R. 4624-18 et R. 4624-19.' where id = 951
A46: 955 | B46: Bruit, nuisance sonore | C46: Vérification Périodique 5 ans | D46: Évaluation des niveaux de bruit (si jugé nécessaire par la médecine du travail) : Vérification Périodique quinquennale | E46: CDT. Art. R 4433-2 : Mesurage des niveaux de bruit L''évaluation des niveaux de bruit et, si nécessaire, leur mesurage sont planifiés et réalisés par des personnes compétentes, avec le concours, le cas échéant, du service de santé au travail. Ils sont réalisés à des intervalles appropriés, notamment lorsqu''une modification des installations ou des modes de travail est susceptible d''entraîner une élévation des niveaux de bruit. En cas de mesurage, celui-ci est renouvelé au moins tous les cinq ans | F46: Code du travail Article R4433-1 à R4433-4 | H46: Ecart Détecté | M46: 1 | N46: 1 | O46: 1 | P46: 0 | Q46: =Y42 -> 938 | R46: =Z42 -> 1681 | S46: 1 | T46: 4 | V46: Locataire / Utilisateur | Y46: =VLOOKUP(A50,Feuil1!A:B,2,FALSE) -> 1309 | Z46: =VLOOKUP(A50,Feuil1!A:C,3,FALSE) -> 1742 | AA46: =CONCATENATE("insert into AOCR_ref_arbo (libelle,reglementation,typologie,pere,commentaires,personne_habilitee,type_cont,pere_superieur,criticite) values ('",Tableau6[[#This Row],[Obligation]],"','",Tableau6[[#This Row],[Référence]],"',1,",Tableau6[[#This Row],[ID Domaine2]],",'",Tableau6[[#This Row],[Libellé détaillé]],"','",Tableau6[[#This Row],[Possible réalisateur]],"',3,",Tableau6[[#This Row],[ID Domaine]],",",Tableau6[[#This Row],[Urgence]],")") -> insert into AOCR_ref_arbo (libelle,reglementation,typologie,pere,commentaires,personne_habilitee,type_cont,pere_superieur,criticite) values ('Évaluation des niveaux de bruit (si jugé nécessaire par la médecine du travail) : Vérification Périodique quinquennale','Code du travail Article R4433-1 à R4433-4',1,1681,'CDT. Art. R 4433-2 : Mesurage des niveaux de bruit L''évaluation des niveaux de bruit et, si nécessaire, leur mesurage sont planifiés et réalisés par des personnes compétentes, avec le concours, le cas échéant, du service de santé au travail. Ils sont réalisés à des intervalles appropriés, notamment lorsqu''une modification des installations ou des modes de travail est susceptible d''entraîner une élévation des niveaux de bruit. En cas de mesurage, celui-ci est renouvelé au moins tous les cinq ans','',3,938,4) | AB46: =CONCATENATE("update aocr_ref_arbo set libelle = '",Tableau6[[#This Row],[Obligation]],"', reglementation = '",Tableau6[[#This Row],[Référence]],"', commentaires = '",Tableau6[[#This Row],[Libellé détaillé]],"', personne_habilitee = '",Tableau6[[#This Row],[Possible réalisateur]],"', criticite = ",Tableau6[[#This Row],[Urgence]]," where id = ",Tableau6[[#This Row],[id]]) -> update aocr_ref_arbo set libelle = 'Évaluation des niveaux de bruit (si jugé nécessaire par la médecine du travail) : Vérification Périodique quinquennale', reglementation = 'Code du travail Article R4433-1 à R4433-4', commentaires = 'CDT. Art. R 4433-2 : Mesurage des niveaux de bruit L''évaluation des niveaux de bruit et, si nécessaire, leur mesurage sont planifiés et réalisés par des personnes compétentes, avec le concours, le cas échéant, du service de santé au travail. Ils sont réalisés à des intervalles appropriés, notamment lorsqu''une modification des installations ou des modes de travail est susceptible d''entraîner une élévation des niveaux de bruit. En cas de mesurage, celui-ci est renouvelé au moins tous les cinq ans', personne_habilitee = '', criticite = 4 where id = 955 | AC46: =IF(Tableau6[[#This Row],[Référence]]<>"",CONCATENATE("update aocr_ref_arbo set reglementation = '",Tableau6[[#This Row],[Référence]],"' where id = ",Tableau6[[#This Row],[id]]),"") -> update aocr_ref_arbo set reglementation = 'Code du travail Article R4433-1 à R4433-4' where id = 955
A47: 3804 | B47: Conduite d'engins | C47: Formation | D47: Conduite de équipements de travail mobiles moteurs et de levage: (Chaque fois que nécessaire) Attestation de formation | E47: La conduite des équipements de travail mobiles automoteurs et des équipements de travail servant au levage est réservée aux travailleurs qui ont reçu une formation adéquate. Cette formation est complétée et réactualisée chaque fois que nécessaire. | F47: CDT Article R4323-55 | H47: Ecart Détecté | P47: 0 | Q47: =Y43 -> 3802 | R47: =Z43 -> 3803 | T47: 4 | V47: Locataire / Utilisateur | Y47: =VLOOKUP(A51,Feuil1!A:B,2,FALSE) -> 1309 | Z47: =VLOOKUP(A51,Feuil1!A:C,3,FALSE) -> 1742 | AA47: =CONCATENATE("insert into AOCR_ref_arbo (libelle,reglementation,typologie,pere,commentaires,personne_habilitee,type_cont,pere_superieur,criticite) values ('",Tableau6[[#This Row],[Obligation]],"','",Tableau6[[#This Row],[Référence]],"',1,",Tableau6[[#This Row],[ID Domaine2]],",'",Tableau6[[#This Row],[Libellé détaillé]],"','",Tableau6[[#This Row],[Possible réalisateur]],"',3,",Tableau6[[#This Row],[ID Domaine]],",",Tableau6[[#This Row],[Urgence]],")") -> insert into AOCR_ref_arbo (libelle,reglementation,typologie,pere,commentaires,personne_habilitee,type_cont,pere_superieur,criticite) values ('Conduite de équipements de travail mobiles moteurs et de levage: (Chaque fois que nécessaire) Attestation de formation','CDT Article R4323-55',1,3803,'La conduite des équipements de travail mobiles automoteurs et des équipements de travail servant au levage est réservée aux travailleurs qui ont reçu une formation adéquate. Cette formation est complétée et réactualisée chaque fois que nécessaire.','',3,3802,4) | AB47: =CONCATENATE("update aocr_ref_arbo set libelle = '",Tableau6[[#This Row],[Obligation]],"', reglementation = '",Tableau6[[#This Row],[Référence]],"', commentaires = '",Tableau6[[#This Row],[Libellé détaillé]],"', personne_habilitee = '",Tableau6[[#This Row],[Possible réalisateur]],"', criticite = ",Tableau6[[#This Row],[Urgence]]," where id = ",Tableau6[[#This Row],[id]]) -> update aocr_ref_arbo set libelle = 'Conduite de équipements de travail mobiles moteurs et de levage: (Chaque fois que nécessaire) Attestation de formation', reglementation = 'CDT Article R4323-55', commentaires = 'La conduite des équipements de travail mobiles automoteurs et des équipements de travail servant au levage est réservée aux travailleurs qui ont reçu une formation adéquate. Cette formation est complétée et réactualisée chaque fois que nécessaire.', personne_habilitee = '', criticite = 4 where id = 3804 | AC47: =IF(Tableau6[[#This Row],[Référence]]<>"",CONCATENATE("update aocr_ref_arbo set reglementation = '",Tableau6[[#This Row],[Référence]],"' where id = ",Tableau6[[#This Row],[id]]),"") -> update aocr_ref_arbo set reglementation = 'CDT Article R4323-55' where id = 3804
A48: 3805 | B48: Conduite d'engins | C48: Formation | D48: Autorisation de conduite délivrée par l'employeur | E48: La conduite de certains équipements présentant des risques particuliers, en raison de leurs caractéristiques ou de leur objet, est subordonnée à l'obtention d'une autorisation de conduite délivrée par l'employeur | F48: CDT Article R4323-56 | H48: Ecart Détecté | P48: 0 | Q48: =Y44 -> 3802 | R48: =Z44 -> 3803 | T48: 5 | V48: Locataire / Utilisateur | Y48: =VLOOKUP(A52,Feuil1!A:B,2,FALSE) -> 1309 | Z48: =VLOOKUP(A52,Feuil1!A:C,3,FALSE) -> 1310 | AA48: =CONCATENATE("insert into AOCR_ref_arbo (libelle,reglementation,typologie,pere,commentaires,personne_habilitee,type_cont,pere_superieur,criticite) values ('",Tableau6[[#This Row],[Obligation]],"','",Tableau6[[#This Row],[Référence]],"',1,",Tableau6[[#This Row],[ID Domaine2]],",'",Tableau6[[#This Row],[Libellé détaillé]],"','",Tableau6[[#This Row],[Possible réalisateur]],"',3,",Tableau6[[#This Row],[ID Domaine]],",",Tableau6[[#This Row],[Urgence]],")") -> insert into AOCR_ref_arbo (libelle,reglementation,typologie,pere,commentaires,personne_habilitee,type_cont,pere_superieur,criticite) values ('Autorisation de conduite délivrée par l'employeur','CDT Article R4323-56',1,3803,'La conduite de certains équipements présentant des risques particuliers, en raison de leurs caractéristiques ou de leur objet, est subordonnée à l'obtention d'une autorisation de conduite délivrée par l'employeur','',3,3802,5) | AB48: =CONCATENATE("update aocr_ref_arbo set libelle = '",Tableau6[[#This Row],[Obligation]],"', reglementation = '",Tableau6[[#This Row],[Référence]],"', commentaires = '",Tableau6[[#This Row],[Libellé détaillé]],"', personne_habilitee = '",Tableau6[[#This Row],[Possible réalisateur]],"', criticite = ",Tableau6[[#This Row],[Urgence]]," where id = ",Tableau6[[#This Row],[id]]) -> update aocr_ref_arbo set libelle = 'Autorisation de conduite délivrée par l'employeur', reglementation = 'CDT Article R4323-56', commentaires = 'La conduite de certains équipements présentant des risques particuliers, en raison de leurs caractéristiques ou de leur objet, est subordonnée à l'obtention d'une autorisation de conduite délivrée par l'employeur', personne_habilitee = '', criticite = 5 where id = 3805 | AC48: =IF(Tableau6[[#This Row],[Référence]]<>"",CONCATENATE("update aocr_ref_arbo set reglementation = '",Tableau6[[#This Row],[Référence]],"' where id = ",Tableau6[[#This Row],[id]]),"") -> update aocr_ref_arbo set reglementation = 'CDT Article R4323-56' where id = 3805
A49: 3706 | B49: Cuisine | C49: Établissement Recevant du Public (ERP) | D49: Appareil de cuisson ou de réchauffage destiné à la restauration : Contrôle Périodique annuel Rapport de Vérification Réglementaire en Exploitation (RVRE) | F49: Arrêté du 25 juin 1980 Article GC 22 | H49: Ecart Détecté | M49: 0 | N49: 0 | O49: 1 | P49: 0 | Q49: =Y45 -> 1309 | R49: =Z45 -> 1742 | S49: 1 | T49: 4 | V49: Locataire / Utilisateur | Y49: =VLOOKUP(A53,Feuil1!A:B,2,FALSE) -> 1309 | Z49: =VLOOKUP(A53,Feuil1!A:C,3,FALSE) -> 1310 | AA49: =CONCATENATE("insert into AOCR_ref_arbo (libelle,reglementation,typologie,pere,commentaires,personne_habilitee,type_cont,pere_superieur,criticite) values ('",Tableau6[[#This Row],[Obligation]],"','",Tableau6[[#This Row],[Référence]],"',1,",Tableau6[[#This Row],[ID Domaine2]],",'",Tableau6[[#This Row],[Libellé détaillé]],"','",Tableau6[[#This Row],[Possible réalisateur]],"',3,",Tableau6[[#This Row],[ID Domaine]],",",Tableau6[[#This Row],[Urgence]],")") -> insert into AOCR_ref_arbo (libelle,reglementation,typologie,pere,commentaires,personne_habilitee,type_cont,pere_superieur,criticite) values ('Appareil de cuisson ou de réchauffage destiné à la restauration : Contrôle Périodique annuel Rapport de Vérification Réglementaire en Exploitation (RVRE)','Arrêté du 25 juin 1980 Article GC 22 ',1,1742,'','',3,1309,4) | AB49: =CONCATENATE("update aocr_ref_arbo set libelle = '",Tableau6[[#This Row],[Obligation]],"', reglementation = '",Tableau6[[#This Row],[Référence]],"', commentaires = '",Tableau6[[#This Row],[Libellé détaillé]],"', personne_habilitee = '",Tableau6[[#This Row],[Possible réalisateur]],"', criticite = ",Tableau6[[#This Row],[Urgence]]," where id = ",Tableau6[[#This Row],[id]]) -> update aocr_ref_arbo set libelle = 'Appareil de cuisson ou de réchauffage destiné à la restauration : Contrôle Périodique annuel Rapport de Vérification Réglementaire en Exploitation (RVRE)', reglementation = 'Arrêté du 25 juin 1980 Article GC 22 ', commentaires = '', personne_habilitee = '', criticite = 4 where id = 3706 | AC49: =IF(Tableau6[[#This Row],[Référence]]<>"",CONCATENATE("update aocr_ref_arbo set reglementation = '",Tableau6[[#This Row],[Référence]],"' where id = ",Tableau6[[#This Row],[id]]),"") -> update aocr_ref_arbo set reglementation = 'Arrêté du 25 juin 1980 Article GC 22 ' where id = 3706
A50: 669 | B50: Cuisine | C50: Établissement Recevant du Public (ERP) | D50: Filtres des conduits d''évacuation des buées et graisses des appareils de cuisson destinés à la restauration ERP : Vérification Périodique hebomadaire | E50: Les filtres doivent être nettoyés ou remplacés avant chaque mise en place et au moins toutes les semaines | F50: Arrêté du 25 juin 1980 Article GC 21 | H50: Ecart Détecté | M50: 0 | N50: 0 | O50: 1 | P50: 0 | Q50: =Y46 -> 1309 | R50: =Z46 -> 1742 | S50: 1 | T50: 4 | V50: Locataire / Utilisateur | Y50: =VLOOKUP(A54,Feuil1!A:B,2,FALSE) -> 1309 | Z50: =VLOOKUP(A54,Feuil1!A:C,3,FALSE) -> 1310 | AA50: =CONCATENATE("insert into AOCR_ref_arbo (libelle,reglementation,typologie,pere,commentaires,personne_habilitee,type_cont,pere_superieur,criticite) values ('",Tableau6[[#This Row],[Obligation]],"','",Tableau6[[#This Row],[Référence]],"',1,",Tableau6[[#This Row],[ID Domaine2]],",'",Tableau6[[#This Row],[Libellé détaillé]],"','",Tableau6[[#This Row],[Possible réalisateur]],"',3,",Tableau6[[#This Row],[ID Domaine]],",",Tableau6[[#This Row],[Urgence]],")") -> insert into AOCR_ref_arbo (libelle,reglementation,typologie,pere,commentaires,personne_habilitee,type_cont,pere_superieur,criticite) values ('Filtres des conduits d''évacuation des buées et graisses des appareils de cuisson destinés à la restauration ERP : Vérification Périodique hebomadaire','Arrêté du 25 juin 1980 Article GC 21 ',1,1742,'Les filtres doivent être nettoyés ou remplacés avant chaque mise en place et au moins toutes les semaines','',3,1309,4) | AB50: =CONCATENATE("update aocr_ref_arbo set libelle = '",Tableau6[[#This Row],[Obligation]],"', reglementation = '",Tableau6[[#This Row],[Référence]],"', commentaires = '",Tableau6[[#This Row],[Libellé détaillé]],"', personne_habilitee = '",Tableau6[[#This Row],[Possible réalisateur]],"', criticite = ",Tableau6[[#This Row],[Urgence]]," where id = ",Tableau6[[#This Row],[id]]) -> update aocr_ref_arbo set libelle = 'Filtres des conduits d''évacuation des buées et graisses des appareils de cuisson destinés à la restauration ERP : Vérification Périodique hebomadaire', reglementation = 'Arrêté du 25 juin 1980 Article GC 21 ', commentaires = 'Les filtres doivent être nettoyés ou remplacés avant chaque mise en place et au moins toutes les semaines', personne_habilitee = '', criticite = 4 where id = 669 | AC50: =IF(Tableau6[[#This Row],[Référence]]<>"",CONCATENATE("update aocr_ref_arbo set reglementation = '",Tableau6[[#This Row],[Référence]],"' where id = ",Tableau6[[#This Row],[id]]),"") -> update aocr_ref_arbo set reglementation = 'Arrêté du 25 juin 1980 Article GC 21 ' where id = 669
A51: 674 | B51: Cuisine | C51: Établissement Recevant du Public (ERP) | D51: Conduits d''évacuation des buées et graisses des appareils de cuisson destinés à la restauration ERP : Vérification Périodique annuelle | E51: Vérification technique des installations des Grandes Cuisines. Nettoyage des conduits d''air vicié, de buées et de graisses, y compris les ventilateurs et les dispositifs de récupération de chaleur disposés dans les circuits d''extraction et ramonage des conduits. | F51: Arrêté du 25 juin 1980 Article GC 21 | H51: Ecart Détecté | M51: 0 | N51: 0 | O51: 1 | P51: 0 | Q51: =Y47 -> 1309 | R51: =Z47 -> 1742 | S51: 1 | T51: 4 | V51: Locataire / Utilisateur | Y51: =VLOOKUP(A55,Feuil1!A:B,2,FALSE) -> 1309 | Z51: =VLOOKUP(A55,Feuil1!A:C,3,FALSE) -> 3681 | AA51: =CONCATENATE("insert into AOCR_ref_arbo (libelle,reglementation,typologie,pere,commentaires,personne_habilitee,type_cont,pere_superieur,criticite) values ('",Tableau6[[#This Row],[Obligation]],"','",Tableau6[[#This Row],[Référence]],"',1,",Tableau6[[#This Row],[ID Domaine2]],",'",Tableau6[[#This Row],[Libellé détaillé]],"','",Tableau6[[#This Row],[Possible réalisateur]],"',3,",Tableau6[[#This Row],[ID Domaine]],",",Tableau6[[#This Row],[Urgence]],")") -> insert into AOCR_ref_arbo (libelle,reglementation,typologie,pere,commentaires,personne_habilitee,type_cont,pere_superieur,criticite) values ('Conduits d''évacuation des buées et graisses des appareils de cuisson destinés à la restauration ERP : Vérification Périodique annuelle','Arrêté du 25 juin 1980 Article GC 21 ',1,1742,'Vérification technique des installations des Grandes Cuisines. Nettoyage des conduits d''air vicié, de buées et de graisses, y compris les ventilateurs et les dispositifs de récupération de chaleur disposés dans les circuits d''extraction et ramonage des conduits.','',3,1309,4) | AB51: =CONCATENATE("update aocr_ref_arbo set libelle = '",Tableau6[[#This Row],[Obligation]],"', reglementation = '",Tableau6[[#This Row],[Référence]],"', commentaires = '",Tableau6[[#This Row],[Libellé détaillé]],"', personne_habilitee = '",Tableau6[[#This Row],[Possible réalisateur]],"', criticite = ",Tableau6[[#This Row],[Urgence]]," where id = ",Tableau6[[#This Row],[id]]) -> update aocr_ref_arbo set libelle = 'Conduits d''évacuation des buées et graisses des appareils de cuisson destinés à la restauration ERP : Vérification Périodique annuelle', reglementation = 'Arrêté du 25 juin 1980 Article GC 21 ', commentaires = 'Vérification technique des installations des Grandes Cuisines. Nettoyage des conduits d''air vicié, de buées et de graisses, y compris les ventilateurs et les dispositifs de récupération de chaleur disposés dans les circuits d''extraction et ramonage des conduits.', personne_habilitee = '', criticite = 4 where id = 674 | AC51: =IF(Tableau6[[#This Row],[Référence]]<>"",CONCATENATE("update aocr_ref_arbo set reglementation = '",Tableau6[[#This Row],[Référence]],"' where id = ",Tableau6[[#This Row],[id]]),"") -> update aocr_ref_arbo set reglementation = 'Arrêté du 25 juin 1980 Article GC 21 ' where id = 674
A52: 1311 | B52: Cuisine | C52: Immeuble de Grande Hauteur (IGH) | D52: Conduits d''évacuation des buées et graisses des appareils de cuisson destinés à la restauration IGH : Vérification Périodique annuelle | E52: Vérification technique des installations des Grandes Cuisines. Nettoyage des conduits d''air vicié, de buées et de graisses, y compris les ventilateurs et les dispositifs de récupération de chaleur disposés dans les circuits d''extraction et ramonage des conduits. | F52: Arrêté du 25 juin 1980 Article GC 21 GH5 §3.1.2 | H52: Ecart Détecté | M52: 0 | N52: 0 | O52: 1 | P52: 0 | Q52: =Y48 -> 1309 | R52: =Z48 -> 1310 | S52: 1 | T52: 4 | V52: Locataire / Utilisateur | Y52: =VLOOKUP(A56,Feuil1!A:B,2,FALSE) -> 431 | Z52: =VLOOKUP(A56,Feuil1!A:C,3,FALSE) -> 1667 | AA52: =CONCATENATE("insert into AOCR_ref_arbo (libelle,reglementation,typologie,pere,commentaires,personne_habilitee,type_cont,pere_superieur,criticite) values ('",Tableau6[[#This Row],[Obligation]],"','",Tableau6[[#This Row],[Référence]],"',1,",Tableau6[[#This Row],[ID Domaine2]],",'",Tableau6[[#This Row],[Libellé détaillé]],"','",Tableau6[[#This Row],[Possible réalisateur]],"',3,",Tableau6[[#This Row],[ID Domaine]],",",Tableau6[[#This Row],[Urgence]],")") -> insert into AOCR_ref_arbo (libelle,reglementation,typologie,pere,commentaires,personne_habilitee,type_cont,pere_superieur,criticite) values ('Conduits d''évacuation des buées et graisses des appareils de cuisson destinés à la restauration IGH : Vérification Périodique annuelle','Arrêté du 25 juin 1980 Article GC 21 GH5 §3.1.2',1,1310,'Vérification technique des installations des Grandes Cuisines. Nettoyage des conduits d''air vicié, de buées et de graisses, y compris les ventilateurs et les dispositifs de récupération de chaleur disposés dans les circuits d''extraction et ramonage des conduits.','',3,1309,4) | AB52: =CONCATENATE("update aocr_ref_arbo set libelle = '",Tableau6[[#This Row],[Obligation]],"', reglementation = '",Tableau6[[#This Row],[Référence]],"', commentaires = '",Tableau6[[#This Row],[Libellé détaillé]],"', personne_habilitee = '",Tableau6[[#This Row],[Possible réalisateur]],"', criticite = ",Tableau6[[#This Row],[Urgence]]," where id = ",Tableau6[[#This Row],[id]]) -> update aocr_ref_arbo set libelle = 'Conduits d''évacuation des buées et graisses des appareils de cuisson destinés à la restauration IGH : Vérification Périodique annuelle', reglementation = 'Arrêté du 25 juin 1980 Article GC 21 GH5 §3.1.2', commentaires = 'Vérification technique des installations des Grandes Cuisines. Nettoyage des conduits d''air vicié, de buées et de graisses, y compris les ventilateurs et les dispositifs de récupération de chaleur disposés dans les circuits d''extraction et ramonage des conduits.', personne_habilitee = '', criticite = 4 where id = 1311 | AC52: =IF(Tableau6[[#This Row],[Référence]]<>"",CONCATENATE("update aocr_ref_arbo set reglementation = '",Tableau6[[#This Row],[Référence]],"' where id = ",Tableau6[[#This Row],[id]]),"") -> update aocr_ref_arbo set reglementation = 'Arrêté du 25 juin 1980 Article GC 21 GH5 §3.1.2' where id = 1311
A53: 1312 | B53: Cuisine | C53: Immeuble de Grande Hauteur (IGH) | D53: Filtres des conduits d''évacuation des buées et graisses des appareils de cuisson destinés à la restauration IGH: Vérification Périodique hebomadaire | E53: Les filtres doivent être nettoyés ou remplacés avant chaque mise en place et au moins toutes les semaines | F53: Arrêté du 25 juin 1980 Article GC 21 GH5 §3.1.2 | H53: Ecart Détecté | M53: 0 | N53: 0 | O53: 1 | P53: 0 | Q53: =Y49 -> 1309 | R53: =Z49 -> 1310 | S53: 1 | T53: 4 | V53: Locataire / Utilisateur | Y53: =VLOOKUP(A57,Feuil1!A:B,2,FALSE) -> 431 | Z53: =VLOOKUP(A57,Feuil1!A:C,3,FALSE) -> 1656 | AA53: =CONCATENATE("insert into AOCR_ref_arbo (libelle,reglementation,typologie,pere,commentaires,personne_habilitee,type_cont,pere_superieur,criticite) values ('",Tableau6[[#This Row],[Obligation]],"','",Tableau6[[#This Row],[Référence]],"',1,",Tableau6[[#This Row],[ID Domaine2]],",'",Tableau6[[#This Row],[Libellé détaillé]],"','",Tableau6[[#This Row],[Possible réalisateur]],"',3,",Tableau6[[#This Row],[ID Domaine]],",",Tableau6[[#This Row],[Urgence]],")") -> insert into AOCR_ref_arbo (libelle,reglementation,typologie,pere,commentaires,personne_habilitee,type_cont,pere_superieur,criticite) values ('Filtres des conduits d''évacuation des buées et graisses des appareils de cuisson destinés à la restauration IGH: Vérification Périodique hebomadaire','Arrêté du 25 juin 1980 Article GC 21 GH5 §3.1.2',1,1310,'Les filtres doivent être nettoyés ou remplacés avant chaque mise en place et au moins toutes les semaines','',3,1309,4) | AB53: =CONCATENATE("update aocr_ref_arbo set libelle = '",Tableau6[[#This Row],[Obligation]],"', reglementation = '",Tableau6[[#This Row],[Référence]],"', commentaires = '",Tableau6[[#This Row],[Libellé détaillé]],"', personne_habilitee = '",Tableau6[[#This Row],[Possible réalisateur]],"', criticite = ",Tableau6[[#This Row],[Urgence]]," where id = ",Tableau6[[#This Row],[id]]) -> update aocr_ref_arbo set libelle = 'Filtres des conduits d''évacuation des buées et graisses des appareils de cuisson destinés à la restauration IGH: Vérification Périodique hebomadaire', reglementation = 'Arrêté du 25 juin 1980 Article GC 21 GH5 §3.1.2', commentaires = 'Les filtres doivent être nettoyés ou remplacés avant chaque mise en place et au moins toutes les semaines', personne_habilitee = '', criticite = 4 where id = 1312 | AC53: =IF(Tableau6[[#This Row],[Référence]]<>"",CONCATENATE("update aocr_ref_arbo set reglementation = '",Tableau6[[#This Row],[Référence]],"' where id = ",Tableau6[[#This Row],[id]]),"") -> update aocr_ref_arbo set reglementation = 'Arrêté du 25 juin 1980 Article GC 21 GH5 §3.1.2' where id = 1312
A54: 1878 | B54: Cuisine | C54: Immeuble de Grande Hauteur (IGH) | D54: Appareil de cuisson ou de réchauffage destiné à la restauration : Contrôle Périodique annuel Rapport de Vérification Réglementaire en Exploitation (RVRE) | F54: Arrêté du 25 juin 1980 Article GC 22 GH5 §3.1.2 | H54: Ecart Détecté | M54: 0 | N54: 0 | O54: 1 | P54: 0 | Q54: =Y50 -> 1309 | R54: =Z50 -> 1310 | S54: 1 | T54: 4 | V54: Locataire / Utilisateur | Y54: =VLOOKUP(A58,Feuil1!A:B,2,FALSE) -> 431 | Z54: =VLOOKUP(A58,Feuil1!A:C,3,FALSE) -> 1666 | AA54: =CONCATENATE("insert into AOCR_ref_arbo (libelle,reglementation,typologie,pere,commentaires,personne_habilitee,type_cont,pere_superieur,criticite) values ('",Tableau6[[#This Row],[Obligation]],"','",Tableau6[[#This Row],[Référence]],"',1,",Tableau6[[#This Row],[ID Domaine2]],",'",Tableau6[[#This Row],[Libellé détaillé]],"','",Tableau6[[#This Row],[Possible réalisateur]],"',3,",Tableau6[[#This Row],[ID Domaine]],",",Tableau6[[#This Row],[Urgence]],")") -> insert into AOCR_ref_arbo (libelle,reglementation,typologie,pere,commentaires,personne_habilitee,type_cont,pere_superieur,criticite) values ('Appareil de cuisson ou de réchauffage destiné à la restauration : Contrôle Périodique annuel Rapport de Vérification Réglementaire en Exploitation (RVRE)','Arrêté du 25 juin 1980 Article GC 22 GH5 §3.1.2',1,1310,'','',3,1309,4) | AB54: =CONCATENATE("update aocr_ref_arbo set libelle = '",Tableau6[[#This Row],[Obligation]],"', reglementation = '",Tableau6[[#This Row],[Référence]],"', commentaires = '",Tableau6[[#This Row],[Libellé détaillé]],"', personne_habilitee = '",Tableau6[[#This Row],[Possible réalisateur]],"', criticite = ",Tableau6[[#This Row],[Urgence]]," where id = ",Tableau6[[#This Row],[id]]) -> update aocr_ref_arbo set libelle = 'Appareil de cuisson ou de réchauffage destiné à la restauration : Contrôle Périodique annuel Rapport de Vérification Réglementaire en Exploitation (RVRE)', reglementation = 'Arrêté du 25 juin 1980 Article GC 22 GH5 §3.1.2', commentaires = '', personne_habilitee = '', criticite = 4 where id = 1878 | AC54: =IF(Tableau6[[#This Row],[Référence]]<>"",CONCATENATE("update aocr_ref_arbo set reglementation = '",Tableau6[[#This Row],[Référence]],"' where id = ",Tableau6[[#This Row],[id]]),"") -> update aocr_ref_arbo set reglementation = 'Arrêté du 25 juin 1980 Article GC 22 GH5 §3.1.2' where id = 1878
A55: 3707 | B55: Cuisine | C55: Livret d'entretien Grande Cuisine | D55: Cuisine : Livret d''entretien annexé au Registre de sécurité Les résultats des vérifications, des contrôles et des maintenances doivent être portés sur le livret et annexé au registre sécurité. | F55: Arrêté du 25 juin 1980 Article GC 21 § 3 GH5 §3.1.2 | H55: Ecart Détecté | M55: 1 | N55: 1 | O55: 1 | P55: 0 | Q55: =Y51 -> 1309 | R55: =Z51 -> 3681 | S55: 1 | T55: 4 | V55: Locataire / Utilisateur | Y55: =VLOOKUP(A59,Feuil1!A:B,2,FALSE) -> 431 | Z55: =VLOOKUP(A59,Feuil1!A:C,3,FALSE) -> 1315 | AA55: =CONCATENATE("insert into AOCR_ref_arbo (libelle,reglementation,typologie,pere,commentaires,personne_habilitee,type_cont,pere_superieur,criticite) values ('",Tableau6[[#This Row],[Obligation]],"','",Tableau6[[#This Row],[Référence]],"',1,",Tableau6[[#This Row],[ID Domaine2]],",'",Tableau6[[#This Row],[Libellé détaillé]],"','",Tableau6[[#This Row],[Possible réalisateur]],"',3,",Tableau6[[#This Row],[ID Domaine]],",",Tableau6[[#This Row],[Urgence]],")") -> insert into AOCR_ref_arbo (libelle,reglementation,typologie,pere,commentaires,personne_habilitee,type_cont,pere_superieur,criticite) values ('Cuisine : Livret d''entretien annexé au Registre de sécurité Les résultats des vérifications, des contrôles et des maintenances doivent être portés sur le livret et annexé au registre sécurité.','Arrêté du 25 juin 1980 Article GC 21 § 3 GH5 §3.1.2',1,3681,'','',3,1309,4) | AB55: =CONCATENATE("update aocr_ref_arbo set libelle = '",Tableau6[[#This Row],[Obligation]],"', reglementation = '",Tableau6[[#This Row],[Référence]],"', commentaires = '",Tableau6[[#This Row],[Libellé détaillé]],"', personne_habilitee = '",Tableau6[[#This Row],[Possible réalisateur]],"', criticite = ",Tableau6[[#This Row],[Urgence]]," where id = ",Tableau6[[#This Row],[id]]) -> update aocr_ref_arbo set libelle = 'Cuisine : Livret d''entretien annexé au Registre de sécurité Les résultats des vérifications, des contrôles et des maintenances doivent être portés sur le livret et annexé au registre sécurité.', reglementation = 'Arrêté du 25 juin 1980 Article GC 21 § 3 GH5 §3.1.2', commentaires = '', personne_habilitee = '', criticite = 4 where id = 3707 | AC55: =IF(Tableau6[[#This Row],[Référence]]<>"",CONCATENATE("update aocr_ref_arbo set reglementation = '",Tableau6[[#This Row],[Référence]],"' where id = ",Tableau6[[#This Row],[id]]),"") -> update aocr_ref_arbo set reglementation = 'Arrêté du 25 juin 1980 Article GC 21 § 3 GH5 §3.1.2' where id = 3707
A56: 1816 | B56: Cuve, bassin, réservoir, citerne | C56: Bilan de conformité | D56: Stockage de produits pétroliers Installation antérieure 25/01/05 : Bilan de conformité | F56: Arrêté du 1er juillet 2004 fixant les règles techniques et de sécurité applicables au stockage de produits pétroliers dans les lieux non visés par la législation des installations classées ni la réglementation des établissements recevant du public Article 31; | H56: Ecart Détecté | M56: 1 | N56: 1 | O56: 1 | P56: 0 | Q56: =Y52 -> 431 | R56: =Z52 -> 1667 | S56: 1 | T56: 5 | V56: Propriétaire | Y56: =VLOOKUP(A60,Feuil1!A:B,2,FALSE) -> 431 | Z56: =VLOOKUP(A60,Feuil1!A:C,3,FALSE) -> 1665 | AA56: =CONCATENATE("insert into AOCR_ref_arbo (libelle,reglementation,typologie,pere,commentaires,personne_habilitee,type_cont,pere_superieur,criticite) values ('",Tableau6[[#This Row],[Obligation]],"','",Tableau6[[#This Row],[Référence]],"',1,",Tableau6[[#This Row],[ID Domaine2]],",'",Tableau6[[#This Row],[Libellé détaillé]],"','",Tableau6[[#This Row],[Possible réalisateur]],"',3,",Tableau6[[#This Row],[ID Domaine]],",",Tableau6[[#This Row],[Urgence]],")") -> insert into AOCR_ref_arbo (libelle,reglementation,typologie,pere,commentaires,personne_habilitee,type_cont,pere_superieur,criticite) values ('Stockage de produits pétroliers Installation antérieure 25/01/05 : Bilan de conformité','Arrêté du 1er juillet 2004 fixant les règles techniques et de sécurité applicables au stockage de produits pétroliers dans les lieux non visés par la législation des installations classées ni la réglementation des établissements recevant du public Article 31;',1,1667,'','',3,431,5) | AB56: =CONCATENATE("update aocr_ref_arbo set libelle = '",Tableau6[[#This Row],[Obligation]],"', reglementation = '",Tableau6[[#This Row],[Référence]],"', commentaires = '",Tableau6[[#This Row],[Libellé détaillé]],"', personne_habilitee = '",Tableau6[[#This Row],[Possible réalisateur]],"', criticite = ",Tableau6[[#This Row],[Urgence]]," where id = ",Tableau6[[#This Row],[id]]) -> update aocr_ref_arbo set libelle = 'Stockage de produits pétroliers Installation antérieure 25/01/05 : Bilan de conformité', reglementation = 'Arrêté du 1er juillet 2004 fixant les règles techniques et de sécurité applicables au stockage de produits pétroliers dans les lieux non visés par la législation des installations classées ni la réglementation des établissements recevant du public Article 31;', commentaires = '', personne_habilitee = '', criticite = 5 where id = 1816 | AC56: =IF(Tableau6[[#This Row],[Référence]]<>"",CONCATENATE("update aocr_ref_arbo set reglementation = '",Tableau6[[#This Row],[Référence]],"' where id = ",Tableau6[[#This Row],[id]]),"") -> update aocr_ref_arbo set reglementation = 'Arrêté du 1er juillet 2004 fixant les règles techniques et de sécurité applicables au stockage de produits pétroliers dans les lieux non visés par la législation des installations classées ni la réglementation des établissements recevant du public Article 31;' where id = 1816
A57: 1821 | B57: Cuve, bassin, réservoir, citerne | C57: Certificat d'abandon | D57: Stockage de produits pétroliers : Certificat d''abandon cuve (définitif ou provisoire) | E57: L''entreprise qui intervient dans ce cadre fournit un certificat à l''utilisateur garantissant la bonne exécution des opérations de mise à l''état inerte citées ci-dessus. Si l''abandon est consécutif à la modification de l''installation de chauffage, il appartient à l''entreprise intervenante de respecter ces dispositions. | F57: Arrêté du 1er juillet 2004 fixant les règles techniques et de sécurité applicables au stockage de produits pétroliers dans les lieux non visés par la législation des installations classées ni la réglementation des établissements recevant du public Article 28; | H57: Ecart Détecté | M57: 1 | N57: 1 | O57: 1 | P57: 0 | Q57: =Y53 -> 431 | R57: =Z53 -> 1656 | S57: 1 | T57: 5 | V57: Propriétaire | Y57: =VLOOKUP(A61,Feuil1!A:B,2,FALSE) -> 431 | Z57: =VLOOKUP(A61,Feuil1!A:C,3,FALSE) -> 1661 | AA57: =CONCATENATE("insert into AOCR_ref_arbo (libelle,reglementation,typologie,pere,commentaires,personne_habilitee,type_cont,pere_superieur,criticite) values ('",Tableau6[[#This Row],[Obligation]],"','",Tableau6[[#This Row],[Référence]],"',1,",Tableau6[[#This Row],[ID Domaine2]],",'",Tableau6[[#This Row],[Libellé détaillé]],"','",Tableau6[[#This Row],[Possible réalisateur]],"',3,",Tableau6[[#This Row],[ID Domaine]],",",Tableau6[[#This Row],[Urgence]],")") -> insert into AOCR_ref_arbo (libelle,reglementation,typologie,pere,commentaires,personne_habilitee,type_cont,pere_superieur,criticite) values ('Stockage de produits pétroliers : Certificat d''abandon cuve (définitif ou provisoire)','Arrêté du 1er juillet 2004 fixant les règles techniques et de sécurité applicables au stockage de produits pétroliers dans les lieux non visés par la législation des installations classées ni la réglementation des établissements recevant du public Article 28;',1,1656,'L''entreprise qui intervient dans ce cadre fournit un certificat à l''utilisateur garantissant la bonne exécution des opérations de mise à l''état inerte citées ci-dessus. Si l''abandon est consécutif à la modification de l''installation de chauffage, il appartient à l''entreprise intervenante de respecter ces dispositions.','',3,431,5) | AB57: =CONCATENATE("update aocr_ref_arbo set libelle = '",Tableau6[[#This Row],[Obligation]],"', reglementation = '",Tableau6[[#This Row],[Référence]],"', commentaires = '",Tableau6[[#This Row],[Libellé détaillé]],"', personne_habilitee = '",Tableau6[[#This Row],[Possible réalisateur]],"', criticite = ",Tableau6[[#This Row],[Urgence]]," where id = ",Tableau6[[#This Row],[id]]) -> update aocr_ref_arbo set libelle = 'Stockage de produits pétroliers : Certificat d''abandon cuve (définitif ou provisoire)', reglementation = 'Arrêté du 1er juillet 2004 fixant les règles techniques et de sécurité applicables au stockage de produits pétroliers dans les lieux non visés par la législation des installations classées ni la réglementation des établissements recevant du public Article 28;', commentaires = 'L''entreprise qui intervient dans ce cadre fournit un certificat à l''utilisateur garantissant la bonne exécution des opérations de mise à l''état inerte citées ci-dessus. Si l''abandon est consécutif à la modification de l''installation de chauffage, il appartient à l''entreprise intervenante de respecter ces dispositions.', personne_habilitee = '', criticite = 5 where id = 1821 | AC57: =IF(Tableau6[[#This Row],[Référence]]<>"",CONCATENATE("update aocr_ref_arbo set reglementation = '",Tableau6[[#This Row],[Référence]],"' where id = ",Tableau6[[#This Row],[id]]),"") -> update aocr_ref_arbo set reglementation = 'Arrêté du 1er juillet 2004 fixant les règles techniques et de sécurité applicables au stockage de produits pétroliers dans les lieux non visés par la législation des installations classées ni la réglementation des établissements recevant du public Article 28;' where id = 1821
A58: 1823 | B58: Cuve, bassin, réservoir, citerne | C58: Contrôle à la mise en service | D58: Stockage de produits pétroliers : Contrôle à la mise en service - Certificat essai d''étanchéité | F58: Arrêté du 1er juillet 2004 fixant les règles techniques et de sécurité applicables au stockage de produits pétroliers dans les lieux non visés par la législation des installations classées ni la réglementation des établissements recevant du public Article 24; | H58: Ecart Détecté | M58: 1 | N58: 1 | O58: 1 | P58: 0 | Q58: =Y54 -> 431 | R58: =Z54 -> 1666 | S58: 1 | T58: 5 | V58: Propriétaire | Y58: =VLOOKUP(A62,Feuil1!A:B,2,FALSE) -> 431 | Z58: =VLOOKUP(A62,Feuil1!A:C,3,FALSE) -> 1657 | AA58: =CONCATENATE("insert into AOCR_ref_arbo (libelle,reglementation,typologie,pere,commentaires,personne_habilitee,type_cont,pere_superieur,criticite) values ('",Tableau6[[#This Row],[Obligation]],"','",Tableau6[[#This Row],[Référence]],"',1,",Tableau6[[#This Row],[ID Domaine2]],",'",Tableau6[[#This Row],[Libellé détaillé]],"','",Tableau6[[#This Row],[Possible réalisateur]],"',3,",Tableau6[[#This Row],[ID Domaine]],",",Tableau6[[#This Row],[Urgence]],")") -> insert into AOCR_ref_arbo (libelle,reglementation,typologie,pere,commentaires,personne_habilitee,type_cont,pere_superieur,criticite) values ('Stockage de produits pétroliers : Contrôle à la mise en service - Certificat essai d''étanchéité','Arrêté du 1er juillet 2004 fixant les règles techniques et de sécurité applicables au stockage de produits pétroliers dans les lieux non visés par la législation des installations classées ni la réglementation des établissements recevant du public Article 24;',1,1666,'','',3,431,5) | AB58: =CONCATENATE("update aocr_ref_arbo set libelle = '",Tableau6[[#This Row],[Obligation]],"', reglementation = '",Tableau6[[#This Row],[Référence]],"', commentaires = '",Tableau6[[#This Row],[Libellé détaillé]],"', personne_habilitee = '",Tableau6[[#This Row],[Possible réalisateur]],"', criticite = ",Tableau6[[#This Row],[Urgence]]," where id = ",Tableau6[[#This Row],[id]]) -> update aocr_ref_arbo set libelle = 'Stockage de produits pétroliers : Contrôle à la mise en service - Certificat essai d''étanchéité', reglementation = 'Arrêté du 1er juillet 2004 fixant les règles techniques et de sécurité applicables au stockage de produits pétroliers dans les lieux non visés par la législation des installations classées ni la réglementation des établissements recevant du public Article 24;', commentaires = '', personne_habilitee = '', criticite = 5 where id = 1823 | AC58: =IF(Tableau6[[#This Row],[Référence]]<>"",CONCATENATE("update aocr_ref_arbo set reglementation = '",Tableau6[[#This Row],[Référence]],"' where id = ",Tableau6[[#This Row],[id]]),"") -> update aocr_ref_arbo set reglementation = 'Arrêté du 1er juillet 2004 fixant les règles techniques et de sécurité applicables au stockage de produits pétroliers dans les lieux non visés par la législation des installations classées ni la réglementation des établissements recevant du public Article 24;' where id = 1823
A59: 1320 | B59: Cuve, bassin, réservoir, citerne | C59: Établissement Recevant du Public (ERP) | D59: Installation de stockage de combustible ERP : Vérification Périodique annuelle | E59: Les vérifications périodiques doivent avoir lieu tous les ans et concernent : - le stockage des combustibles; Elles ont pour objet de s''assurer : - de l''état apparent d''entretien et de maintenance des installations et appareils ; - des conditions de ventilation des locaux contenant des appareils à combustion ; - des conditions d''évacuation des produits de la combustion ; - du fonctionnement des clapets coupe-feu installés sur les circuits aérauliques ; - de la signalisation des dispositifs de sécurité ; - de la manœuvre des organes de coupure d''alimentation en combustible ; - du fonctionnement des dispositifs asservissant l''alimentation en combustible à un système de sécurité ; - du réglage des détendeurs de gaz ; - de l''étanchéité des canalisations d''alimentation en combustibles liquides ou gazeux, et en fluide frigorigène. | F59: Arrêté du 25 juin 1980 portant approbation des dispositions générales du règlement de sécurité contre les risques d''incendie et de panique dans les établissements recevant du public (ERP). Article CH 58; | H59: Ecart Détecté | M59: 0 | N59: 0 | O59: 1 | P59: 0 | Q59: =Y55 -> 431 | R59: =Z55 -> 1315 | S59: 1 | T59: 4 | V59: Locataire / Utilisateur | Y59: =VLOOKUP(A63,Feuil1!A:B,2,FALSE) -> 11 | Z59: =VLOOKUP(A63,Feuil1!A:C,3,FALSE) -> 1562 | AA59: =CONCATENATE("insert into AOCR_ref_arbo (libelle,reglementation,typologie,pere,commentaires,personne_habilitee,type_cont,pere_superieur,criticite) values ('",Tableau6[[#This Row],[Obligation]],"','",Tableau6[[#This Row],[Référence]],"',1,",Tableau6[[#This Row],[ID Domaine2]],",'",Tableau6[[#This Row],[Libellé détaillé]],"','",Tableau6[[#This Row],[Possible réalisateur]],"',3,",Tableau6[[#This Row],[ID Domaine]],",",Tableau6[[#This Row],[Urgence]],")") -> insert into AOCR_ref_arbo (libelle,reglementation,typologie,pere,commentaires,personne_habilitee,type_cont,pere_superieur,criticite) values ('Installation de stockage de combustible ERP : Vérification Périodique annuelle','Arrêté du 25 juin 1980 portant approbation des dispositions générales du règlement de sécurité contre les risques d''incendie et de panique dans les établissements recevant du public (ERP). Article CH 58;',1,1315,'Les vérifications périodiques doivent avoir lieu tous les ans et concernent : - le stockage des combustibles; Elles ont pour objet de s''assurer : - de l''état apparent d''entretien et de maintenance des installations et appareils ; - des conditions de ventilation des locaux contenant des appareils à combustion ; - des conditions d''évacuation des produits de la combustion ; - du fonctionnement des clapets coupe-feu installés sur les circuits aérauliques ; - de la signalisation des dispositifs de sécurité ; - de la manœuvre des organes de coupure d''alimentation en combustible ; - du fonctionnement des dispositifs asservissant l''alimentation en combustible à un système de sécurité ; - du réglage des détendeurs de gaz ; - de l''étanchéité des canalisations d''alimentation en combustibles liquides ou gazeux, et en fluide frigorigène.','',3,431,4) | AB59: =CONCATENATE("update aocr_ref_arbo set libelle = '",Tableau6[[#This Row],[Obligation]],"', reglementation = '",Tableau6[[#This Row],[Référence]],"', commentaires = '",Tableau6[[#This Row],[Libellé détaillé]],"', personne_habilitee = '",Tableau6[[#This Row],[Possible réalisateur]],"', criticite = ",Tableau6[[#This Row],[Urgence]]," where id = ",Tableau6[[#This Row],[id]]) -> update aocr_ref_arbo set libelle = 'Installation de stockage de combustible ERP : Vérification Périodique annuelle', reglementation = 'Arrêté du 25 juin 1980 portant approbation des dispositions générales du règlement de sécurité contre les risques d''incendie et de panique dans les établissements recevant du public (ERP). Article CH 58;', commentaires = 'Les vérifications périodiques doivent avoir lieu tous les ans et concernent : - le stockage des combustibles; Elles ont pour objet de s''assurer : - de l''état apparent d''entretien et de maintenance des installations et appareils ; - des conditions de ventilation des locaux contenant des appareils à combustion ; - des conditions d''évacuation des produits de la combustion ; - du fonctionnement des clapets coupe-feu installés sur les circuits aérauliques ; - de la signalisation des dispositifs de sécurité ; - de la manœuvre des organes de coupure d''alimentation en combustible ; - du fonctionnement des dispositifs asservissant l''alimentation en combustible à un système de sécurité ; - du réglage des détendeurs de gaz ; - de l''étanchéité des canalisations d''alimentation en combustibles liquides ou gazeux, et en fluide frigorigène.', personne_habilitee = '', criticite = 4 where id = 1320 | AC59: =IF(Tableau6[[#This Row],[Référence]]<>"",CONCATENATE("update aocr_ref_arbo set reglementation = '",Tableau6[[#This Row],[Référence]],"' where id = ",Tableau6[[#This Row],[id]]),"") -> update aocr_ref_arbo set reglementation = 'Arrêté du 25 juin 1980 portant approbation des dispositions générales du règlement de sécurité contre les risques d''incendie et de panique dans les établissements recevant du public (ERP). Article CH 58;' where id = 1320
A60: 1818 | B60: Cuve, bassin, réservoir, citerne | C60: Livret d'entretien | D60: Stockage de produits pétroliers : Livret d''entretien avec les mentions visites, opérations et interventions effectuées. | E60: Les visites, opérations et interventions effectuées en exécution du contrat d''entretien font l''objet de comptes rendus dans un livret d''entretien tenu à jour, établi sous forme d''un registre physique ou électronique suivant le choix du propriétaire. | F60: Arrêté du 1er juillet 2004 fixant les règles techniques et de sécurité applicables au stockage de produits pétroliers dans les lieux non visés par la législation des installations classées ni la réglementation des établissements recevant du public Article 24; | H60: Ecart Détecté | M60: 1 | N60: 1 | O60: 1 | P60: 0 | Q60: =Y56 -> 431 | R60: =Z56 -> 1665 | S60: 1 | T60: 4 | V60: Locataire / Utilisateur | Y60: =VLOOKUP(A64,Feuil1!A:B,2,FALSE) -> 11 | Z60: =VLOOKUP(A64,Feuil1!A:C,3,FALSE) -> 1564 | AA60: =CONCATENATE("insert into AOCR_ref_arbo (libelle,reglementation,typologie,pere,commentaires,personne_habilitee,type_cont,pere_superieur,criticite) values ('",Tableau6[[#This Row],[Obligation]],"','",Tableau6[[#This Row],[Référence]],"',1,",Tableau6[[#This Row],[ID Domaine2]],",'",Tableau6[[#This Row],[Libellé détaillé]],"','",Tableau6[[#This Row],[Possible réalisateur]],"',3,",Tableau6[[#This Row],[ID Domaine]],",",Tableau6[[#This Row],[Urgence]],")") -> insert into AOCR_ref_arbo (libelle,reglementation,typologie,pere,commentaires,personne_habilitee,type_cont,pere_superieur,criticite) values ('Stockage de produits pétroliers : Livret d''entretien avec les mentions visites, opérations et interventions effectuées.','Arrêté du 1er juillet 2004 fixant les règles techniques et de sécurité applicables au stockage de produits pétroliers dans les lieux non visés par la législation des installations classées ni la réglementation des établissements recevant du public Article 24;',1,1665,'Les visites, opérations et interventions effectuées en exécution du contrat d''entretien font l''objet de comptes rendus dans un livret d''entretien tenu à jour, établi sous forme d''un registre physique ou électronique suivant le choix du propriétaire.','',3,431,4) | AB60: =CONCATENATE("update aocr_ref_arbo set libelle = '",Tableau6[[#This Row],[Obligation]],"', reglementation = '",Tableau6[[#This Row],[Référence]],"', commentaires = '",Tableau6[[#This Row],[Libellé détaillé]],"', personne_habilitee = '",Tableau6[[#This Row],[Possible réalisateur]],"', criticite = ",Tableau6[[#This Row],[Urgence]]," where id = ",Tableau6[[#This Row],[id]]) -> update aocr_ref_arbo set libelle = 'Stockage de produits pétroliers : Livret d''entretien avec les mentions visites, opérations et interventions effectuées.', reglementation = 'Arrêté du 1er juillet 2004 fixant les règles techniques et de sécurité applicables au stockage de produits pétroliers dans les lieux non visés par la législation des installations classées ni la réglementation des établissements recevant du public Article 24;', commentaires = 'Les visites, opérations et interventions effectuées en exécution du contrat d''entretien font l''objet de comptes rendus dans un livret d''entretien tenu à jour, établi sous forme d''un registre physique ou électronique suivant le choix du propriétaire.', personne_habilitee = '', criticite = 4 where id = 1818 | AC60: =IF(Tableau6[[#This Row],[Référence]]<>"",CONCATENATE("update aocr_ref_arbo set reglementation = '",Tableau6[[#This Row],[Référence]],"' where id = ",Tableau6[[#This Row],[id]]),"") -> update aocr_ref_arbo set reglementation = 'Arrêté du 1er juillet 2004 fixant les règles techniques et de sécurité applicables au stockage de produits pétroliers dans les lieux non visés par la législation des installations classées ni la réglementation des établissements recevant du public Article 24;' where id = 1818
A61: 821 | B61: Cuve, bassin, réservoir, citerne | C61: Registre de sécurité | D61: Cuves, bassins, réservoirs, citernes : Registre de sécurité Les résultats des vérifications, des contrôles et des maintenances doivent être portés sur le registre sécurité. | F61: Arrêté du 31 janvier 1986 relatif à la protection contre l''incendie des bâtiments d''habitation Article 101; Code de la construction et de l''habitation Article R*123-51; Code de la construction et de l''habitation Article R122-29; Code du travail Article L4711-5; | H61: Ecart Détecté | M61: 1 | N61: 1 | O61: 1 | P61: 0 | Q61: =Y57 -> 431 | R61: =Z57 -> 1661 | S61: 1 | T61: 4 | V61: Locataire / Utilisateur | Y61: =VLOOKUP(A65,Feuil1!A:B,2,FALSE) -> 11 | Z61: =VLOOKUP(A65,Feuil1!A:C,3,FALSE) -> 1563 | AA61: =CONCATENATE("insert into AOCR_ref_arbo (libelle,reglementation,typologie,pere,commentaires,personne_habilitee,type_cont,pere_superieur,criticite) values ('",Tableau6[[#This Row],[Obligation]],"','",Tableau6[[#This Row],[Référence]],"',1,",Tableau6[[#This Row],[ID Domaine2]],",'",Tableau6[[#This Row],[Libellé détaillé]],"','",Tableau6[[#This Row],[Possible réalisateur]],"',3,",Tableau6[[#This Row],[ID Domaine]],",",Tableau6[[#This Row],[Urgence]],")") -> insert into AOCR_ref_arbo (libelle,reglementation,typologie,pere,commentaires,personne_habilitee,type_cont,pere_superieur,criticite) values ('Cuves, bassins, réservoirs, citernes : Registre de sécurité Les résultats des vérifications, des contrôles et des maintenances doivent être portés sur le registre sécurité.','Arrêté du 31 janvier 1986 relatif à la protection contre l''incendie des bâtiments d''habitation Article 101; Code de la construction et de l''habitation Article R*123-51; Code de la construction et de l''habitation Article R122-29; Code du travail Article L4711-5;',1,1661,'','',3,431,4) | AB61: =CONCATENATE("update aocr_ref_arbo set libelle = '",Tableau6[[#This Row],[Obligation]],"', reglementation = '",Tableau6[[#This Row],[Référence]],"', commentaires = '",Tableau6[[#This Row],[Libellé détaillé]],"', personne_habilitee = '",Tableau6[[#This Row],[Possible réalisateur]],"', criticite = ",Tableau6[[#This Row],[Urgence]]," where id = ",Tableau6[[#This Row],[id]]) -> update aocr_ref_arbo set libelle = 'Cuves, bassins, réservoirs, citernes : Registre de sécurité Les résultats des vérifications, des contrôles et des maintenances doivent être portés sur le registre sécurité.', reglementation = 'Arrêté du 31 janvier 1986 relatif à la protection contre l''incendie des bâtiments d''habitation Article 101; Code de la construction et de l''habitation Article R*123-51; Code de la construction et de l''habitation Article R122-29; Code du travail Article L4711-5;', commentaires = '', personne_habilitee = '', criticite = 4 where id = 821 | AC61: =IF(Tableau6[[#This Row],[Référence]]<>"",CONCATENATE("update aocr_ref_arbo set reglementation = '",Tableau6[[#This Row],[Référence]],"' where id = ",Tableau6[[#This Row],[id]]),"") -> update aocr_ref_arbo set reglementation = 'Arrêté du 31 janvier 1986 relatif à la protection contre l''incendie des bâtiments d''habitation Article 101; Code de la construction et de l''habitation Article R*123-51; Code de la construction et de l''habitation Article R122-29; Code du travail Article L4711-5;' where id = 821
A62: 807 | B62: Cuve, bassin, réservoir, citerne | C62: Vérification Périodique 1 an | D62: Cuves, bassins, réservoirs, citernes contenant des produits corrosifs : Vérification Périodique annuelle. | F62: Code du travail Article R4412-25; | H62: Ecart Détecté | M62: 1 | N62: 1 | O62: 1 | P62: 0 | Q62: =Y58 -> 431 | R62: =Z58 -> 1657 | S62: 1 | T62: 4 | V62: Locataire / Utilisateur | Y62: =VLOOKUP(A66,Feuil1!A:B,2,FALSE) -> 11 | Z62: =VLOOKUP(A66,Feuil1!A:C,3,FALSE) -> 1563 | AA62: =CONCATENATE("insert into AOCR_ref_arbo (libelle,reglementation,typologie,pere,commentaires,personne_habilitee,type_cont,pere_superieur,criticite) values ('",Tableau6[[#This Row],[Obligation]],"','",Tableau6[[#This Row],[Référence]],"',1,",Tableau6[[#This Row],[ID Domaine2]],",'",Tableau6[[#This Row],[Libellé détaillé]],"','",Tableau6[[#This Row],[Possible réalisateur]],"',3,",Tableau6[[#This Row],[ID Domaine]],",",Tableau6[[#This Row],[Urgence]],")") -> insert into AOCR_ref_arbo (libelle,reglementation,typologie,pere,commentaires,personne_habilitee,type_cont,pere_superieur,criticite) values ('Cuves, bassins, réservoirs, citernes contenant des produits corrosifs : Vérification Périodique annuelle.','Code du travail Article R4412-25;',1,1657,'','',3,431,4) | AB62: =CONCATENATE("update aocr_ref_arbo set libelle = '",Tableau6[[#This Row],[Obligation]],"', reglementation = '",Tableau6[[#This Row],[Référence]],"', commentaires = '",Tableau6[[#This Row],[Libellé détaillé]],"', personne_habilitee = '",Tableau6[[#This Row],[Possible réalisateur]],"', criticite = ",Tableau6[[#This Row],[Urgence]]," where id = ",Tableau6[[#This Row],[id]]) -> update aocr_ref_arbo set libelle = 'Cuves, bassins, réservoirs, citernes contenant des produits corrosifs : Vérification Périodique annuelle.', reglementation = 'Code du travail Article R4412-25;', commentaires = '', personne_habilitee = '', criticite = 4 where id = 807 | AC62: =IF(Tableau6[[#This Row],[Référence]]<>"",CONCATENATE("update aocr_ref_arbo set reglementation = '",Tableau6[[#This Row],[Référence]],"' where id = ",Tableau6[[#This Row],[id]]),"") -> update aocr_ref_arbo set reglementation = 'Code du travail Article R4412-25;' where id = 807
A63: 1817 | B63: Déchet | C63: Bordereau de Suivi des Déchets Dangereux (BSDD) | D63: Déchet Dangereux : Déchets d''Activités de Soins (DAS) | E63: Les déchets d''activités de soins sont les déchets issus des activités de diagnostic, de suivi et de traitement préventif, curatif ou palliatif, dans les domaines de la médecine humaine et vétérinaire. Les personnes mentionnées à l''article R. 1335-2 du Code de la santé publique peuvent, par une convention qui doit être écrite, confier l''élimination de leurs déchets d''activités de soins et assimilés à une autre personne qui est en mesure d''effectuer ces opérations. Un arrêté des ministres chargés de l''environnement et de la santé fixe les stipulations que doivent obligatoirement comporter ces conventions. | F63: Code de la santé publique Article R1335-4; | H63: Ecart Détecté | M63: 0 | N63: 1 | O63: 1 | P63: 0 | Q63: =Y59 -> 11 | R63: =Z59 -> 1562 | S63: 1 | T63: 4 | V63: Locataire / Utilisateur | Y63: =VLOOKUP(A67,Feuil1!A:B,2,FALSE) -> 11 | Z63: =VLOOKUP(A67,Feuil1!A:C,3,FALSE) -> 1561 | AA63: =CONCATENATE("insert into AOCR_ref_arbo (libelle,reglementation,typologie,pere,commentaires,personne_habilitee,type_cont,pere_superieur,criticite) values ('",Tableau6[[#This Row],[Obligation]],"','",Tableau6[[#This Row],[Référence]],"',1,",Tableau6[[#This Row],[ID Domaine2]],",'",Tableau6[[#This Row],[Libellé détaillé]],"','",Tableau6[[#This Row],[Possible réalisateur]],"',3,",Tableau6[[#This Row],[ID Domaine]],",",Tableau6[[#This Row],[Urgence]],")") -> insert into AOCR_ref_arbo (libelle,reglementation,typologie,pere,commentaires,personne_habilitee,type_cont,pere_superieur,criticite) values ('Déchet Dangereux : Déchets d''Activités de Soins (DAS)','Code de la santé publique Article R1335-4;',1,1562,'Les déchets d''activités de soins sont les déchets issus des activités de diagnostic, de suivi et de traitement préventif, curatif ou palliatif, dans les domaines de la médecine humaine et vétérinaire. Les personnes mentionnées à l''article R. 1335-2 du Code de la santé publique peuvent, par une convention qui doit être écrite, confier l''élimination de leurs déchets d''activités de soins et assimilés à une autre personne qui est en mesure d''effectuer ces opérations. Un arrêté des ministres chargés de l''environnement et de la santé fixe les stipulations que doivent obligatoirement comporter ces conventions.','',3,11,4) | AB63: =CONCATENATE("update aocr_ref_arbo set libelle = '",Tableau6[[#This Row],[Obligation]],"', reglementation = '",Tableau6[[#This Row],[Référence]],"', commentaires = '",Tableau6[[#This Row],[Libellé détaillé]],"', personne_habilitee = '",Tableau6[[#This Row],[Possible réalisateur]],"', criticite = ",Tableau6[[#This Row],[Urgence]]," where id = ",Tableau6[[#This Row],[id]]) -> update aocr_ref_arbo set libelle = 'Déchet Dangereux : Déchets d''Activités de Soins (DAS)', reglementation = 'Code de la santé publique Article R1335-4;', commentaires = 'Les déchets d''activités de soins sont les déchets issus des activités de diagnostic, de suivi et de traitement préventif, curatif ou palliatif, dans les domaines de la médecine humaine et vétérinaire. Les personnes mentionnées à l''article R. 1335-2 du Code de la santé publique peuvent, par une convention qui doit être écrite, confier l''élimination de leurs déchets d''activités de soins et assimilés à une autre personne qui est en mesure d''effectuer ces opérations. Un arrêté des ministres chargés de l''environnement et de la santé fixe les stipulations que doivent obligatoirement comporter ces conventions.', personne_habilitee = '', criticite = 4 where id = 1817 | AC63: =IF(Tableau6[[#This Row],[Référence]]<>"",CONCATENATE("update aocr_ref_arbo set reglementation = '",Tableau6[[#This Row],[Référence]],"' where id = ",Tableau6[[#This Row],[id]]),"") -> update aocr_ref_arbo set reglementation = 'Code de la santé publique Article R1335-4;' where id = 1817
